Workbook

Sheet Imputs
B2: Risk Free Rate | C2: 0.0667
B3: ERP | C3: 0.0523
B6: 1 | C6: {=TRANSPOSE(Table2[#Headers])} -> NSE Ticker Symbol
B7: =B6+1 -> 2 | C7: Company Name
B8: =B7+1 -> 3 | C8: Sector
B9: =B8+1 -> 4 | C9: Industry
B10: =B9+1 -> 5 | C10: Market Capitalisation In(Cr)
B11: =B10+1 -> 6 | C11: Risk Free Rate
B12: =B11+1 -> 7 | C12: ERP
B13: =B12+1 -> 8 | C13: Daily Beta
B14: =B13+1 -> 9 | C14: Weekly Beta
B15: =B14+1 -> 10 | C15: Monthly Beta
B16: =B15+1 -> 11 | C16: Cost of Equity (Daily Beta)
B17: =B16+1 -> 12 | C17: Cost of Equity (Weekly Beta)
B18: =B17+1 -> 13 | C18: Cost of Equity (Monthly Beta)
... B26: =B25+1 -> 21 | C26: Weight of Debt
B27: =B26+1 -> 22 | C27: WACC (Daily) | E27: =MATCH("WACC (Daily)",Table2[#Headers],0) -> 22
B28: =B27+1 -> 23 | C28: WACC (Weekly) | E28: =MATCH("WACC (Daily)",Table2[#Headers],0) -> 22
B29: =B28+1 -> 24 | C29: WACC (Monthly) | E29: =MATCH("WACC (Daily)",Table2[#Headers],0) -> 22
B30: =B29+1 -> 25 | C30: Financial Services
B31: =B30+1 -> 26 | C31: FIRM TYPE
B32: =B31+1 -> 27

Sheet Analysis
B1: WACC OF STOCKS LISTED ON NSE
B2: NSE Ticker Symbol | C2: Company Name | D2: Sector | E2: Industry | F2: Market Capitalisation In(Cr) | G2: Risk Free Rate | H2: ERP | I2: Daily Beta | J2: Weekly Beta | K2: Monthly Beta | L2: Cost of Equity (Daily Beta) | M2: Cost of Equity (Weekly Beta) | N2: Cost of Equity (Monthly Beta) | O2: Interest Coverage Ratio | P2: Default Spread | Q2: Credit Rating (Acc to lookup table) | R2: Cost of Debt | S2: Market Value of Equity | T2: Market Value of Debt | U2: Weight of Equity | V2: Weight of Debt | W2: WACC (Daily) | X2: WACC (Weekly) | Y2: WACC (Monthly) | Z2: Financial Services | AA2: FIRM TYPE
B3: NAGAFERT | C3: =_xlfn.XLOOKUP(B3,stock_analysis[Stock],stock_analysis[Company_Name]) -> Nagarjuna Fertilizers and Chemicals Limited | D3: =_xlfn.XLOOKUP(B3,stock_analysis[Stock],stock_analysis[Sector]) -> Basic Materials | E3: =_xlfn.XLOOKUP($B3,stock_analysis[Stock],stock_analysis[Industry]) -> Agricultural Inputs | F3: =_xlfn.XLOOKUP($B3,stock_analysis[Stock],stock_analysis[Market_Cap_Cr]) -> 262.55053 | G3: =Imputs!$C$2 -> 0.0667 | H3: =Imputs!$C$3 -> 0.0523 | I3: =_xlfn.XLOOKUP($B3,stock_analysis[Stock],stock_analysis[Beta_Daily]) -> 0.42369843 | J3: =_xlfn.XLOOKUP($B3,stock_analysis[Stock],stock_analysis[Beta_Weekly]) -> 0.88594892 | K3: =_xlfn.XLOOKUP($B3,stock_analysis[Stock],stock_analysis[Beta_Monthly]) -> 1.1651509 | L3: =G3+H3*I3 -> 0.088859428 | M3: =J3*H3+G3 -> 0.11303513 | N3: =K3*H3+G3 -> 0.12763739 | O3: =_xlfn.XLOOKUP($B3,stock_analysis[Stock],stock_analysis[Interest_Coverage_Ratio]) -> 189.71151 | P3: {=CHOOSE( _xlfn.IFS(Table2[[#This Row],[Financial Services ]]=TRUE,2,Table2[[#This Row],[FIRM TYPE]]=TRUE,1,Table2[[#This Row],[FIRM TYPE]]=FALSE,3), _xlfn.CHOOSECOLS(_xlfn._xlws.FILTER(Rating1[],(Table2[[#This Row],[Interest Coverage Ratio]]>Rating1[>])*(Table2[[#This Row],[Interest Coverage Ratio]]<Rating1[≤ to])),4), _xlfn.CHOOSECOLS(_xlfn._xlws.FILTER(Rating2[],(Table2[[#This Row],[Interest Coverage Ratio]]>Rating2[greater than])*(Table2[[#This Row],[Interest Coverage Ratio]]<Rating2[≤ to])),4), _xlfn.CHOOSECOLS(_xlfn._xlws.FILTER(Rating3[],(Table2[[#This Row],[Interest Coverage Ratio]]>Rating3[greater than])*(Table2[[#This Row],[Interest Coverage Ratio]]<Rating3[≤ to])),4) )} -> 0.004 | Q3: {=CHOOSE( _xlfn.IFS(Table2[[#This Row],[Financial Services ]]=TRUE,2,Table2[[#This Row],[FIRM TYPE]]=TRUE,1,Table2[[#This Row],[FIRM TYPE]]=FALSE,3), _xlfn.CHOOSECOLS(_xlfn._xlws.FILTER(Rating1[],(Table2[[#This Row],[Interest Coverage Ratio]]>Rating1[>])*(Table2[[#This Row],[Interest Coverage Ratio]]<Rating1[≤ to])),3), _xlfn.CHOOSECOLS(_xlfn._xlws.FILTER(Rating2[],(Table2[[#This Row],[Interest Coverage Ratio]]>Rating2[greater than])*(Table2[[#This Row],[Interest Coverage Ratio]]<Rating2[≤ to])),3), _xlfn.CHOOSECOLS(_xlfn._xlws.FILTER(Rating3[],(Table2[[#This Row],[Interest Coverage Ratio]]>Rating3[greater than])*(Table2[[#This Row],[Interest Coverage Ratio]]<Rating3[≤ to])),3) )} -> Aaa/AAA | R3: =Table2[[#This Row],[Default Spread]]+Table2[[#This Row],[Risk Free Rate]] -> 0.0707 | S3: =_xlfn.XLOOKUP($B3,stock_analysis[Stock],stock_analysis[Market_Cap_Cr]) -> 262.55053 | T3: =_xlfn.XLOOKUP($B3,stock_analysis[Stock],stock_analysis[Total_Debt_Cr]) -> 19.437 | U3: =Table2[[#This Row],[Market Value of Equity]]/(Table2[[#This Row],[Market Value of Equity]]+Table2[[#This Row],[Market Value of Debt]]) -> 0.93107142 | V3: =Table2[[#This Row],[Market Value of Debt]]/(Table2[[#This Row],[Market Value of Equity]]+Table2[[#This Row],[Market Value of Debt]]) -> 0.06892858 | W3: =(Table2[[#This Row],[Cost of Equity (Daily Beta)]]*Table2[[#This Row],[Weight of Equity]])+(Table2[[#This Row],[Cost of Debt]]*Table2[[#This Row],[Weight of Debt]]) -> 0.087607724 | X3: =(Table2[[#This Row],[Cost of Equity (Weekly Beta)]]*Table2[[#This Row],[Weight of Equity]])+(Table2[[#This Row],[Cost of Debt]]*Table2[[#This Row],[Weight of Debt]]) -> 0.11011703 | Y3: =(Table2[[#This Row],[Cost of Equity (Monthly Beta)]]*Table2[[#This Row],[Weight of Equity]])+(Table2[[#This Row],[Cost of Debt]]*Table2[[#This Row],[Weight of Debt]]) -> 0.12371278 | Z3: =IF(Table2[[#This Row],[Sector]]="Financial Services",TRUE,FALSE) -> FALSE | AA3: =IF(Table2[[#This Row],[Market Capitalisation In(Cr)]]>25000,TRUE,FALSE) -> FALSE
B4: OSWALSEEDS | C4: =_xlfn.XLOOKUP(B4,stock_analysis[Stock],stock_analysis[Company_Name]) -> ShreeOswal Seeds And Chemicals Limited | D4: =_xlfn.XLOOKUP(B4,stock_analysis[Stock],stock_analysis[Sector]) -> Basic Materials | E4: =_xlfn.XLOOKUP($B4,stock_analysis[Stock],stock_analysis[Industry]) -> Agricultural Inputs | F4: =_xlfn.XLOOKUP($B4,stock_analysis[Stock],stock_analysis[Market_Cap_Cr]) -> 116.34984 | G4: =Imputs!$C$2 -> 0.0667 | H4: =Imputs!$C$3 -> 0.0523 | I4: =_xlfn.XLOOKUP($B4,stock_analysis[Stock],stock_analysis[Beta_Daily]) -> 0.40441496 | J4: =_xlfn.XLOOKUP($B4,stock_analysis[Stock],stock_analysis[Beta_Weekly]) -> 1.0544635 | K4: =_xlfn.XLOOKUP($B4,stock_analysis[Stock],stock_analysis[Beta_Monthly]) -> -1.0236841 | L4: =G4+H4*I4 -> 0.087850903 | M4: =J4*H4+G4 -> 0.12184844 | N4: =K4*H4+G4 -> 0.01316132 | O4: =_xlfn.XLOOKUP($B4,stock_analysis[Stock],stock_analysis[Interest_Coverage_Ratio]) -> 2.2586428 | P4: {=CHOOSE( _xlfn.IFS(Table2[[#This Row],[Financial Services ]]=TRUE,2,Table2[[#This Row],[FIRM TYPE]]=TRUE,1,Table2[[#This Row],[FIRM TYPE]]=FALSE,3), _xlfn.CHOOSECOLS(_xlfn._xlws.FILTER(Rating1[],(Table2[[#This Row],[Interest Coverage Ratio]]>Rating1[>])*(Table2[[#This Row],[Interest Coverage Ratio]]<Rating1[≤ to])),4), _xlfn.CHOOSECOLS(_xlfn._xlws.FILTER(Rating2[],(Table2[[#This Row],[Interest Coverage Ratio]]>Rating2[greater than])*(Table2[[#This Row],[Interest Coverage Ratio]]<Rating2[≤ to])),4), _xlfn.CHOOSECOLS(_xlfn._xlws.FILTER(Rating3[],(Table2[[#This Row],[Interest Coverage Ratio]]>Rating3[greater than])*(Table2[[#This Row],[Interest Coverage Ratio]]<Rating3[≤ to])),4) )} -> 0.0321 | Q4: {=CHOOSE( _xlfn.IFS(Table2[[#This Row],[Financial Services ]]=TRUE,2,Table2[[#This Row],[FIRM TYPE]]=TRUE,1,Table2[[#This Row],[FIRM TYPE]]=FALSE,3), _xlfn.CHOOSECOLS(_xlfn._xlws.FILTER(Rating1[],(Table2[[#This Row],[Interest Coverage Ratio]]>Rating1[>])*(Table2[[#This Row],[Interest Coverage Ratio]]<Rating1[≤ to])),3), _xlfn.CHOOSECOLS(_xlfn._xlws.FILTER(Rating2[],(Table2[[#This Row],[Interest Coverage Ratio]]>Rating2[greater than])*(Table2[[#This Row],[Interest Coverage Ratio]]<Rating2[≤ to])),3), _xlfn.CHOOSECOLS(_xlfn._xlws.FILTER(Rating3[],(Table2[[#This Row],[Interest Coverage Ratio]]>Rating3[greater than])*(Table2[[#This Row],[Interest Coverage Ratio]]<Rating3[≤ to])),3) )} -> B2/B | R4: =Table2[[#This Row],[Default Spread]]+Table2[[#This Row],[Risk Free Rate]] -> 0.0988 | S4: =_xlfn.XLOOKUP($B4,stock_analysis[Stock],stock_analysis[Market_Cap_Cr]) -> 116.34984 | T4: =_xlfn.XLOOKUP($B4,stock_analysis[Stock],stock_analysis[Total_Debt_Cr]) -> 46.593501 | U4: =Table2[[#This Row],[Market Value of Equity]]/(Table2[[#This Row],[Market Value of Equity]]+Table2[[#This Row],[Market Value of Debt]]) -> 0.7140509 | V4: =Table2[[#This Row],[Market Value of Debt]]/(Table2[[#This Row],[Market Value of Equity]]+Table2[[#This Row],[Market Value of Debt]]) -> 0.2859491 | W4: =(Table2[[#This Row],[Cost of Equity (Daily Beta)]]*Table2[[#This Row],[Weight of Equity]])+(Table2[[#This Row],[Cost of Debt]]*Table2[[#This Row],[Weight of Debt]]) -> 0.090981787 | X4: =(Table2[[#This Row],[Cost of Equity (Weekly Beta)]]*Table2[[#This Row],[Weight of Equity]])+(Table2[[#This Row],[Cost of Debt]]*Table2[[#This Row],[Weight of Debt]]) -> 0.11525776 | Y4: =(Table2[[#This Row],[Cost of Equity (Monthly Beta)]]*Table2[[#This Row],[Weight of Equity]])+(Table2[[#This Row],[Cost of Debt]]*Table2[[#This Row],[Weight of Debt]]) -> 0.037649624 | Z4: =IF(Table2[[#This Row],[Sector]]="Financial Services",TRUE,FALSE) -> FALSE | AA4: =IF(Table2[[#This Row],[Market Capitalisation In(Cr)]]>25000,TRUE,FALSE) -> FALSE
B5: BESTAGRO | C5: =_xlfn.XLOOKUP(B5,stock_analysis[Stock],stock_analysis[Company_Name]) -> Best Agrolife Limited | D5: =_xlfn.XLOOKUP(B5,stock_analysis[Stock],stock_analysis[Sector]) -> Basic Materials | E5: =_xlfn.XLOOKUP($B5,stock_analysis[Stock],stock_analysis[Industry]) -> Agricultural Inputs | F5: =_xlfn.XLOOKUP($B5,stock_analysis[Stock],stock_analysis[Market_Cap_Cr]) -> 550.5919 | G5: =Imputs!$C$2 -> 0.0667 | H5: =Imputs!$C$3 -> 0.0523 | I5: =_xlfn.XLOOKUP($B5,stock_analysis[Stock],stock_analysis[Beta_Daily]) -> 0.43568159 | J5: =_xlfn.XLOOKUP($B5,stock_analysis[Stock],stock_analysis[Beta_Weekly]) -> 0.77127596 | K5: =_xlfn.XLOOKUP($B5,stock_analysis[Stock],stock_analysis[Beta_Monthly]) -> 0.5328715 | L5: =G5+H5*I5 -> 0.089486147 | M5: =J5*H5+G5 -> 0.10703773 | N5: =K5*H5+G5 -> 0.094569179 | O5: =_xlfn.XLOOKUP($B5,stock_analysis[Stock],stock_analysis[Interest_Coverage_Ratio]) -> 2.6000332 | P5: {=CHOOSE( _xlfn.IFS(Table2[[#This Row],[Financial Services ]]=TRUE,2,Table2[[#This Row],[FIRM TYPE]]=TRUE,1,Table2[[#This Row],[FIRM TYPE]]=FALSE,3), _xlfn.CHOOSECOLS(_xlfn._xlws.FILTER(Rating1[],(Table2[[#This Row],[Interest Coverage Ratio]]>Rating1[>])*(Table2[[#This Row],[Interest Coverage Ratio]]<Rating1[≤ to])),4), _xlfn.CHOOSECOLS(_xlfn._xlws.FILTER(Rating2[],(Table2[[#This Row],[Interest Coverage Ratio]]>Rating2[greater than])*(Table2[[#This Row],[Interest Coverage Ratio]]<Rating2[≤ to])),4), _xlfn.CHOOSECOLS(_xlfn._xlws.FILTER(Rating3[],(Table2[[#This Row],[Interest Coverage Ratio]]>Rating3[greater than])*(Table2[[#This Row],[Interest Coverage Ratio]]<Rating3[≤ to])),4) )} -> 0.0275 | Q5: {=CHOOSE( _xlfn.IFS(Table2[[#This Row],[Financial Services ]]=TRUE,2,Table2[[#This Row],[FIRM TYPE]]=TRUE,1,Table2[[#This Row],[FIRM TYPE]]=FALSE,3), _xlfn.CHOOSECOLS(_xlfn._xlws.FILTER(Rating1[],(Table2[[#This Row],[Interest Coverage Ratio]]>Rating1[>])*(Table2[[#This Row],[Interest Coverage Ratio]]<Rating1[≤ to])),3), _xlfn.CHOOSECOLS(_xlfn._xlws.FILTER(Rating2[],(Table2[[#This Row],[Interest Coverage Ratio]]>Rating2[greater than])*(Table2[[#This Row],[Interest Coverage Ratio]]<Rating2[≤ to])),3), _xlfn.CHOOSECOLS(_xlfn._xlws.FILTER(Rating3[],(Table2[[#This Row],[Interest Coverage Ratio]]>Rating3[greater than])*(Table2[[#This Row],[Interest Coverage Ratio]]<Rating3[≤ to])),3) )} -> B1/B+ | R5: =Table2[[#This Row],[Default Spread]]+Table2[[#This Row],[Risk Free Rate]] -> 0.0942 | S5: =_xlfn.XLOOKUP($B5,stock_analysis[Stock],stock_analysis[Market_Cap_Cr]) -> 550.5919 | T5: =_xlfn.XLOOKUP($B5,stock_analysis[Stock],stock_analysis[Total_Debt_Cr]) -> 435.68 | U5: =Table2[[#This Row],[Market Value of Equity]]/(Table2[[#This Row],[Market Value of Equity]]+Table2[[#This Row],[Market Value of Debt]]) -> 0.55825569 | V5: =Table2[[#This Row],[Market Value of Debt]]/(Table2[[#This Row],[Market Value of Equity]]+Table2[[#This Row],[Market Value of Debt]]) -> 0.44174431 | W5: =(Table2[[#This Row],[Cost of Equity (Daily Beta)]]*Table2[[#This Row],[Weight of Equity]])+(Table2[[#This Row],[Cost of Debt]]*Table2[[#This Row],[Weight of Debt]]) -> 0.091568465 | X5: =(Table2[[#This Row],[Cost of Equity (Weekly Beta)]]*Table2[[#This Row],[Weight of Equity]])+(Table2[[#This Row],[Cost of Debt]]*Table2[[#This Row],[Weight of Debt]]) -> 0.10136674 | Y5: =(Table2[[#This Row],[Cost of Equity (Monthly Beta)]]*Table2[[#This Row],[Weight of Equity]])+(Table2[[#This Row],[Cost of Debt]]*Table2[[#This Row],[Weight of Debt]]) -> 0.094406097 | Z5: =IF(Table2[[#This Row],[Sector]]="Financial Services",TRUE,FALSE) -> FALSE | AA5: =IF(Table2[[#This Row],[Market Capitalisation In(Cr)]]>25000,TRUE,FALSE) -> FALSE
B6: BHAGCHEM | C6: =_xlfn.XLOOKUP(B6,stock_analysis[Stock],stock_analysis[Company_Name]) -> Bhagiradha Chemicals & Industries Limited | D6: =_xlfn.XLOOKUP(B6,stock_analysis[Stock],stock_analysis[Sector]) -> Basic Materials | E6: =_xlfn.XLOOKUP($B6,stock_analysis[Stock],stock_analysis[Industry]) -> Agricultural Inputs | F6: =_xlfn.XLOOKUP($B6,stock_analysis[Stock],stock_analysis[Market_Cap_Cr]) -> 2587.8528 | G6: =Imputs!$C$2 -> 0.0667 | H6: =Imputs!$C$3 -> 0.0523 | I6: =_xlfn.XLOOKUP($B6,stock_analysis[Stock],stock_analysis[Beta_Daily]) -> 0.50418825 | J6: =_xlfn.XLOOKUP($B6,stock_analysis[Stock],stock_analysis[Beta_Weekly]) -> 1.0261575 | K6: =_xlfn.XLOOKUP($B6,stock_analysis[Stock],stock_analysis[Beta_Monthly]) -> 1.1118535 | L6: =G6+H6*I6 -> 0.093069045 | M6: =J6*H6+G6 -> 0.12036804 | N6: =K6*H6+G6 -> 0.12484994 | O6: =_xlfn.XLOOKUP($B6,stock_analysis[Stock],stock_analysis[Interest_Coverage_Ratio]) -> 5.9107494 | P6: {=CHOOSE( _xlfn.IFS(Table2[[#This Row],[Financial Services ]]=TRUE,2,Table2[[#This Row],[FIRM TYPE]]=TRUE,1,Table2[[#This Row],[FIRM TYPE]]=FALSE,3), _xlfn.CHOOSECOLS(_xlfn._xlws.FILTER(Rating1[],(Table2[[#This Row],[Interest Coverage Ratio]]>Rating1[>])*(Table2[[#This Row],[Interest Coverage Ratio]]<Rating1[≤ to])),4), _xlfn.CHOOSECOLS(_xlfn._xlws.FILTER(Rating2[],(Table2[[#This Row],[Interest Coverage Ratio]]>Rating2[greater than])*(Table2[[#This Row],[Interest Coverage Ratio]]<Rating2[≤ to])),4), _xlfn.CHOOSECOLS(_xlfn._xlws.FILTER(Rating3[],(Table2[[#This Row],[Interest Coverage Ratio]]>Rating3[greater than])*(Table2[[#This Row],[Interest Coverage Ratio]]<Rating3[≤ to])),4) )} -> 0.0089 | Q6: {=CHOOSE( _xlfn.IFS(Table2[[#This Row],[Financial Services ]]=TRUE,2,Table2[[#This Row],[FIRM TYPE]]=TRUE,1,Table2[[#This Row],[FIRM TYPE]]=FALSE,3), _xlfn.CHOOSECOLS(_xlfn._xlws.FILTER(Rating1[],(Table2[[#This Row],[Interest Coverage Ratio]]>Rating1[>])*(Table2[[#This Row],[Interest Coverage Ratio]]<Rating1[≤ to])),3), _xlfn.CHOOSECOLS(_xlfn._xlws.FILTER(Rating2[],(Table2[[#This Row],[Interest Coverage Ratio]]>Rating2[greater than])*(Table2[[#This Row],[Interest Coverage Ratio]]<Rating2[≤ to])),3), _xlfn.CHOOSECOLS(_xlfn._xlws.FILTER(Rating3[],(Table2[[#This Row],[Interest Coverage Ratio]]>Rating3[greater than])*(Table2[[#This Row],[Interest Coverage Ratio]]<Rating3[≤ to])),3) )} -> A3/A- | R6: =Table2[[#This Row],[Default Spread]]+Table2[[#This Row],[Risk Free Rate]] -> 0.0756 | S6: =_xlfn.XLOOKUP($B6,stock_analysis[Stock],stock_analysis[Market_Cap_Cr]) -> 2587.8528 | T6: =_xlfn.XLOOKUP($B6,stock_analysis[Stock],stock_analysis[Total_Debt_Cr]) -> 188.8293 | U6: =Table2[[#This Row],[Market Value of Equity]]/(Table2[[#This Row],[Market Value of Equity]]+Table2[[#This Row],[Market Value of Debt]]) -> 0.93199463 | V6: =Table2[[#This Row],[Market Value of Debt]]/(Table2[[#This Row],[Market Value of Equity]]+Table2[[#This Row],[Market Value of Debt]]) -> 0.068005372 | W6: =(Table2[[#This Row],[Cost of Equity (Daily Beta)]]*Table2[[#This Row],[Weight of Equity]])+(Table2[[#This Row],[Cost of Debt]]*Table2[[#This Row],[Weight of Debt]]) -> 0.091881056 | X6: =(Table2[[#This Row],[Cost of Equity (Weekly Beta)]]*Table2[[#This Row],[Weight of Equity]])+(Table2[[#This Row],[Cost of Debt]]*Table2[[#This Row],[Weight of Debt]]) -> 0.11732357 | Y6: =(Table2[[#This Row],[Cost of Equity (Monthly Beta)]]*Table2[[#This Row],[Weight of Equity]])+(Table2[[#This Row],[Cost of Debt]]*Table2[[#This Row],[Weight of Debt]]) -> 0.12150068 | Z6: =IF(Table2[[#This Row],[Sector]]="Financial Services",TRUE,FALSE) -> FALSE | AA6: =IF(Table2[[#This Row],[Market Capitalisation In(Cr)]]>25000,TRUE,FALSE) -> FALSE
B7: BAYERCROP | C7: =_xlfn.XLOOKUP(B7,stock_analysis[Stock],stock_analysis[Company_Name]) -> Bayer Cropscience Limited | D7: =_xlfn.XLOOKUP(B7,stock_analysis[Stock],stock_analysis[Sector]) -> Basic Materials | E7: =_xlfn.XLOOKUP($B7,stock_analysis[Stock],stock_analysis[Industry]) -> Agricultural Inputs | F7: =_xlfn.XLOOKUP($B7,stock_analysis[Stock],stock_analysis[Market_Cap_Cr]) -> 20255.257 | G7: =Imputs!$C$2 -> 0.0667 | H7: =Imputs!$C$3 -> 0.0523 | I7: =_xlfn.XLOOKUP($B7,stock_analysis[Stock],stock_analysis[Beta_Daily]) -> 0.50725538 | J7: =_xlfn.XLOOKUP($B7,stock_analysis[Stock],stock_analysis[Beta_Weekly]) -> 1.1368508 | K7: =_xlfn.XLOOKUP($B7,stock_analysis[Stock],stock_analysis[Beta_Monthly]) -> 0.88865631 | L7: =G7+H7*I7 -> 0.093229457 | M7: =J7*H7+G7 -> 0.1261573 | N7: =K7*H7+G7 -> 0.11317673 | O7: =_xlfn.XLOOKUP($B7,stock_analysis[Stock],stock_analysis[Interest_Coverage_Ratio]) -> 42.611765 | P7: {=CHOOSE( _xlfn.IFS(Table2[[#This Row],[Financial Services ]]=TRUE,2,Table2[[#This Row],[FIRM TYPE]]=TRUE,1,Table2[[#This Row],[FIRM TYPE]]=FALSE,3), _xlfn.CHOOSECOLS(_xlfn._xlws.FILTER(Rating1[],(Table2[[#This Row],[Interest Coverage Ratio]]>Rating1[>])*(Table2[[#This Row],[Interest Coverage Ratio]]<Rating1[≤ to])),4), _xlfn.CHOOSECOLS(_xlfn._xlws.FILTER(Rating2[],(Table2[[#This Row],[Interest Coverage Ratio]]>Rating2[greater than])*(Table2[[#This Row],[Interest Coverage Ratio]]<Rating2[≤ to])),4), _xlfn.CHOOSECOLS(_xlfn._xlws.FILTER(Rating3[],(Table2[[#This Row],[Interest Coverage Ratio]]>Rating3[greater than])*(Table2[[#This Row],[Interest Coverage Ratio]]<Rating3[≤ to])),4) )} -> 0.004 | Q7: {=CHOOSE( _xlfn.IFS(Table2[[#This Row],[Financial Services ]]=TRUE,2,Table2[[#This Row],[FIRM TYPE]]=TRUE,1,Table2[[#This Row],[FIRM TYPE]]=FALSE,3), _xlfn.CHOOSECOLS(_xlfn._xlws.FILTER(Rating1[],(Table2[[#This Row],[Interest Coverage Ratio]]>Rating1[>])*(Table2[[#This Row],[Interest Coverage Ratio]]<Rating1[≤ to])),3), _xlfn.CHOOSECOLS(_xlfn._xlws.FILTER(Rating2[],(Table2[[#This Row],[Interest Coverage Ratio]]>Rating2[greater than])*(Table2[[#This Row],[Interest Coverage Ratio]]<Rating2[≤ to])),3), _xlfn.CHOOSECOLS(_xlfn._xlws.FILTER(Rating3[],(Table2[[#This Row],[Interest Coverage Ratio]]>Rating3[greater than])*(Table2[[#This Row],[Interest Coverage Ratio]]<Rating3[≤ to])),3) )} -> Aaa/AAA | R7: =Table2[[#This Row],[Default Spread]]+Table2[[#This Row],[Risk Free Rate]] -> 0.0707 | S7: =_xlfn.XLOOKUP($B7,stock_analysis[Stock],stock_analysis[Market_Cap_Cr]) -> 20255.257 | T7: =_xlfn.XLOOKUP($B7,stock_analysis[Stock],stock_analysis[Total_Debt_Cr]) -> 102 | U7: =Table2[[#This Row],[Market Value of Equity]]/(Table2[[#This Row],[Market Value of Equity]]+Table2[[#This Row],[Market Value of Debt]]) -> 0.9949895 | V7: =Table2[[#This Row],[Market Value of Debt]]/(Table2[[#This Row],[Market Value of Equity]]+Table2[[#This Row],[Market Value of Debt]]) -> 0.0050104981 | W7: =(Table2[[#This Row],[Cost of Equity (Daily Beta)]]*Table2[[#This Row],[Weight of Equity]])+(Table2[[#This Row],[Cost of Debt]]*Table2[[#This Row],[Weight of Debt]]) -> 0.093116573 | X7: =(Table2[[#This Row],[Cost of Equity (Weekly Beta)]]*Table2[[#This Row],[Weight of Equity]])+(Table2[[#This Row],[Cost of Debt]]*Table2[[#This Row],[Weight of Debt]]) -> 0.12587943 | Y7: =(Table2[[#This Row],[Cost of Equity (Monthly Beta)]]*Table2[[#This Row],[Weight of Equity]])+(Table2[[#This Row],[Cost of Debt]]*Table2[[#This Row],[Weight of Debt]]) -> 0.1129639 | Z7: =IF(Table2[[#This Row],[Sector]]="Financial Services",TRUE,FALSE) -> FALSE | AA7: =IF(Table2[[#This Row],[Market Capitalisation In(Cr)]]>25000,TRUE,FALSE) -> FALSE
B8: INSECTICID | C8: =_xlfn.XLOOKUP(B8,stock_analysis[Stock],stock_analysis[Company_Name]) -> Insecticides (India) Limited | D8: =_xlfn.XLOOKUP(B8,stock_analysis[Stock],stock_analysis[Sector]) -> Basic Materials | E8: =_xlfn.XLOOKUP($B8,stock_analysis[Stock],stock_analysis[Industry]) -> Agricultural Inputs | F8: =_xlfn.XLOOKUP($B8,stock_analysis[Stock],stock_analysis[Market_Cap_Cr]) -> 1776.8593 | G8: =Imputs!$C$2 -> 0.0667 | H8: =Imputs!$C$3 -> 0.0523 | I8: =_xlfn.XLOOKUP($B8,stock_analysis[Stock],stock_analysis[Beta_Daily]) -> 0.6201922 | J8: =_xlfn.XLOOKUP($B8,stock_analysis[Stock],stock_analysis[Beta_Weekly]) -> 1.2702471 | K8: =_xlfn.XLOOKUP($B8,stock_analysis[Stock],stock_analysis[Beta_Monthly]) -> 1.0892812 | L8: =G8+H8*I8 -> 0.099136052 | M8: =J8*H8+G8 -> 0.13313392 | N8: =K8*H8+G8 -> 0.12366941 | O8: =_xlfn.XLOOKUP($B8,stock_analysis[Stock],stock_analysis[Interest_Coverage_Ratio]) -> 40.55867 | P8: {=CHOOSE( _xlfn.IFS(Table2[[#This Row],[Financial Services ]]=TRUE,2,Table2[[#This Row],[FIRM TYPE]]=TRUE,1,Table2[[#This Row],[FIRM TYPE]]=FALSE,3), _xlfn.CHOOSECOLS(_xlfn._xlws.FILTER(Rating1[],(Table2[[#This Row],[Interest Coverage Ratio]]>Rating1[>])*(Table2[[#This Row],[Interest Coverage Ratio]]<Rating1[≤ to])),4), _xlfn.CHOOSECOLS(_xlfn._xlws.FILTER(Rating2[],(Table2[[#This Row],[Interest Coverage Ratio]]>Rating2[greater than])*(Table2[[#This Row],[Interest Coverage Ratio]]<Rating2[≤ to])),4), _xlfn.CHOOSECOLS(_xlfn._xlws.FILTER(Rating3[],(Table2[[#This Row],[Interest Coverage Ratio]]>Rating3[greater than])*(Table2[[#This Row],[Interest Coverage Ratio]]<Rating3[≤ to])),4) )} -> 0.004 | Q8: {=CHOOSE( _xlfn.IFS(Table2[[#This Row],[Financial Services ]]=TRUE,2,Table2[[#This Row],[FIRM TYPE]]=TRUE,1,Table2[[#This Row],[FIRM TYPE]]=FALSE,3), _xlfn.CHOOSECOLS(_xlfn._xlws.FILTER(Rating1[],(Table2[[#This Row],[Interest Coverage Ratio]]>Rating1[>])*(Table2[[#This Row],[Interest Coverage Ratio]]<Rating1[≤ to])),3), _xlfn.CHOOSECOLS(_xlfn._xlws.FILTER(Rating2[],(Table2[[#This Row],[Interest Coverage Ratio]]>Rating2[greater than])*(Table2[[#This Row],[Interest Coverage Ratio]]<Rating2[≤ to])),3), _xlfn.CHOOSECOLS(_xlfn._xlws.FILTER(Rating3[],(Table2[[#This Row],[Interest Coverage Ratio]]>Rating3[greater than])*(Table2[[#This Row],[Interest Coverage Ratio]]<Rating3[≤ to])),3) )} -> Aaa/AAA | R8: =Table2[[#This Row],[Default Spread]]+Table2[[#This Row],[Risk Free Rate]] -> 0.0707 | S8: =_xlfn.XLOOKUP($B8,stock_analysis[Stock],stock_analysis[Market_Cap_Cr]) -> 1776.8593 | T8: =_xlfn.XLOOKUP($B8,stock_analysis[Stock],stock_analysis[Total_Debt_Cr]) -> 246.44539 | U8: =Table2[[#This Row],[Market Value of Equity]]/(Table2[[#This Row],[Market Value of Equity]]+Table2[[#This Row],[Market Value of Debt]]) -> 0.8781966 | V8: =Table2[[#This Row],[Market Value of Debt]]/(Table2[[#This Row],[Market Value of Equity]]+Table2[[#This Row],[Market Value of Debt]]) -> 0.1218034 | W8: =(Table2[[#This Row],[Cost of Equity (Daily Beta)]]*Table2[[#This Row],[Weight of Equity]])+(Table2[[#This Row],[Cost of Debt]]*Table2[[#This Row],[Weight of Debt]]) -> 0.095672444 | X8: =(Table2[[#This Row],[Cost of Equity (Weekly Beta)]]*Table2[[#This Row],[Weight of Equity]])+(Table2[[#This Row],[Cost of Debt]]*Table2[[#This Row],[Weight of Debt]]) -> 0.12552926 | Y8: =(Table2[[#This Row],[Cost of Equity (Monthly Beta)]]*Table2[[#This Row],[Weight of Equity]])+(Table2[[#This Row],[Cost of Debt]]*Table2[[#This Row],[Weight of Debt]]) -> 0.11721755 | Z8: =IF(Table2[[#This Row],[Sector]]="Financial Services",TRUE,FALSE) -> FALSE | AA8: =IF(Table2[[#This Row],[Market Capitalisation In(Cr)]]>25000,TRUE,FALSE) -> FALSE
B9: SIKKO | C9: =_xlfn.XLOOKUP(B9,stock_analysis[Stock],stock_analysis[Company_Name]) -> Sikko Industries Limited | D9: =_xlfn.XLOOKUP(B9,stock_analysis[Stock],stock_analysis[Sector]) -> Basic Materials | E9: =_xlfn.XLOOKUP($B9,stock_analysis[Stock],stock_analysis[Industry]) -> Agricultural Inputs | F9: =_xlfn.XLOOKUP($B9,stock_analysis[Stock],stock_analysis[Market_Cap_Cr]) -> 196.56 | G9: =Imputs!$C$2 -> 0.0667 | H9: =Imputs!$C$3 -> 0.0523 | I9: =_xlfn.XLOOKUP($B9,stock_analysis[Stock],stock_analysis[Beta_Daily]) -> 0.63903525 | J9: =_xlfn.XLOOKUP($B9,stock_analysis[Stock],stock_analysis[Beta_Weekly]) -> 1.3034265 | K9: =_xlfn.XLOOKUP($B9,stock_analysis[Stock],stock_analysis[Beta_Monthly]) -> 1.9895812 | L9: =G9+H9*I9 -> 0.10012154 | M9: =J9*H9+G9 -> 0.13486921 | N9: =K9*H9+G9 -> 0.1707551 | O9: =_xlfn.XLOOKUP($B9,stock_analysis[Stock],stock_analysis[Interest_Coverage_Ratio]) -> 16.921879 | P9: {=CHOOSE( _xlfn.IFS(Table2[[#This Row],[Financial Services ]]=TRUE,2,Table2[[#This Row],[FIRM TYPE]]=TRUE,1,Table2[[#This Row],[FIRM TYPE]]=FALSE,3), _xlfn.CHOOSECOLS(_xlfn._xlws.FILTER(Rating1[],(Table2[[#This Row],[Interest Coverage Ratio]]>Rating1[>])*(Table2[[#This Row],[Interest Coverage Ratio]]<Rating1[≤ to])),4), _xlfn.CHOOSECOLS(_xlfn._xlws.FILTER(Rating2[],(Table2[[#This Row],[Interest Coverage Ratio]]>Rating2[greater than])*(Table2[[#This Row],[Interest Coverage Ratio]]<Rating2[≤ to])),4), _xlfn.CHOOSECOLS(_xlfn._xlws.FILTER(Rating3[],(Table2[[#This Row],[Interest Coverage Ratio]]>Rating3[greater than])*(Table2[[#This Row],[Interest Coverage Ratio]]<Rating3[≤ to])),4) )} -> 0.004 | Q9: {=CHOOSE( _xlfn.IFS(Table2[[#This Row],[Financial Services ]]=TRUE,2,Table2[[#This Row],[FIRM TYPE]]=TRUE,1,Table2[[#This Row],[FIRM TYPE]]=FALSE,3), _xlfn.CHOOSECOLS(_xlfn._xlws.FILTER(Rating1[],(Table2[[#This Row],[Interest Coverage Ratio]]>Rating1[>])*(Table2[[#This Row],[Interest Coverage Ratio]]<Rating1[≤ to])),3), _xlfn.CHOOSECOLS(_xlfn._xlws.FILTER(Rating2[],(Table2[[#This Row],[Interest Coverage Ratio]]>Rating2[greater than])*(Table2[[#This Row],[Interest Coverage Ratio]]<Rating2[≤ to])),3), _xlfn.CHOOSECOLS(_xlfn._xlws.FILTER(Rating3[],(Table2[[#This Row],[Interest Coverage Ratio]]>Rating3[greater than])*(Table2[[#This Row],[Interest Coverage Ratio]]<Rating3[≤ to])),3) )} -> Aaa/AAA | R9: =Table2[[#This Row],[Default Spread]]+Table2[[#This Row],[Risk Free Rate]] -> 0.0707 | S9: =_xlfn.XLOOKUP($B9,stock_analysis[Stock],stock_analysis[Market_Cap_Cr]) -> 196.56 | T9: =_xlfn.XLOOKUP($B9,stock_analysis[Stock],stock_analysis[Total_Debt_Cr]) -> 12.2905 | U9: =Table2[[#This Row],[Market Value of Equity]]/(Table2[[#This Row],[Market Value of Equity]]+Table2[[#This Row],[Market Value of Debt]]) -> 0.94115169 | V9: =Table2[[#This Row],[Market Value of Debt]]/(Table2[[#This Row],[Market Value of Equity]]+Table2[[#This Row],[Market Value of Debt]]) -> 0.058848315 | W9: =(Table2[[#This Row],[Cost of Equity (Daily Beta)]]*Table2[[#This Row],[Weight of Equity]])+(Table2[[#This Row],[Cost of Debt]]*Table2[[#This Row],[Weight of Debt]]) -> 0.098390135 | X9: =(Table2[[#This Row],[Cost of Equity (Weekly Beta)]]*Table2[[#This Row],[Weight of Equity]])+(Table2[[#This Row],[Cost of Debt]]*Table2[[#This Row],[Weight of Debt]]) -> 0.13109296 | Y9: =(Table2[[#This Row],[Cost of Equity (Monthly Beta)]]*Table2[[#This Row],[Weight of Equity]])+(Table2[[#This Row],[Cost of Debt]]*Table2[[#This Row],[Weight of Debt]]) -> 0.16486702 | Z9: =IF(Table2[[#This Row],[Sector]]="Financial Services",TRUE,FALSE) -> FALSE | AA9: =IF(Table2[[#This Row],[Market Capitalisation In(Cr)]]>25000,TRUE,FALSE) -> FALSE
B10: DHARMAJ | C10: =_xlfn.XLOOKUP(B10,stock_analysis[Stock],stock_analysis[Company_Name]) -> Dharmaj Crop Guard Limited | D10: =_xlfn.XLOOKUP(B10,stock_analysis[Stock],stock_analysis[Sector]) -> Basic Materials | E10: =_xlfn.XLOOKUP($B10,stock_analysis[Stock],stock_analysis[Industry]) -> Agricultural Inputs | F10: =_xlfn.XLOOKUP($B10,stock_analysis[Stock],stock_analysis[Market_Cap_Cr]) -> 812.45317 | G10: =Imputs!$C$2 -> 0.0667 | H10: =Imputs!$C$3 -> 0.0523 | I10: =_xlfn.XLOOKUP($B10,stock_analysis[Stock],stock_analysis[Beta_Daily]) -> 0.71048324 | J10: =_xlfn.XLOOKUP($B10,stock_analysis[Stock],stock_analysis[Beta_Weekly]) -> 1.1768834 | K10: =_xlfn.XLOOKUP($B10,stock_analysis[Stock],stock_analysis[Beta_Monthly]) -> 1.0270976 | L10: =G10+H10*I10 -> 0.10385827 | M10: =J10*H10+G10 -> 0.128251 | N10: =K10*H10+G10 -> 0.1204172 | O10: =_xlfn.XLOOKUP($B10,stock_analysis[Stock],stock_analysis[Interest_Coverage_Ratio]) -> 5.1574596 | P10: {=CHOOSE( _xlfn.IFS(Table2[[#This Row],[Financial Services ]]=TRUE,2,Table2[[#This Row],[FIRM TYPE]]=TRUE,1,Table2[[#This Row],[FIRM TYPE]]=FALSE,3), _xlfn.CHOOSECOLS(_xlfn._xlws.FILTER(Rating1[],(Table2[[#This Row],[Interest Coverage Ratio]]>Rating1[>])*(Table2[[#This Row],[Interest Coverage Ratio]]<Rating1[≤ to])),4), _xlfn.CHOOSECOLS(_xlfn._xlws.FILTER(Rating2[],(Table2[[#This Row],[Interest Coverage Ratio]]>Rating2[greater than])*(Table2[[#This Row],[Interest Coverage Ratio]]<Rating2[≤ to])),4), _xlfn.CHOOSECOLS(_xlfn._xlws.FILTER(Rating3[],(Table2[[#This Row],[Interest Coverage Ratio]]>Rating3[greater than])*(Table2[[#This Row],[Interest Coverage Ratio]]<Rating3[≤ to])),4) )} -> 0.0089 | Q10: {=CHOOSE( _xlfn.IFS(Table2[[#This Row],[Financial Services ]]=TRUE,2,Table2[[#This Row],[FIRM TYPE]]=TRUE,1,Table2[[#This Row],[FIRM TYPE]]=FALSE,3), _xlfn.CHOOSECOLS(_xlfn._xlws.FILTER(Rating1[],(Table2[[#This Row],[Interest Coverage Ratio]]>Rating1[>])*(Table2[[#This Row],[Interest Coverage Ratio]]<Rating1[≤ to])),3), _xlfn.CHOOSECOLS(_xlfn._xlws.FILTER(Rating2[],(Table2[[#This Row],[Interest Coverage Ratio]]>Rating2[greater than])*(Table2[[#This Row],[Interest Coverage Ratio]]<Rating2[≤ to])),3), _xlfn.CHOOSECOLS(_xlfn._xlws.FILTER(Rating3[],(Table2[[#This Row],[Interest Coverage Ratio]]>Rating3[greater than])*(Table2[[#This Row],[Interest Coverage Ratio]]<Rating3[≤ to])),3) )} -> A3/A- | R10: =Table2[[#This Row],[Default Spread]]+Table2[[#This Row],[Risk Free Rate]] -> 0.0756 | S10: =_xlfn.XLOOKUP($B10,stock_analysis[Stock],stock_analysis[Market_Cap_Cr]) -> 812.45317 | T10: =_xlfn.XLOOKUP($B10,stock_analysis[Stock],stock_analysis[Total_Debt_Cr]) -> 138.875 | U10: =Table2[[#This Row],[Market Value of Equity]]/(Table2[[#This Row],[Market Value of Equity]]+Table2[[#This Row],[Market Value of Debt]]) -> 0.85401988 | V10: =Table2[[#This Row],[Market Value of Debt]]/(Table2[[#This Row],[Market Value of Equity]]+Table2[[#This Row],[Market Value of Debt]]) -> 0.14598012 | W10: =(Table2[[#This Row],[Cost of Equity (Daily Beta)]]*Table2[[#This Row],[Weight of Equity]])+(Table2[[#This Row],[Cost of Debt]]*Table2[[#This Row],[Weight of Debt]]) -> 0.099733128 | X10: =(Table2[[#This Row],[Cost of Equity (Weekly Beta)]]*Table2[[#This Row],[Weight of Equity]])+(Table2[[#This Row],[Cost of Debt]]*Table2[[#This Row],[Weight of Debt]]) -> 0.120565 | Y10: =(Table2[[#This Row],[Cost of Equity (Monthly Beta)]]*Table2[[#This Row],[Weight of Equity]])+(Table2[[#This Row],[Cost of Debt]]*Table2[[#This Row],[Weight of Debt]]) -> 0.11387478 | Z10: =IF(Table2[[#This Row],[Sector]]="Financial Services",TRUE,FALSE) -> FALSE | AA10: =IF(Table2[[#This Row],[Market Capitalisation In(Cr)]]>25000,TRUE,FALSE) -> FALSE
B11: INDOUS | C11: =_xlfn.XLOOKUP(B11,stock_analysis[Stock],stock_analysis[Company_Name]) -> Indo Us Biotech Limited | D11: =_xlfn.XLOOKUP(B11,stock_analysis[Stock],stock_analysis[Sector]) -> Basic Materials | E11: =_xlfn.XLOOKUP($B11,stock_analysis[Stock],stock_analysis[Industry]) -> Agricultural Inputs | F11: =_xlfn.XLOOKUP($B11,stock_analysis[Stock],stock_analysis[Market_Cap_Cr]) -> 276.40061 | G11: =Imputs!$C$2 -> 0.0667 | H11: =Imputs!$C$3 -> 0.0523 | I11: =_xlfn.XLOOKUP($B11,stock_analysis[Stock],stock_analysis[Beta_Daily]) -> 0.69794506 | J11: =_xlfn.XLOOKUP($B11,stock_analysis[Stock],stock_analysis[Beta_Weekly]) -> 1.1978305 | K11: =_xlfn.XLOOKUP($B11,stock_analysis[Stock],stock_analysis[Beta_Monthly]) -> -0.67415215 | L11: =G11+H11*I11 -> 0.10320253 | M11: =J11*H11+G11 -> 0.12934653 | N11: =K11*H11+G11 -> 0.031441843 | O11: =_xlfn.XLOOKUP($B11,stock_analysis[Stock],stock_analysis[Interest_Coverage_Ratio]) -> 12.510954 | P11: {=CHOOSE( _xlfn.IFS(Table2[[#This Row],[Financial Services ]]=TRUE,2,Table2[[#This Row],[FIRM TYPE]]=TRUE,1,Table2[[#This Row],[FIRM TYPE]]=FALSE,3), _xlfn.CHOOSECOLS(_xlfn._xlws.FILTER(Rating1[],(Table2[[#This Row],[Interest Coverage Ratio]]>Rating1[>])*(Table2[[#This Row],[Interest Coverage Ratio]]<Rating1[≤ to])),4), _xlfn.CHOOSECOLS(_xlfn._xlws.FILTER(Rating2[],(Table2[[#This Row],[Interest Coverage Ratio]]>Rating2[greater than])*(Table2[[#This Row],[Interest Coverage Ratio]]<Rating2[≤ to])),4), _xlfn.CHOOSECOLS(_xlfn._xlws.FILTER(Rating3[],(Table2[[#This Row],[Interest Coverage Ratio]]>Rating3[greater than])*(Table2[[#This Row],[Interest Coverage Ratio]]<Rating3[≤ to])),4) )} -> 0.004 | Q11: {=CHOOSE( _xlfn.IFS(Table2[[#This Row],[Financial Services ]]=TRUE,2,Table2[[#This Row],[FIRM TYPE]]=TRUE,1,Table2[[#This Row],[FIRM TYPE]]=FALSE,3), _xlfn.CHOOSECOLS(_xlfn._xlws.FILTER(Rating1[],(Table2[[#This Row],[Interest Coverage Ratio]]>Rating1[>])*(Table2[[#This Row],[Interest Coverage Ratio]]<Rating1[≤ to])),3), _xlfn.CHOOSECOLS(_xlfn._xlws.FILTER(Rating2[],(Table2[[#This Row],[Interest Coverage Ratio]]>Rating2[greater than])*(Table2[[#This Row],[Interest Coverage Ratio]]<Rating2[≤ to])),3), _xlfn.CHOOSECOLS(_xlfn._xlws.FILTER(Rating3[],(Table2[[#This Row],[Interest Coverage Ratio]]>Rating3[greater than])*(Table2[[#This Row],[Interest Coverage Ratio]]<Rating3[≤ to])),3) )} -> Aaa/AAA | R11: =Table2[[#This Row],[Default Spread]]+Table2[[#This Row],[Risk Free Rate]] -> 0.0707 | S11: =_xlfn.XLOOKUP($B11,stock_analysis[Stock],stock_analysis[Market_Cap_Cr]) -> 276.40061 | T11: =_xlfn.XLOOKUP($B11,stock_analysis[Stock],stock_analysis[Total_Debt_Cr]) -> 27.643398 | U11: =Table2[[#This Row],[Market Value of Equity]]/(Table2[[#This Row],[Market Value of Equity]]+Table2[[#This Row],[Market Value of Debt]]) -> 0.90908093 | V11: =Table2[[#This Row],[Market Value of Debt]]/(Table2[[#This Row],[Market Value of Equity]]+Table2[[#This Row],[Market Value of Debt]]) -> 0.090919068 | W11: =(Table2[[#This Row],[Cost of Equity (Daily Beta)]]*Table2[[#This Row],[Weight of Equity]])+(Table2[[#This Row],[Cost of Debt]]*Table2[[#This Row],[Weight of Debt]]) -> 0.10024743 | X11: =(Table2[[#This Row],[Cost of Equity (Weekly Beta)]]*Table2[[#This Row],[Weight of Equity]])+(Table2[[#This Row],[Cost of Debt]]*Table2[[#This Row],[Weight of Debt]]) -> 0.12401445 | Y11: =(Table2[[#This Row],[Cost of Equity (Monthly Beta)]]*Table2[[#This Row],[Weight of Equity]])+(Table2[[#This Row],[Cost of Debt]]*Table2[[#This Row],[Weight of Debt]]) -> 0.035011158 | Z11: =IF(Table2[[#This Row],[Sector]]="Financial Services",TRUE,FALSE) -> FALSE | AA11: =IF(Table2[[#This Row],[Market Capitalisation In(Cr)]]>25000,TRUE,FALSE) -> FALSE
B12: MBAPL | C12: =_xlfn.XLOOKUP(B12,stock_analysis[Stock],stock_analysis[Company_Name]) -> Madhya Bharat Agro Products Limited | D12: =_xlfn.XLOOKUP(B12,stock_analysis[Stock],stock_analysis[Sector]) -> Basic Materials | E12: =_xlfn.XLOOKUP($B12,stock_analysis[Stock],stock_analysis[Industry]) -> Agricultural Inputs | F12: =_xlfn.XLOOKUP($B12,stock_analysis[Stock],stock_analysis[Market_Cap_Cr]) -> 4058.0039 | G12: =Imputs!$C$2 -> 0.0667 | H12: =Imputs!$C$3 -> 0.0523 | I12: =_xlfn.XLOOKUP($B12,stock_analysis[Stock],stock_analysis[Beta_Daily]) -> 0.70754567 | J12: =_xlfn.XLOOKUP($B12,stock_analysis[Stock],stock_analysis[Beta_Weekly]) -> 0.54003016 | K12: =_xlfn.XLOOKUP($B12,stock_analysis[Stock],stock_analysis[Beta_Monthly]) -> 0.099410438 | L12: =G12+H12*I12 -> 0.10370464 | M12: =J12*H12+G12 -> 0.094943577 | N12: =K12*H12+G12 -> 0.071899166 | O12: =_xlfn.XLOOKUP($B12,stock_analysis[Stock],stock_analysis[Interest_Coverage_Ratio]) -> 4.5335801 | P12: {=CHOOSE( _xlfn.IFS(Table2[[#This Row],[Financial Services ]]=TRUE,2,Table2[[#This Row],[FIRM TYPE]]=TRUE,1,Table2[[#This Row],[FIRM TYPE]]=FALSE,3), _xlfn.CHOOSECOLS(_xlfn._xlws.FILTER(Rating1[],(Table2[[#This Row],[Interest Coverage Ratio]]>Rating1[>])*(Table2[[#This Row],[Interest Coverage Ratio]]<Rating1[≤ to])),4), _xlfn.CHOOSECOLS(_xlfn._xlws.FILTER(Rating2[],(Table2[[#This Row],[Interest Coverage Ratio]]>Rating2[greater than])*(Table2[[#This Row],[Interest Coverage Ratio]]<Rating2[≤ to])),4), _xlfn.CHOOSECOLS(_xlfn._xlws.FILTER(Rating3[],(Table2[[#This Row],[Interest Coverage Ratio]]>Rating3[greater than])*(Table2[[#This Row],[Interest Coverage Ratio]]<Rating3[≤ to])),4) )} -> 0.0089 | Q12: {=CHOOSE( _xlfn.IFS(Table2[[#This Row],[Financial Services ]]=TRUE,2,Table2[[#This Row],[FIRM TYPE]]=TRUE,1,Table2[[#This Row],[FIRM TYPE]]=FALSE,3), _xlfn.CHOOSECOLS(_xlfn._xlws.FILTER(Rating1[],(Table2[[#This Row],[Interest Coverage Ratio]]>Rating1[>])*(Table2[[#This Row],[Interest Coverage Ratio]]<Rating1[≤ to])),3), _xlfn.CHOOSECOLS(_xlfn._xlws.FILTER(Rating2[],(Table2[[#This Row],[Interest Coverage Ratio]]>Rating2[greater than])*(Table2[[#This Row],[Interest Coverage Ratio]]<Rating2[≤ to])),3), _xlfn.CHOOSECOLS(_xlfn._xlws.FILTER(Rating3[],(Table2[[#This Row],[Interest Coverage Ratio]]>Rating3[greater than])*(Table2[[#This Row],[Interest Coverage Ratio]]<Rating3[≤ to])),3) )} -> A3/A- | R12: =Table2[[#This Row],[Default Spread]]+Table2[[#This Row],[Risk Free Rate]] -> 0.0756 | S12: =_xlfn.XLOOKUP($B12,stock_analysis[Stock],stock_analysis[Market_Cap_Cr]) -> 4058.0039 | T12: =_xlfn.XLOOKUP($B12,stock_analysis[Stock],stock_analysis[Total_Debt_Cr]) -> 312.21571 | U12: =Table2[[#This Row],[Market Value of Equity]]/(Table2[[#This Row],[Market Value of Equity]]+Table2[[#This Row],[Market Value of Debt]]) -> 0.92855835 | V12: =Table2[[#This Row],[Market Value of Debt]]/(Table2[[#This Row],[Market Value of Equity]]+Table2[[#This Row],[Market Value of Debt]]) -> 0.071441652 | W12: =(Table2[[#This Row],[Cost of Equity (Daily Beta)]]*Table2[[#This Row],[Weight of Equity]])+(Table2[[#This Row],[Cost of Debt]]*Table2[[#This Row],[Weight of Debt]]) -> 0.1016968 | X12: =(Table2[[#This Row],[Cost of Equity (Weekly Beta)]]*Table2[[#This Row],[Weight of Equity]])+(Table2[[#This Row],[Cost of Debt]]*Table2[[#This Row],[Weight of Debt]]) -> 0.09356164 | Y12: =(Table2[[#This Row],[Cost of Equity (Monthly Beta)]]*Table2[[#This Row],[Weight of Equity]])+(Table2[[#This Row],[Cost of Debt]]*Table2[[#This Row],[Weight of Debt]]) -> 0.07216356 | Z12: =IF(Table2[[#This Row],[Sector]]="Financial Services",TRUE,FALSE) -> FALSE | AA12: =IF(Table2[[#This Row],[Market Capitalisation In(Cr)]]>25000,TRUE,FALSE) -> FALSE
B13: NATHBIOGEN | C13: =_xlfn.XLOOKUP(B13,stock_analysis[Stock],stock_analysis[Company_Name]) -> Nath Bio-Genes (India) Limited | D13: =_xlfn.XLOOKUP(B13,stock_analysis[Stock],stock_analysis[Sector]) -> Basic Materials | E13: =_xlfn.XLOOKUP($B13,stock_analysis[Stock],stock_analysis[Industry]) -> Agricultural Inputs | F13: =_xlfn.XLOOKUP($B13,stock_analysis[Stock],stock_analysis[Market_Cap_Cr]) -> 272.13507 | G13: =Imputs!$C$2 -> 0.0667 | H13: =Imputs!$C$3 -> 0.0523 | I13: =_xlfn.XLOOKUP($B13,stock_analysis[Stock],stock_analysis[Beta_Daily]) -> 0.99060073 | J13: =_xlfn.XLOOKUP($B13,stock_analysis[Stock],stock_analysis[Beta_Weekly]) -> 1.4398622 | K13: =_xlfn.XLOOKUP($B13,stock_analysis[Stock],stock_analysis[Beta_Monthly]) -> 1.3740203 | L13: =G13+H13*I13 -> 0.11850842 | M13: =J13*H13+G13 -> 0.14200479 | N13: =K13*H13+G13 -> 0.13856126 | O13: =_xlfn.XLOOKUP($B13,stock_analysis[Stock],stock_analysis[Interest_Coverage_Ratio]) -> 5.0996 | P13: {=CHOOSE( _xlfn.IFS(Table2[[#This Row],[Financial Services ]]=TRUE,2,Table2[[#This Row],[FIRM TYPE]]=TRUE,1,Table2[[#This Row],[FIRM TYPE]]=FALSE,3), _xlfn.CHOOSECOLS(_xlfn._xlws.FILTER(Rating1[],(Table2[[#This Row],[Interest Coverage Ratio]]>Rating1[>])*(Table2[[#This Row],[Interest Coverage Ratio]]<Rating1[≤ to])),4), _xlfn.CHOOSECOLS(_xlfn._xlws.FILTER(Rating2[],(Table2[[#This Row],[Interest Coverage Ratio]]>Rating2[greater than])*(Table2[[#This Row],[Interest Coverage Ratio]]<Rating2[≤ to])),4), _xlfn.CHOOSECOLS(_xlfn._xlws.FILTER(Rating3[],(Table2[[#This Row],[Interest Coverage Ratio]]>Rating3[greater than])*(Table2[[#This Row],[Interest Coverage Ratio]]<Rating3[≤ to])),4) )} -> 0.0089 | Q13: {=CHOOSE( _xlfn.IFS(Table2[[#This Row],[Financial Services ]]=TRUE,2,Table2[[#This Row],[FIRM TYPE]]=TRUE,1,Table2[[#This Row],[FIRM TYPE]]=FALSE,3), _xlfn.CHOOSECOLS(_xlfn._xlws.FILTER(Rating1[],(Table2[[#This Row],[Interest Coverage Ratio]]>Rating1[>])*(Table2[[#This Row],[Interest Coverage Ratio]]<Rating1[≤ to])),3), _xlfn.CHOOSECOLS(_xlfn._xlws.FILTER(Rating2[],(Table2[[#This Row],[Interest Coverage Ratio]]>Rating2[greater than])*(Table2[[#This Row],[Interest Coverage Ratio]]<Rating2[≤ to])),3), _xlfn.CHOOSECOLS(_xlfn._xlws.FILTER(Rating3[],(Table2[[#This Row],[Interest Coverage Ratio]]>Rating3[greater than])*(Table2[[#This Row],[Interest Coverage Ratio]]<Rating3[≤ to])),3) )} -> A3/A- | R13: =Table2[[#This Row],[Default Spread]]+Table2[[#This Row],[Risk Free Rate]] -> 0.0756 | S13: =_xlfn.XLOOKUP($B13,stock_analysis[Stock],stock_analysis[Market_Cap_Cr]) -> 272.13507 | T13: =_xlfn.XLOOKUP($B13,stock_analysis[Stock],stock_analysis[Total_Debt_Cr]) -> 154.8288 | U13: =Table2[[#This Row],[Market Value of Equity]]/(Table2[[#This Row],[Market Value of Equity]]+Table2[[#This Row],[Market Value of Debt]]) -> 0.63737259 | V13: =Table2[[#This Row],[Market Value of Debt]]/(Table2[[#This Row],[Market Value of Equity]]+Table2[[#This Row],[Market Value of Debt]]) -> 0.36262741 | W13: =(Table2[[#This Row],[Cost of Equity (Daily Beta)]]*Table2[[#This Row],[Weight of Equity]])+(Table2[[#This Row],[Cost of Debt]]*Table2[[#This Row],[Weight of Debt]]) -> 0.10294865 | X13: =(Table2[[#This Row],[Cost of Equity (Weekly Beta)]]*Table2[[#This Row],[Weight of Equity]])+(Table2[[#This Row],[Cost of Debt]]*Table2[[#This Row],[Weight of Debt]]) -> 0.1179246 | Y13: =(Table2[[#This Row],[Cost of Equity (Monthly Beta)]]*Table2[[#This Row],[Weight of Equity]])+(Table2[[#This Row],[Cost of Debt]]*Table2[[#This Row],[Weight of Debt]]) -> 0.11572978 | Z13: =IF(Table2[[#This Row],[Sector]]="Financial Services",TRUE,FALSE) -> FALSE | AA13: =IF(Table2[[#This Row],[Market Capitalisation In(Cr)]]>25000,TRUE,FALSE) -> FALSE
B14: CHAMBLFERT | C14: =_xlfn.XLOOKUP(B14,stock_analysis[Stock],stock_analysis[Company_Name]) -> Chambal Fertilizers & Chemicals Limited | D14: =_xlfn.XLOOKUP(B14,stock_analysis[Stock],stock_analysis[Sector]) -> Basic Materials | E14: =_xlfn.XLOOKUP($B14,stock_analysis[Stock],stock_analysis[Industry]) -> Agricultural Inputs | F14: =_xlfn.XLOOKUP($B14,stock_analysis[Stock],stock_analysis[Market_Cap_Cr]) -> 17147.917 | G14: =Imputs!$C$2 -> 0.0667 | H14: =Imputs!$C$3 -> 0.0523 | I14: =_xlfn.XLOOKUP($B14,stock_analysis[Stock],stock_analysis[Beta_Daily]) -> 0.76192181 | J14: =_xlfn.XLOOKUP($B14,stock_analysis[Stock],stock_analysis[Beta_Weekly]) -> 0.9502772 | K14: =_xlfn.XLOOKUP($B14,stock_analysis[Stock],stock_analysis[Beta_Monthly]) -> 1.7737476 | L14: =G14+H14*I14 -> 0.10654851 | M14: =J14*H14+G14 -> 0.1163995 | N14: =K14*H14+G14 -> 0.159467 | O14: =_xlfn.XLOOKUP($B14,stock_analysis[Stock],stock_analysis[Interest_Coverage_Ratio]) -> 75.316763 | P14: {=CHOOSE( _xlfn.IFS(Table2[[#This Row],[Financial Services ]]=TRUE,2,Table2[[#This Row],[FIRM TYPE]]=TRUE,1,Table2[[#This Row],[FIRM TYPE]]=FALSE,3), _xlfn.CHOOSECOLS(_xlfn._xlws.FILTER(Rating1[],(Table2[[#This Row],[Interest Coverage Ratio]]>Rating1[>])*(Table2[[#This Row],[Interest Coverage Ratio]]<Rating1[≤ to])),4), _xlfn.CHOOSECOLS(_xlfn._xlws.FILTER(Rating2[],(Table2[[#This Row],[Interest Coverage Ratio]]>Rating2[greater than])*(Table2[[#This Row],[Interest Coverage Ratio]]<Rating2[≤ to])),4), _xlfn.CHOOSECOLS(_xlfn._xlws.FILTER(Rating3[],(Table2[[#This Row],[Interest Coverage Ratio]]>Rating3[greater than])*(Table2[[#This Row],[Interest Coverage Ratio]]<Rating3[≤ to])),4) )} -> 0.004 | Q14: {=CHOOSE( _xlfn.IFS(Table2[[#This Row],[Financial Services ]]=TRUE,2,Table2[[#This Row],[FIRM TYPE]]=TRUE,1,Table2[[#This Row],[FIRM TYPE]]=FALSE,3), _xlfn.CHOOSECOLS(_xlfn._xlws.FILTER(Rating1[],(Table2[[#This Row],[Interest Coverage Ratio]]>Rating1[>])*(Table2[[#This Row],[Interest Coverage Ratio]]<Rating1[≤ to])),3), _xlfn.CHOOSECOLS(_xlfn._xlws.FILTER(Rating2[],(Table2[[#This Row],[Interest Coverage Ratio]]>Rating2[greater than])*(Table2[[#This Row],[Interest Coverage Ratio]]<Rating2[≤ to])),3), _xlfn.CHOOSECOLS(_xlfn._xlws.FILTER(Rating3[],(Table2[[#This Row],[Interest Coverage Ratio]]>Rating3[greater than])*(Table2[[#This Row],[Interest Coverage Ratio]]<Rating3[≤ to])),3) )} -> Aaa/AAA | R14: =Table2[[#This Row],[Default Spread]]+Table2[[#This Row],[Risk Free Rate]] -> 0.0707 | S14: =_xlfn.XLOOKUP($B14,stock_analysis[Stock],stock_analysis[Market_Cap_Cr]) -> 17147.917 | T14: =_xlfn.XLOOKUP($B14,stock_analysis[Stock],stock_analysis[Total_Debt_Cr]) -> 100.37 | U14: =Table2[[#This Row],[Market Value of Equity]]/(Table2[[#This Row],[Market Value of Equity]]+Table2[[#This Row],[Market Value of Debt]]) -> 0.99418087 | V14: =Table2[[#This Row],[Market Value of Debt]]/(Table2[[#This Row],[Market Value of Equity]]+Table2[[#This Row],[Market Value of Debt]]) -> 0.0058191284 | W14: =(Table2[[#This Row],[Cost of Equity (Daily Beta)]]*Table2[[#This Row],[Weight of Equity]])+(Table2[[#This Row],[Cost of Debt]]*Table2[[#This Row],[Weight of Debt]]) -> 0.1063399 | X14: =(Table2[[#This Row],[Cost of Equity (Weekly Beta)]]*Table2[[#This Row],[Weight of Equity]])+(Table2[[#This Row],[Cost of Debt]]*Table2[[#This Row],[Weight of Debt]]) -> 0.11613357 | Y14: =(Table2[[#This Row],[Cost of Equity (Monthly Beta)]]*Table2[[#This Row],[Weight of Equity]])+(Table2[[#This Row],[Cost of Debt]]*Table2[[#This Row],[Weight of Debt]]) -> 0.15895045 | Z14: =IF(Table2[[#This Row],[Sector]]="Financial Services",TRUE,FALSE) -> FALSE | AA14: =IF(Table2[[#This Row],[Market Capitalisation In(Cr)]]>25000,TRUE,FALSE) -> FALSE
... B133: JAINREC | C133: =_xlfn.XLOOKUP(B133,stock_analysis[Stock],stock_analysis[Company_Name]) -> Jain Resource Recycling Limited | D133: =_xlfn.XLOOKUP(B133,stock_analysis[Stock],stock_analysis[Sector]) -> Basic Materials | E133: =_xlfn.XLOOKUP($B133,stock_analysis[Stock],stock_analysis[Industry]) -> Other Industrial Metals & Mining | F133: =_xlfn.XLOOKUP($B133,stock_analysis[Stock],stock_analysis[Market_Cap_Cr]) -> 13837.941 | G133: =Imputs!$C$2 -> 0.0667 | H133: =Imputs!$C$3 -> 0.0523 | I133: =_xlfn.XLOOKUP($B133,stock_analysis[Stock],stock_analysis[Beta_Daily]) -> 0.78616311 | J133: =_xlfn.XLOOKUP($B133,stock_analysis[Stock],stock_analysis[Beta_Weekly]) -> 1.259266 | K133: =_xlfn.XLOOKUP($B133,stock_analysis[Stock],stock_analysis[Beta_Monthly]) -> 0.72399193 | L133: =G133+H133*I133 -> 0.10781633 | M133: =J133*H133+G133 -> 0.13255961 | N133: =K133*H133+G133 -> 0.10456478 | O133: =_xlfn.XLOOKUP($B133,stock_analysis[Stock],stock_analysis[Interest_Coverage_Ratio]) -> 5.0523249 | P133: {=CHOOSE( _xlfn.IFS(Table2[[#This Row],[Financial Services ]]=TRUE,2,Table2[[#This Row],[FIRM TYPE]]=TRUE,1,Table2[[#This Row],[FIRM TYPE]]=FALSE,3), _xlfn.CHOOSECOLS(_xlfn._xlws.FILTER(Rating1[],(Table2[[#This Row],[Interest Coverage Ratio]]>Rating1[>])*(Table2[[#This Row],[Interest Coverage Ratio]]<Rating1[≤ to])),4), _xlfn.CHOOSECOLS(_xlfn._xlws.FILTER(Rating2[],(Table2[[#This Row],[Interest Coverage Ratio]]>Rating2[greater than])*(Table2[[#This Row],[Interest Coverage Ratio]]<Rating2[≤ to])),4), _xlfn.CHOOSECOLS(_xlfn._xlws.FILTER(Rating3[],(Table2[[#This Row],[Interest Coverage Ratio]]>Rating3[greater than])*(Table2[[#This Row],[Interest Coverage Ratio]]<Rating3[≤ to])),4) )} -> 0.0089 | Q133: {=CHOOSE( _xlfn.IFS(Table2[[#This Row],[Financial Services ]]=TRUE,2,Table2[[#This Row],[FIRM TYPE]]=TRUE,1,Table2[[#This Row],[FIRM TYPE]]=FALSE,3), _xlfn.CHOOSECOLS(_xlfn._xlws.FILTER(Rating1[],(Table2[[#This Row],[Interest Coverage Ratio]]>Rating1[>])*(Table2[[#This Row],[Interest Coverage Ratio]]<Rating1[≤ to])),3), _xlfn.CHOOSECOLS(_xlfn._xlws.FILTER(Rating2[],(Table2[[#This Row],[Interest Coverage Ratio]]>Rating2[greater than])*(Table2[[#This Row],[Interest Coverage Ratio]]<Rating2[≤ to])),3), _xlfn.CHOOSECOLS(_xlfn._xlws.FILTER(Rating3[],(Table2[[#This Row],[Interest Coverage Ratio]]>Rating3[greater than])*(Table2[[#This Row],[Interest Coverage Ratio]]<Rating3[≤ to])),3) )} -> A3/A- | R133: =Table2[[#This Row],[Default Spread]]+Table2[[#This Row],[Risk Free Rate]] -> 0.0756 | S133: =_xlfn.XLOOKUP($B133,stock_analysis[Stock],stock_analysis[Market_Cap_Cr]) -> 13837.941 | T133: =_xlfn.XLOOKUP($B133,stock_analysis[Stock],stock_analysis[Total_Debt_Cr]) -> 1293.571 | U133: =Table2[[#This Row],[Market Value of Equity]]/(Table2[[#This Row],[Market Value of Equity]]+Table2[[#This Row],[Market Value of Debt]]) -> 0.91451145 | V133: =Table2[[#This Row],[Market Value of Debt]]/(Table2[[#This Row],[Market Value of Equity]]+Table2[[#This Row],[Market Value of Debt]]) -> 0.085488546 | W133: =(Table2[[#This Row],[Cost of Equity (Daily Beta)]]*Table2[[#This Row],[Weight of Equity]])+(Table2[[#This Row],[Cost of Debt]]*Table2[[#This Row],[Weight of Debt]]) -> 0.1050622 | X133: =(Table2[[#This Row],[Cost of Equity (Weekly Beta)]]*Table2[[#This Row],[Weight of Equity]])+(Table2[[#This Row],[Cost of Debt]]*Table2[[#This Row],[Weight of Debt]]) -> 0.12769022 | Y133: =(Table2[[#This Row],[Cost of Equity (Monthly Beta)]]*Table2[[#This Row],[Weight of Equity]])+(Table2[[#This Row],[Cost of Debt]]*Table2[[#This Row],[Weight of Debt]]) -> 0.10208862 | Z133: =IF(Table2[[#This Row],[Sector]]="Financial Services",TRUE,FALSE) -> FALSE | AA133: =IF(Table2[[#This Row],[Market Capitalisation In(Cr)]]>25000,TRUE,FALSE) -> FALSE
B134: 20MICRONS | C134: =_xlfn.XLOOKUP(B134,stock_analysis[Stock],stock_analysis[Company_Name]) -> 20 Microns Limited | D134: =_xlfn.XLOOKUP($B134,stock_analysis[Stock],stock_analysis[Sector]) -> Basic Materials | E134: =_xlfn.XLOOKUP($B134,stock_analysis[Stock],stock_analysis[Industry]) -> Other Industrial Metals & Mining | F134: =_xlfn.XLOOKUP($B134,stock_analysis[Stock],stock_analysis[Market_Cap_Cr]) -> 589.33535 | G134: =Imputs!$C$2 -> 0.0667 | H134: =Imputs!$C$3 -> 0.0523 | I134: =_xlfn.XLOOKUP($B134,stock_analysis[Stock],stock_analysis[Beta_Daily]) -> 1.1950363 | J134: =_xlfn.XLOOKUP($B134,stock_analysis[Stock],stock_analysis[Beta_Weekly]) -> 1.37515 | K134: =_xlfn.XLOOKUP($B134,stock_analysis[Stock],stock_analysis[Beta_Monthly]) -> 8.2148172 | L134: =G134+H134*I134 -> 0.1292004 | M134: =J134*H134+G134 -> 0.13862035 | N134: =K134*H134+G134 -> 0.49633494 | O134: =_xlfn.XLOOKUP($B134,stock_analysis[Stock],stock_analysis[Interest_Coverage_Ratio]) -> 8.3028055 | P134: {=CHOOSE( _xlfn.IFS(Table2[[#This Row],[Financial Services ]]=TRUE,2,Table2[[#This Row],[FIRM TYPE]]=TRUE,1,Table2[[#This Row],[FIRM TYPE]]=FALSE,3), _xlfn.CHOOSECOLS(_xlfn._xlws.FILTER(Rating1[],(Table2[[#This Row],[Interest Coverage Ratio]]>Rating1[>])*(Table2[[#This Row],[Interest Coverage Ratio]]<Rating1[≤ to])),4), _xlfn.CHOOSECOLS(_xlfn._xlws.FILTER(Rating2[],(Table2[[#This Row],[Interest Coverage Ratio]]>Rating2[greater than])*(Table2[[#This Row],[Interest Coverage Ratio]]<Rating2[≤ to])),4), _xlfn.CHOOSECOLS(_xlfn._xlws.FILTER(Rating3[],(Table2[[#This Row],[Interest Coverage Ratio]]>Rating3[greater than])*(Table2[[#This Row],[Interest Coverage Ratio]]<Rating3[≤ to])),4) )} -> 0.007 | Q134: {=CHOOSE( _xlfn.IFS(Table2[[#This Row],[Financial Services ]]=TRUE,2,Table2[[#This Row],[FIRM TYPE]]=TRUE,1,Table2[[#This Row],[FIRM TYPE]]=FALSE,3), _xlfn.CHOOSECOLS(_xlfn._xlws.FILTER(Rating1[],(Table2[[#This Row],[Interest Coverage Ratio]]>Rating1[>])*(Table2[[#This Row],[Interest Coverage Ratio]]<Rating1[≤ to])),3), _xlfn.CHOOSECOLS(_xlfn._xlws.FILTER(Rating2[],(Table2[[#This Row],[Interest Coverage Ratio]]>Rating2[greater than])*(Table2[[#This Row],[Interest Coverage Ratio]]<Rating2[≤ to])),3), _xlfn.CHOOSECOLS(_xlfn._xlws.FILTER(Rating3[],(Table2[[#This Row],[Interest Coverage Ratio]]>Rating3[greater than])*(Table2[[#This Row],[Interest Coverage Ratio]]<Rating3[≤ to])),3) )} -> A1/A+ | R134: =Table2[[#This Row],[Default Spread]]+Table2[[#This Row],[Risk Free Rate]] -> 0.0737 | S134: =_xlfn.XLOOKUP($B134,stock_analysis[Stock],stock_analysis[Market_Cap_Cr]) -> 589.33535 | T134: =_xlfn.XLOOKUP($B134,stock_analysis[Stock],stock_analysis[Total_Debt_Cr]) -> 163.3658 | U134: =Table2[[#This Row],[Market Value of Equity]]/(Table2[[#This Row],[Market Value of Equity]]+Table2[[#This Row],[Market Value of Debt]]) -> 0.78296061 | V134: =Table2[[#This Row],[Market Value of Debt]]/(Table2[[#This Row],[Market Value of Equity]]+Table2[[#This Row],[Market Value of Debt]]) -> 0.21703939 | W134: =(Table2[[#This Row],[Cost of Equity (Daily Beta)]]*Table2[[#This Row],[Weight of Equity]])+(Table2[[#This Row],[Cost of Debt]]*Table2[[#This Row],[Weight of Debt]]) -> 0.11715462 | X134: =(Table2[[#This Row],[Cost of Equity (Weekly Beta)]]*Table2[[#This Row],[Weight of Equity]])+(Table2[[#This Row],[Cost of Debt]]*Table2[[#This Row],[Weight of Debt]]) -> 0.12453007 | Y134: =(Table2[[#This Row],[Cost of Equity (Monthly Beta)]]*Table2[[#This Row],[Weight of Equity]])+(Table2[[#This Row],[Cost of Debt]]*Table2[[#This Row],[Weight of Debt]]) -> 0.40460651 | Z134: =IF(Table2[[#This Row],[Sector]]="Financial Services",TRUE,FALSE) -> FALSE | AA134: =IF(Table2[[#This Row],[Market Capitalisation In(Cr)]]>25000,TRUE,FALSE) -> FALSE
B135: IMFA | C135: =_xlfn.XLOOKUP(B135,stock_analysis[Stock],stock_analysis[Company_Name]) -> Indian Metals & Ferro Alloys Limited | D135: =_xlfn.XLOOKUP(B135,stock_analysis[Stock],stock_analysis[Sector]) -> Basic Materials | E135: =_xlfn.XLOOKUP($B135,stock_analysis[Stock],stock_analysis[Industry]) -> Other Industrial Metals & Mining | F135: =_xlfn.XLOOKUP($B135,stock_analysis[Stock],stock_analysis[Market_Cap_Cr]) -> 6378.6467 | G135: =Imputs!$C$2 -> 0.0667 | H135: =Imputs!$C$3 -> 0.0523 | I135: =_xlfn.XLOOKUP($B135,stock_analysis[Stock],stock_analysis[Beta_Daily]) -> 1.0561701 | J135: =_xlfn.XLOOKUP($B135,stock_analysis[Stock],stock_analysis[Beta_Weekly]) -> 1.7206584 | K135: =_xlfn.XLOOKUP($B135,stock_analysis[Stock],stock_analysis[Beta_Monthly]) -> 0.7156995 | L135: =G135+H135*I135 -> 0.12193769 | M135: =J135*H135+G135 -> 0.15669044 | N135: =K135*H135+G135 -> 0.10413108 | O135: =_xlfn.XLOOKUP($B135,stock_analysis[Stock],stock_analysis[Interest_Coverage_Ratio]) -> 23.323491 | P135: {=CHOOSE( _xlfn.IFS(Table2[[#This Row],[Financial Services ]]=TRUE,2,Table2[[#This Row],[FIRM TYPE]]=TRUE,1,Table2[[#This Row],[FIRM TYPE]]=FALSE,3), _xlfn.CHOOSECOLS(_xlfn._xlws.FILTER(Rating1[],(Table2[[#This Row],[Interest Coverage Ratio]]>Rating1[>])*(Table2[[#This Row],[Interest Coverage Ratio]]<Rating1[≤ to])),4), _xlfn.CHOOSECOLS(_xlfn._xlws.FILTER(Rating2[],(Table2[[#This Row],[Interest Coverage Ratio]]>Rating2[greater than])*(Table2[[#This Row],[Interest Coverage Ratio]]<Rating2[≤ to])),4), _xlfn.CHOOSECOLS(_xlfn._xlws.FILTER(Rating3[],(Table2[[#This Row],[Interest Coverage Ratio]]>Rating3[greater than])*(Table2[[#This Row],[Interest Coverage Ratio]]<Rating3[≤ to])),4) )} -> 0.004 | Q135: {=CHOOSE( _xlfn.IFS(Table2[[#This Row],[Financial Services ]]=TRUE,2,Table2[[#This Row],[FIRM TYPE]]=TRUE,1,Table2[[#This Row],[FIRM TYPE]]=FALSE,3), _xlfn.CHOOSECOLS(_xlfn._xlws.FILTER(Rating1[],(Table2[[#This Row],[Interest Coverage Ratio]]>Rating1[>])*(Table2[[#This Row],[Interest Coverage Ratio]]<Rating1[≤ to])),3), _xlfn.CHOOSECOLS(_xlfn._xlws.FILTER(Rating2[],(Table2[[#This Row],[Interest Coverage Ratio]]>Rating2[greater than])*(Table2[[#This Row],[Interest Coverage Ratio]]<Rating2[≤ to])),3), _xlfn.CHOOSECOLS(_xlfn._xlws.FILTER(Rating3[],(Table2[[#This Row],[Interest Coverage Ratio]]>Rating3[greater than])*(Table2[[#This Row],[Interest Coverage Ratio]]<Rating3[≤ to])),3) )} -> Aaa/AAA | R135: =Table2[[#This Row],[Default Spread]]+Table2[[#This Row],[Risk Free Rate]] -> 0.0707 | S135: =_xlfn.XLOOKUP($B135,stock_analysis[Stock],stock_analysis[Market_Cap_Cr]) -> 6378.6467 | T135: =_xlfn.XLOOKUP($B135,stock_analysis[Stock],stock_analysis[Total_Debt_Cr]) -> 435.32001 | U135: =Table2[[#This Row],[Market Value of Equity]]/(Table2[[#This Row],[Market Value of Equity]]+Table2[[#This Row],[Market Value of Debt]]) -> 0.93611357 | V135: =Table2[[#This Row],[Market Value of Debt]]/(Table2[[#This Row],[Market Value of Equity]]+Table2[[#This Row],[Market Value of Debt]]) -> 0.06388643 | W135: =(Table2[[#This Row],[Cost of Equity (Daily Beta)]]*Table2[[#This Row],[Weight of Equity]])+(Table2[[#This Row],[Cost of Debt]]*Table2[[#This Row],[Weight of Debt]]) -> 0.1186643 | X135: =(Table2[[#This Row],[Cost of Equity (Weekly Beta)]]*Table2[[#This Row],[Weight of Equity]])+(Table2[[#This Row],[Cost of Debt]]*Table2[[#This Row],[Weight of Debt]]) -> 0.15119681 | Y135: =(Table2[[#This Row],[Cost of Equity (Monthly Beta)]]*Table2[[#This Row],[Weight of Equity]])+(Table2[[#This Row],[Cost of Debt]]*Table2[[#This Row],[Weight of Debt]]) -> 0.10199529 | Z135: =IF(Table2[[#This Row],[Sector]]="Financial Services",TRUE,FALSE) -> FALSE | AA135: =IF(Table2[[#This Row],[Market Capitalisation In(Cr)]]>25000,TRUE,FALSE) -> FALSE
B136: VEDL | C136: =_xlfn.XLOOKUP(B136,stock_analysis[Stock],stock_analysis[Company_Name]) -> Vedanta Limited | D136: =_xlfn.XLOOKUP(B136,stock_analysis[Stock],stock_analysis[Sector]) -> Basic Materials | E136: =_xlfn.XLOOKUP($B136,stock_analysis[Stock],stock_analysis[Industry]) -> Other Industrial Metals & Mining | F136: =_xlfn.XLOOKUP($B136,stock_analysis[Stock],stock_analysis[Market_Cap_Cr]) -> 281114.71 | G136: =Imputs!$C$2 -> 0.0667 | H136: =Imputs!$C$3 -> 0.0523 | I136: =_xlfn.XLOOKUP($B136,stock_analysis[Stock],stock_analysis[Beta_Daily]) -> 1.3951658 | J136: =_xlfn.XLOOKUP($B136,stock_analysis[Stock],stock_analysis[Beta_Weekly]) -> 1.4937794 | K136: =_xlfn.XLOOKUP($B136,stock_analysis[Stock],stock_analysis[Beta_Monthly]) -> 0.94049146 | L136: =G136+H136*I136 -> 0.13966717 | M136: =J136*H136+G136 -> 0.14482466 | N136: =K136*H136+G136 -> 0.1158877 | O136: =_xlfn.XLOOKUP($B136,stock_analysis[Stock],stock_analysis[Interest_Coverage_Ratio]) -> 4.0280532 | P136: {=CHOOSE( _xlfn.IFS(Table2[[#This Row],[Financial Services ]]=TRUE,2,Table2[[#This Row],[FIRM TYPE]]=TRUE,1,Table2[[#This Row],[FIRM TYPE]]=FALSE,3), _xlfn.CHOOSECOLS(_xlfn._xlws.FILTER(Rating1[],(Table2[[#This Row],[Interest Coverage Ratio]]>Rating1[>])*(Table2[[#This Row],[Interest Coverage Ratio]]<Rating1[≤ to])),4), _xlfn.CHOOSECOLS(_xlfn._xlws.FILTER(Rating2[],(Table2[[#This Row],[Interest Coverage Ratio]]>Rating2[greater than])*(Table2[[#This Row],[Interest Coverage Ratio]]<Rating2[≤ to])),4), _xlfn.CHOOSECOLS(_xlfn._xlws.FILTER(Rating3[],(Table2[[#This Row],[Interest Coverage Ratio]]>Rating3[greater than])*(Table2[[#This Row],[Interest Coverage Ratio]]<Rating3[≤ to])),4) )} -> 0.0089 | Q136: {=CHOOSE( _xlfn.IFS(Table2[[#This Row],[Financial Services ]]=TRUE,2,Table2[[#This Row],[FIRM TYPE]]=TRUE,1,Table2[[#This Row],[FIRM TYPE]]=FALSE,3), _xlfn.CHOOSECOLS(_xlfn._xlws.FILTER(Rating1[],(Table2[[#This Row],[Interest Coverage Ratio]]>Rating1[>])*(Table2[[#This Row],[Interest Coverage Ratio]]<Rating1[≤ to])),3), _xlfn.CHOOSECOLS(_xlfn._xlws.FILTER(Rating2[],(Table2[[#This Row],[Interest Coverage Ratio]]>Rating2[greater than])*(Table2[[#This Row],[Interest Coverage Ratio]]<Rating2[≤ to])),3), _xlfn.CHOOSECOLS(_xlfn._xlws.FILTER(Rating3[],(Table2[[#This Row],[Interest Coverage Ratio]]>Rating3[greater than])*(Table2[[#This Row],[Interest Coverage Ratio]]<Rating3[≤ to])),3) )} -> A3/A- | R136: =Table2[[#This Row],[Default Spread]]+Table2[[#This Row],[Risk Free Rate]] -> 0.0756 | S136: =_xlfn.XLOOKUP($B136,stock_analysis[Stock],stock_analysis[Market_Cap_Cr]) -> 281114.71 | T136: =_xlfn.XLOOKUP($B136,stock_analysis[Stock],stock_analysis[Total_Debt_Cr]) -> 103143 | U136: =Table2[[#This Row],[Market Value of Equity]]/(Table2[[#This Row],[Market Value of Equity]]+Table2[[#This Row],[Market Value of Debt]]) -> 0.73157858 | V136: =Table2[[#This Row],[Market Value of Debt]]/(Table2[[#This Row],[Market Value of Equity]]+Table2[[#This Row],[Market Value of Debt]]) -> 0.26842142 | W136: =(Table2[[#This Row],[Cost of Equity (Daily Beta)]]*Table2[[#This Row],[Weight of Equity]])+(Table2[[#This Row],[Cost of Debt]]*Table2[[#This Row],[Weight of Debt]]) -> 0.12247017 | X136: =(Table2[[#This Row],[Cost of Equity (Weekly Beta)]]*Table2[[#This Row],[Weight of Equity]])+(Table2[[#This Row],[Cost of Debt]]*Table2[[#This Row],[Weight of Debt]]) -> 0.12624328 | Y136: =(Table2[[#This Row],[Cost of Equity (Monthly Beta)]]*Table2[[#This Row],[Weight of Equity]])+(Table2[[#This Row],[Cost of Debt]]*Table2[[#This Row],[Weight of Debt]]) -> 0.10507362 | Z136: =IF(Table2[[#This Row],[Sector]]="Financial Services",TRUE,FALSE) -> FALSE | AA136: =IF(Table2[[#This Row],[Market Capitalisation In(Cr)]]>25000,TRUE,FALSE) -> TRUE
B137: HINDZINC | C137: =_xlfn.XLOOKUP(B137,stock_analysis[Stock],stock_analysis[Company_Name]) -> Hindustan Zinc Limited | D137: =_xlfn.XLOOKUP(B137,stock_analysis[Stock],stock_analysis[Sector]) -> Basic Materials | E137: =_xlfn.XLOOKUP($B137,stock_analysis[Stock],stock_analysis[Industry]) -> Other Industrial Metals & Mining | F137: =_xlfn.XLOOKUP($B137,stock_analysis[Stock],stock_analysis[Market_Cap_Cr]) -> 252864.21 | G137: =Imputs!$C$2 -> 0.0667 | H137: =Imputs!$C$3 -> 0.0523 | I137: =_xlfn.XLOOKUP($B137,stock_analysis[Stock],stock_analysis[Beta_Daily]) -> 1.230481 | J137: =_xlfn.XLOOKUP($B137,stock_analysis[Stock],stock_analysis[Beta_Weekly]) -> 1.2663747 | K137: =_xlfn.XLOOKUP($B137,stock_analysis[Stock],stock_analysis[Beta_Monthly]) -> 0.6037714 | L137: =G137+H137*I137 -> 0.13105416 | M137: =J137*H137+G137 -> 0.1329314 | N137: =K137*H137+G137 -> 0.098277244 | O137: =_xlfn.XLOOKUP($B137,stock_analysis[Stock],stock_analysis[Interest_Coverage_Ratio]) -> 14.829592 | P137: {=CHOOSE( _xlfn.IFS(Table2[[#This Row],[Financial Services ]]=TRUE,2,Table2[[#This Row],[FIRM TYPE]]=TRUE,1,Table2[[#This Row],[FIRM TYPE]]=FALSE,3), _xlfn.CHOOSECOLS(_xlfn._xlws.FILTER(Rating1[],(Table2[[#This Row],[Interest Coverage Ratio]]>Rating1[>])*(Table2[[#This Row],[Interest Coverage Ratio]]<Rating1[≤ to])),4), _xlfn.CHOOSECOLS(_xlfn._xlws.FILTER(Rating2[],(Table2[[#This Row],[Interest Coverage Ratio]]>Rating2[greater than])*(Table2[[#This Row],[Interest Coverage Ratio]]<Rating2[≤ to])),4), _xlfn.CHOOSECOLS(_xlfn._xlws.FILTER(Rating3[],(Table2[[#This Row],[Interest Coverage Ratio]]>Rating3[greater than])*(Table2[[#This Row],[Interest Coverage Ratio]]<Rating3[≤ to])),4) )} -> 0.004 | Q137: {=CHOOSE( _xlfn.IFS(Table2[[#This Row],[Financial Services ]]=TRUE,2,Table2[[#This Row],[FIRM TYPE]]=TRUE,1,Table2[[#This Row],[FIRM TYPE]]=FALSE,3), _xlfn.CHOOSECOLS(_xlfn._xlws.FILTER(Rating1[],(Table2[[#This Row],[Interest Coverage Ratio]]>Rating1[>])*(Table2[[#This Row],[Interest Coverage Ratio]]<Rating1[≤ to])),3), _xlfn.CHOOSECOLS(_xlfn._xlws.FILTER(Rating2[],(Table2[[#This Row],[Interest Coverage Ratio]]>Rating2[greater than])*(Table2[[#This Row],[Interest Coverage Ratio]]<Rating2[≤ to])),3), _xlfn.CHOOSECOLS(_xlfn._xlws.FILTER(Rating3[],(Table2[[#This Row],[Interest Coverage Ratio]]>Rating3[greater than])*(Table2[[#This Row],[Interest Coverage Ratio]]<Rating3[≤ to])),3) )} -> Aaa/AAA | R137: =Table2[[#This Row],[Default Spread]]+Table2[[#This Row],[Risk Free Rate]] -> 0.0707 | S137: =_xlfn.XLOOKUP($B137,stock_analysis[Stock],stock_analysis[Market_Cap_Cr]) -> 252864.21 | T137: =_xlfn.XLOOKUP($B137,stock_analysis[Stock],stock_analysis[Total_Debt_Cr]) -> 12077 | U137: =Table2[[#This Row],[Market Value of Equity]]/(Table2[[#This Row],[Market Value of Equity]]+Table2[[#This Row],[Market Value of Debt]]) -> 0.9544163 | V137: =Table2[[#This Row],[Market Value of Debt]]/(Table2[[#This Row],[Market Value of Equity]]+Table2[[#This Row],[Market Value of Debt]]) -> 0.045583699 | W137: =(Table2[[#This Row],[Cost of Equity (Daily Beta)]]*Table2[[#This Row],[Weight of Equity]])+(Table2[[#This Row],[Cost of Debt]]*Table2[[#This Row],[Weight of Debt]]) -> 0.12830299 | X137: =(Table2[[#This Row],[Cost of Equity (Weekly Beta)]]*Table2[[#This Row],[Weight of Equity]])+(Table2[[#This Row],[Cost of Debt]]*Table2[[#This Row],[Weight of Debt]]) -> 0.13009466 | Y137: =(Table2[[#This Row],[Cost of Equity (Monthly Beta)]]*Table2[[#This Row],[Weight of Equity]])+(Table2[[#This Row],[Cost of Debt]]*Table2[[#This Row],[Weight of Debt]]) -> 0.097020171 | Z137: =IF(Table2[[#This Row],[Sector]]="Financial Services",TRUE,FALSE) -> FALSE | AA137: =IF(Table2[[#This Row],[Market Capitalisation In(Cr)]]>25000,TRUE,FALSE) -> TRUE
B138: ASHAPURMIN | C138: =_xlfn.XLOOKUP(B138,stock_analysis[Stock],stock_analysis[Company_Name]) -> Ashapura Minechem Limited | D138: =_xlfn.XLOOKUP(B138,stock_analysis[Stock],stock_analysis[Sector]) -> Basic Materials | E138: =_xlfn.XLOOKUP($B138,stock_analysis[Stock],stock_analysis[Industry]) -> Other Industrial Metals & Mining | F138: =_xlfn.XLOOKUP($B138,stock_analysis[Stock],stock_analysis[Market_Cap_Cr]) -> 4876.1295 | G138: =Imputs!$C$2 -> 0.0667 | H138: =Imputs!$C$3 -> 0.0523 | I138: =_xlfn.XLOOKUP($B138,stock_analysis[Stock],stock_analysis[Beta_Daily]) -> 1.4499822 | J138: =_xlfn.XLOOKUP($B138,stock_analysis[Stock],stock_analysis[Beta_Weekly]) -> 1.6075563 | K138: =_xlfn.XLOOKUP($B138,stock_analysis[Stock],stock_analysis[Beta_Monthly]) -> 1.0728914 | L138: =G138+H138*I138 -> 0.14253407 | M138: =J138*H138+G138 -> 0.15077519 | N138: =K138*H138+G138 -> 0.12281222 | O138: =_xlfn.XLOOKUP($B138,stock_analysis[Stock],stock_analysis[Interest_Coverage_Ratio]) -> 4.448217 | P138: {=CHOOSE( _xlfn.IFS(Table2[[#This Row],[Financial Services ]]=TRUE,2,Table2[[#This Row],[FIRM TYPE]]=TRUE,1,Table2[[#This Row],[FIRM TYPE]]=FALSE,3), _xlfn.CHOOSECOLS(_xlfn._xlws.FILTER(Rating1[],(Table2[[#This Row],[Interest Coverage Ratio]]>Rating1[>])*(Table2[[#This Row],[Interest Coverage Ratio]]<Rating1[≤ to])),4), _xlfn.CHOOSECOLS(_xlfn._xlws.FILTER(Rating2[],(Table2[[#This Row],[Interest Coverage Ratio]]>Rating2[greater than])*(Table2[[#This Row],[Interest Coverage Ratio]]<Rating2[≤ to])),4), _xlfn.CHOOSECOLS(_xlfn._xlws.FILTER(Rating3[],(Table2[[#This Row],[Interest Coverage Ratio]]>Rating3[greater than])*(Table2[[#This Row],[Interest Coverage Ratio]]<Rating3[≤ to])),4) )} -> 0.0111 | Q138: {=CHOOSE( _xlfn.IFS(Table2[[#This Row],[Financial Services ]]=TRUE,2,Table2[[#This Row],[FIRM TYPE]]=TRUE,1,Table2[[#This Row],[FIRM TYPE]]=FALSE,3), _xlfn.CHOOSECOLS(_xlfn._xlws.FILTER(Rating1[],(Table2[[#This Row],[Interest Coverage Ratio]]>Rating1[>])*(Table2[[#This Row],[Interest Coverage Ratio]]<Rating1[≤ to])),3), _xlfn.CHOOSECOLS(_xlfn._xlws.FILTER(Rating2[],(Table2[[#This Row],[Interest Coverage Ratio]]>Rating2[greater than])*(Table2[[#This Row],[Interest Coverage Ratio]]<Rating2[≤ to])),3), _xlfn.CHOOSECOLS(_xlfn._xlws.FILTER(Rating3[],(Table2[[#This Row],[Interest Coverage Ratio]]>Rating3[greater than])*(Table2[[#This Row],[Interest Coverage Ratio]]<Rating3[≤ to])),3) )} -> Baa2/BBB | R138: =Table2[[#This Row],[Default Spread]]+Table2[[#This Row],[Risk Free Rate]] -> 0.0778 | S138: =_xlfn.XLOOKUP($B138,stock_analysis[Stock],stock_analysis[Market_Cap_Cr]) -> 4876.1295 | T138: =_xlfn.XLOOKUP($B138,stock_analysis[Stock],stock_analysis[Total_Debt_Cr]) -> 1227.55 | U138: =Table2[[#This Row],[Market Value of Equity]]/(Table2[[#This Row],[Market Value of Equity]]+Table2[[#This Row],[Market Value of Debt]]) -> 0.79888361 | V138: =Table2[[#This Row],[Market Value of Debt]]/(Table2[[#This Row],[Market Value of Equity]]+Table2[[#This Row],[Market Value of Debt]]) -> 0.20111639 | W138: =(Table2[[#This Row],[Cost of Equity (Daily Beta)]]*Table2[[#This Row],[Weight of Equity]])+(Table2[[#This Row],[Cost of Debt]]*Table2[[#This Row],[Weight of Debt]]) -> 0.12951499 | X138: =(Table2[[#This Row],[Cost of Equity (Weekly Beta)]]*Table2[[#This Row],[Weight of Equity]])+(Table2[[#This Row],[Cost of Debt]]*Table2[[#This Row],[Weight of Debt]]) -> 0.13609869 | Y138: =(Table2[[#This Row],[Cost of Equity (Monthly Beta)]]*Table2[[#This Row],[Weight of Equity]])+(Table2[[#This Row],[Cost of Debt]]*Table2[[#This Row],[Weight of Debt]]) -> 0.11375952 | Z138: =IF(Table2[[#This Row],[Sector]]="Financial Services",TRUE,FALSE) -> FALSE | AA138: =IF(Table2[[#This Row],[Market Capitalisation In(Cr)]]>25000,TRUE,FALSE) -> FALSE
B139: JGCHEM | C139: =_xlfn.XLOOKUP(B139,stock_analysis[Stock],stock_analysis[Company_Name]) -> J.G.Chemicals Limited | D139: =_xlfn.XLOOKUP(B139,stock_analysis[Stock],stock_analysis[Sector]) -> Basic Materials | E139: =_xlfn.XLOOKUP($B139,stock_analysis[Stock],stock_analysis[Industry]) -> Other Industrial Metals & Mining | F139: =_xlfn.XLOOKUP($B139,stock_analysis[Stock],stock_analysis[Market_Cap_Cr]) -> 1401.0976 | G139: =Imputs!$C$2 -> 0.0667 | H139: =Imputs!$C$3 -> 0.0523 | I139: =_xlfn.XLOOKUP($B139,stock_analysis[Stock],stock_analysis[Beta_Daily]) -> 1.3628379 | J139: =_xlfn.XLOOKUP($B139,stock_analysis[Stock],stock_analysis[Beta_Weekly]) -> 1.2786031 | K139: =_xlfn.XLOOKUP($B139,stock_analysis[Stock],stock_analysis[Beta_Monthly]) -> 1.6744237 | L139: =G139+H139*I139 -> 0.13797642 | M139: =J139*H139+G139 -> 0.13357094 | N139: =K139*H139+G139 -> 0.15427236 | O139: =_xlfn.XLOOKUP($B139,stock_analysis[Stock],stock_analysis[Interest_Coverage_Ratio]) -> 145.53376 | P139: {=CHOOSE( _xlfn.IFS(Table2[[#This Row],[Financial Services ]]=TRUE,2,Table2[[#This Row],[FIRM TYPE]]=TRUE,1,Table2[[#This Row],[FIRM TYPE]]=FALSE,3), _xlfn.CHOOSECOLS(_xlfn._xlws.FILTER(Rating1[],(Table2[[#This Row],[Interest Coverage Ratio]]>Rating1[>])*(Table2[[#This Row],[Interest Coverage Ratio]]<Rating1[≤ to])),4), _xlfn.CHOOSECOLS(_xlfn._xlws.FILTER(Rating2[],(Table2[[#This Row],[Interest Coverage Ratio]]>Rating2[greater than])*(Table2[[#This Row],[Interest Coverage Ratio]]<Rating2[≤ to])),4), _xlfn.CHOOSECOLS(_xlfn._xlws.FILTER(Rating3[],(Table2[[#This Row],[Interest Coverage Ratio]]>Rating3[greater than])*(Table2[[#This Row],[Interest Coverage Ratio]]<Rating3[≤ to])),4) )} -> 0.004 | Q139: {=CHOOSE( _xlfn.IFS(Table2[[#This Row],[Financial Services ]]=TRUE,2,Table2[[#This Row],[FIRM TYPE]]=TRUE,1,Table2[[#This Row],[FIRM TYPE]]=FALSE,3), _xlfn.CHOOSECOLS(_xlfn._xlws.FILTER(Rating1[],(Table2[[#This Row],[Interest Coverage Ratio]]>Rating1[>])*(Table2[[#This Row],[Interest Coverage Ratio]]<Rating1[≤ to])),3), _xlfn.CHOOSECOLS(_xlfn._xlws.FILTER(Rating2[],(Table2[[#This Row],[Interest Coverage Ratio]]>Rating2[greater than])*(Table2[[#This Row],[Interest Coverage Ratio]]<Rating2[≤ to])),3), _xlfn.CHOOSECOLS(_xlfn._xlws.FILTER(Rating3[],(Table2[[#This Row],[Interest Coverage Ratio]]>Rating3[greater than])*(Table2[[#This Row],[Interest Coverage Ratio]]<Rating3[≤ to])),3) )} -> Aaa/AAA | R139: =Table2[[#This Row],[Default Spread]]+Table2[[#This Row],[Risk Free Rate]] -> 0.0707 | S139: =_xlfn.XLOOKUP($B139,stock_analysis[Stock],stock_analysis[Market_Cap_Cr]) -> 1401.0976 | T139: =_xlfn.XLOOKUP($B139,stock_analysis[Stock],stock_analysis[Total_Debt_Cr]) -> 5.108 | U139: =Table2[[#This Row],[Market Value of Equity]]/(Table2[[#This Row],[Market Value of Equity]]+Table2[[#This Row],[Market Value of Debt]]) -> 0.99636753 | V139: =Table2[[#This Row],[Market Value of Debt]]/(Table2[[#This Row],[Market Value of Equity]]+Table2[[#This Row],[Market Value of Debt]]) -> 0.0036324702 | W139: =(Table2[[#This Row],[Cost of Equity (Daily Beta)]]*Table2[[#This Row],[Weight of Equity]])+(Table2[[#This Row],[Cost of Debt]]*Table2[[#This Row],[Weight of Debt]]) -> 0.13773204 | X139: =(Table2[[#This Row],[Cost of Equity (Weekly Beta)]]*Table2[[#This Row],[Weight of Equity]])+(Table2[[#This Row],[Cost of Debt]]*Table2[[#This Row],[Weight of Debt]]) -> 0.13334257 | Y139: =(Table2[[#This Row],[Cost of Equity (Monthly Beta)]]*Table2[[#This Row],[Weight of Equity]])+(Table2[[#This Row],[Cost of Debt]]*Table2[[#This Row],[Weight of Debt]]) -> 0.15396878 | Z139: =IF(Table2[[#This Row],[Sector]]="Financial Services",TRUE,FALSE) -> FALSE | AA139: =IF(Table2[[#This Row],[Market Capitalisation In(Cr)]]>25000,TRUE,FALSE) -> FALSE
B140: ORISSAMINE | C140: =_xlfn.XLOOKUP(B140,stock_analysis[Stock],stock_analysis[Company_Name]) -> The Orissa Minerals Development Company Limited | D140: =_xlfn.XLOOKUP(B140,stock_analysis[Stock],stock_analysis[Sector]) -> Basic Materials | E140: =_xlfn.XLOOKUP($B140,stock_analysis[Stock],stock_analysis[Industry]) -> Other Industrial Metals & Mining | F140: =_xlfn.XLOOKUP($B140,stock_analysis[Stock],stock_analysis[Market_Cap_Cr]) -> 2309.2799 | G140: =Imputs!$C$2 -> 0.0667 | H140: =Imputs!$C$3 -> 0.0523 | I140: =_xlfn.XLOOKUP($B140,stock_analysis[Stock],stock_analysis[Beta_Daily]) -> 1.4853051 | J140: =_xlfn.XLOOKUP($B140,stock_analysis[Stock],stock_analysis[Beta_Weekly]) -> 1.7691725 | K140: =_xlfn.XLOOKUP($B140,stock_analysis[Stock],stock_analysis[Beta_Monthly]) -> 1.5582965 | L140: =G140+H140*I140 -> 0.14438146 | M140: =J140*H140+G140 -> 0.15922772 | N140: =K140*H140+G140 -> 0.14819891 | O140: =_xlfn.XLOOKUP($B140,stock_analysis[Stock],stock_analysis[Interest_Coverage_Ratio]) -> -1.159813 | P140: {=CHOOSE( _xlfn.IFS(Table2[[#This Row],[Financial Services ]]=TRUE,2,Table2[[#This Row],[FIRM TYPE]]=TRUE,1,Table2[[#This Row],[FIRM TYPE]]=FALSE,3), _xlfn.CHOOSECOLS(_xlfn._xlws.FILTER(Rating1[],(Table2[[#This Row],[Interest Coverage Ratio]]>Rating1[>])*(Table2[[#This Row],[Interest Coverage Ratio]]<Rating1[≤ to])),4), _xlfn.CHOOSECOLS(_xlfn._xlws.FILTER(Rating2[],(Table2[[#This Row],[Interest Coverage Ratio]]>Rating2[greater than])*(Table2[[#This Row],[Interest Coverage Ratio]]<Rating2[≤ to])),4), _xlfn.CHOOSECOLS(_xlfn._xlws.FILTER(Rating3[],(Table2[[#This Row],[Interest Coverage Ratio]]>Rating3[greater than])*(Table2[[#This Row],[Interest Coverage Ratio]]<Rating3[≤ to])),4) )} -> 0.19 | Q140: {=CHOOSE( _xlfn.IFS(Table2[[#This Row],[Financial Services ]]=TRUE,2,Table2[[#This Row],[FIRM TYPE]]=TRUE,1,Table2[[#This Row],[FIRM TYPE]]=FALSE,3), _xlfn.CHOOSECOLS(_xlfn._xlws.FILTER(Rating1[],(Table2[[#This Row],[Interest Coverage Ratio]]>Rating1[>])*(Table2[[#This Row],[Interest Coverage Ratio]]<Rating1[≤ to])),3), _xlfn.CHOOSECOLS(_xlfn._xlws.FILTER(Rating2[],(Table2[[#This Row],[Interest Coverage Ratio]]>Rating2[greater than])*(Table2[[#This Row],[Interest Coverage Ratio]]<Rating2[≤ to])),3), _xlfn.CHOOSECOLS(_xlfn._xlws.FILTER(Rating3[],(Table2[[#This Row],[Interest Coverage Ratio]]>Rating3[greater than])*(Table2[[#This Row],[Interest Coverage Ratio]]<Rating3[≤ to])),3) )} -> D2/D | R140: =Table2[[#This Row],[Default Spread]]+Table2[[#This Row],[Risk Free Rate]] -> 0.2567 | S140: =_xlfn.XLOOKUP($B140,stock_analysis[Stock],stock_analysis[Market_Cap_Cr]) -> 2309.2799 | T140: =_xlfn.XLOOKUP($B140,stock_analysis[Stock],stock_analysis[Total_Debt_Cr]) -> 7.9416 | U140: =Table2[[#This Row],[Market Value of Equity]]/(Table2[[#This Row],[Market Value of Equity]]+Table2[[#This Row],[Market Value of Debt]]) -> 0.99657279 | V140: =Table2[[#This Row],[Market Value of Debt]]/(Table2[[#This Row],[Market Value of Equity]]+Table2[[#This Row],[Market Value of Debt]]) -> 0.0034272079 | W140: =(Table2[[#This Row],[Cost of Equity (Daily Beta)]]*Table2[[#This Row],[Weight of Equity]])+(Table2[[#This Row],[Cost of Debt]]*Table2[[#This Row],[Weight of Debt]]) -> 0.1447664 | X140: =(Table2[[#This Row],[Cost of Equity (Weekly Beta)]]*Table2[[#This Row],[Weight of Equity]])+(Table2[[#This Row],[Cost of Debt]]*Table2[[#This Row],[Weight of Debt]]) -> 0.15956178 | Y140: =(Table2[[#This Row],[Cost of Equity (Monthly Beta)]]*Table2[[#This Row],[Weight of Equity]])+(Table2[[#This Row],[Cost of Debt]]*Table2[[#This Row],[Weight of Debt]]) -> 0.14857076 | Z140: =IF(Table2[[#This Row],[Sector]]="Financial Services",TRUE,FALSE) -> FALSE | AA140: =IF(Table2[[#This Row],[Market Capitalisation In(Cr)]]>25000,TRUE,FALSE) -> FALSE
B141: IMPEXFERRO | C141: =_xlfn.XLOOKUP(B141,stock_analysis[Stock],stock_analysis[Company_Name]) -> Impex Ferro Tech Limited | D141: =_xlfn.XLOOKUP(B141,stock_analysis[Stock],stock_analysis[Sector]) -> Basic Materials | E141: =_xlfn.XLOOKUP($B141,stock_analysis[Stock],stock_analysis[Industry]) -> Other Industrial Metals & Mining | F141: =_xlfn.XLOOKUP($B141,stock_analysis[Stock],stock_analysis[Market_Cap_Cr]) -> 14.742726 | G141: =Imputs!$C$2 -> 0.0667 | H141: =Imputs!$C$3 -> 0.0523 | I141: =_xlfn.XLOOKUP($B141,stock_analysis[Stock],stock_analysis[Beta_Daily]) -> 0.14735074 | J141: =_xlfn.XLOOKUP($B141,stock_analysis[Stock],stock_analysis[Beta_Weekly]) -> 0.81601074 | K141: =_xlfn.XLOOKUP($B141,stock_analysis[Stock],stock_analysis[Beta_Monthly]) -> -0.90045759 | L141: =G141+H141*I141 -> 0.074406444 | M141: =J141*H141+G141 -> 0.10937736 | N141: =K141*H141+G141 -> 0.019606068 | O141: =_xlfn.XLOOKUP($B141,stock_analysis[Stock],stock_analysis[Interest_Coverage_Ratio]) -> -4415.1875 | P141: {=CHOOSE( _xlfn.IFS(Table2[[#This Row],[Financial Services ]]=TRUE,2,Table2[[#This Row],[FIRM TYPE]]=TRUE,1,Table2[[#This Row],[FIRM TYPE]]=FALSE,3), _xlfn.CHOOSECOLS(_xlfn._xlws.FILTER(Rating1[],(Table2[[#This Row],[Interest Coverage Ratio]]>Rating1[>])*(Table2[[#This Row],[Interest Coverage Ratio]]<Rating1[≤ to])),4), _xlfn.CHOOSECOLS(_xlfn._xlws.FILTER(Rating2[],(Table2[[#This Row],[Interest Coverage Ratio]]>Rating2[greater than])*(Table2[[#This Row],[Interest Coverage Ratio]]<Rating2[≤ to])),4), _xlfn.CHOOSECOLS(_xlfn._xlws.FILTER(Rating3[],(Table2[[#This Row],[Interest Coverage Ratio]]>Rating3[greater than])*(Table2[[#This Row],[Interest Coverage Ratio]]<Rating3[≤ to])),4) )} -> 0.19 | Q141: {=CHOOSE( _xlfn.IFS(Table2[[#This Row],[Financial Services ]]=TRUE,2,Table2[[#This Row],[FIRM TYPE]]=TRUE,1,Table2[[#This Row],[FIRM TYPE]]=FALSE,3), _xlfn.CHOOSECOLS(_xlfn._xlws.FILTER(Rating1[],(Table2[[#This Row],[Interest Coverage Ratio]]>Rating1[>])*(Table2[[#This Row],[Interest Coverage Ratio]]<Rating1[≤ to])),3), _xlfn.CHOOSECOLS(_xlfn._xlws.FILTER(Rating2[],(Table2[[#This Row],[Interest Coverage Ratio]]>Rating2[greater than])*(Table2[[#This Row],[Interest Coverage Ratio]]<Rating2[≤ to])),3), _xlfn.CHOOSECOLS(_xlfn._xlws.FILTER(Rating3[],(Table2[[#This Row],[Interest Coverage Ratio]]>Rating3[greater than])*(Table2[[#This Row],[Interest Coverage Ratio]]<Rating3[≤ to])),3) )} -> D2/D | R141: =Table2[[#This Row],[Default Spread]]+Table2[[#This Row],[Risk Free Rate]] -> 0.2567 | S141: =_xlfn.XLOOKUP($B141,stock_analysis[Stock],stock_analysis[Market_Cap_Cr]) -> 14.742726 | T141: =_xlfn.XLOOKUP($B141,stock_analysis[Stock],stock_analysis[Total_Debt_Cr]) -> 267.68599 | U141: =Table2[[#This Row],[Market Value of Equity]]/(Table2[[#This Row],[Market Value of Equity]]+Table2[[#This Row],[Market Value of Debt]]) -> 0.052199814 | V141: =Table2[[#This Row],[Market Value of Debt]]/(Table2[[#This Row],[Market Value of Equity]]+Table2[[#This Row],[Market Value of Debt]]) -> 0.94780019 | W141: =(Table2[[#This Row],[Cost of Equity (Daily Beta)]]*Table2[[#This Row],[Weight of Equity]])+(Table2[[#This Row],[Cost of Debt]]*Table2[[#This Row],[Weight of Debt]]) -> 0.24718431 | X141: =(Table2[[#This Row],[Cost of Equity (Weekly Beta)]]*Table2[[#This Row],[Weight of Equity]])+(Table2[[#This Row],[Cost of Debt]]*Table2[[#This Row],[Weight of Debt]]) -> 0.24900979 | Y141: =(Table2[[#This Row],[Cost of Equity (Monthly Beta)]]*Table2[[#This Row],[Weight of Equity]])+(Table2[[#This Row],[Cost of Debt]]*Table2[[#This Row],[Weight of Debt]]) -> 0.24432374 | Z141: =IF(Table2[[#This Row],[Sector]]="Financial Services",TRUE,FALSE) -> FALSE | AA141: =IF(Table2[[#This Row],[Market Capitalisation In(Cr)]]>25000,TRUE,FALSE) -> FALSE
B142: IGIL | C142: =_xlfn.XLOOKUP(B142,stock_analysis[Stock],stock_analysis[Company_Name]) -> International Gemmological Institute (India) Limited | D142: =_xlfn.XLOOKUP(B142,stock_analysis[Stock],stock_analysis[Sector]) -> Basic Materials | E142: =_xlfn.XLOOKUP($B142,stock_analysis[Stock],stock_analysis[Industry]) -> Other Precious Metals & Mining | F142: =_xlfn.XLOOKUP($B142,stock_analysis[Stock],stock_analysis[Market_Cap_Cr]) -> 14045.189 | G142: =Imputs!$C$2 -> 0.0667 | H142: =Imputs!$C$3 -> 0.0523 | I142: =_xlfn.XLOOKUP($B142,stock_analysis[Stock],stock_analysis[Beta_Daily]) -> 1.400404 | J142: =_xlfn.XLOOKUP($B142,stock_analysis[Stock],stock_analysis[Beta_Weekly]) -> 1.5554222 | K142: =_xlfn.XLOOKUP($B142,stock_analysis[Stock],stock_analysis[Beta_Monthly]) -> 0.64590939 | L142: =G142+H142*I142 -> 0.13994113 | M142: =J142*H142+G142 -> 0.14804858 | N142: =K142*H142+G142 -> 0.10048106 | O142: =_xlfn.XLOOKUP($B142,stock_analysis[Stock],stock_analysis[Interest_Coverage_Ratio]) -> 75.850128 | P142: {=CHOOSE( _xlfn.IFS(Table2[[#This Row],[Financial Services ]]=TRUE,2,Table2[[#This Row],[FIRM TYPE]]=TRUE,1,Table2[[#This Row],[FIRM TYPE]]=FALSE,3), _xlfn.CHOOSECOLS(_xlfn._xlws.FILTER(Rating1[],(Table2[[#This Row],[Interest Coverage Ratio]]>Rating1[>])*(Table2[[#This Row],[Interest Coverage Ratio]]<Rating1[≤ to])),4), _xlfn.CHOOSECOLS(_xlfn._xlws.FILTER(Rating2[],(Table2[[#This Row],[Interest Coverage Ratio]]>Rating2[greater than])*(Table2[[#This Row],[Interest Coverage Ratio]]<Rating2[≤ to])),4), _xlfn.CHOOSECOLS(_xlfn._xlws.FILTER(Rating3[],(Table2[[#This Row],[Interest Coverage Ratio]]>Rating3[greater than])*(Table2[[#This Row],[Interest Coverage Ratio]]<Rating3[≤ to])),4) )} -> 0.004 | Q142: {=CHOOSE( _xlfn.IFS(Table2[[#This Row],[Financial Services ]]=TRUE,2,Table2[[#This Row],[FIRM TYPE]]=TRUE,1,Table2[[#This Row],[FIRM TYPE]]=FALSE,3), _xlfn.CHOOSECOLS(_xlfn._xlws.FILTER(Rating1[],(Table2[[#This Row],[Interest Coverage Ratio]]>Rating1[>])*(Table2[[#This Row],[Interest Coverage Ratio]]<Rating1[≤ to])),3), _xlfn.CHOOSECOLS(_xlfn._xlws.FILTER(Rating2[],(Table2[[#This Row],[Interest Coverage Ratio]]>Rating2[greater than])*(Table2[[#This Row],[Interest Coverage Ratio]]<Rating2[≤ to])),3), _xlfn.CHOOSECOLS(_xlfn._xlws.FILTER(Rating3[],(Table2[[#This Row],[Interest Coverage Ratio]]>Rating3[greater than])*(Table2[[#This Row],[Interest Coverage Ratio]]<Rating3[≤ to])),3) )} -> Aaa/AAA | R142: =Table2[[#This Row],[Default Spread]]+Table2[[#This Row],[Risk Free Rate]] -> 0.0707 | S142: =_xlfn.XLOOKUP($B142,stock_analysis[Stock],stock_analysis[Market_Cap_Cr]) -> 14045.189 | T142: =_xlfn.XLOOKUP($B142,stock_analysis[Stock],stock_analysis[Total_Debt_Cr]) -> 142.603 | U142: =Table2[[#This Row],[Market Value of Equity]]/(Table2[[#This Row],[Market Value of Equity]]+Table2[[#This Row],[Market Value of Debt]]) -> 0.98994889 | V142: =Table2[[#This Row],[Market Value of Debt]]/(Table2[[#This Row],[Market Value of Equity]]+Table2[[#This Row],[Market Value of Debt]]) -> 0.010051106 | W142: =(Table2[[#This Row],[Cost of Equity (Daily Beta)]]*Table2[[#This Row],[Weight of Equity]])+(Table2[[#This Row],[Cost of Debt]]*Table2[[#This Row],[Weight of Debt]]) -> 0.13924518 | X142: =(Table2[[#This Row],[Cost of Equity (Weekly Beta)]]*Table2[[#This Row],[Weight of Equity]])+(Table2[[#This Row],[Cost of Debt]]*Table2[[#This Row],[Weight of Debt]]) -> 0.14727114 | Y142: =(Table2[[#This Row],[Cost of Equity (Monthly Beta)]]*Table2[[#This Row],[Weight of Equity]])+(Table2[[#This Row],[Cost of Debt]]*Table2[[#This Row],[Weight of Debt]]) -> 0.10018173 | Z142: =IF(Table2[[#This Row],[Sector]]="Financial Services",TRUE,FALSE) -> FALSE | AA142: =IF(Table2[[#This Row],[Market Capitalisation In(Cr)]]>25000,TRUE,FALSE) -> FALSE
B143: SHREYANIND | C143: =_xlfn.XLOOKUP(B143,stock_analysis[Stock],stock_analysis[Company_Name]) -> Shreyans Industries Limited | D143: =_xlfn.XLOOKUP(B143,stock_analysis[Stock],stock_analysis[Sector]) -> Basic Materials | E143: =_xlfn.XLOOKUP($B143,stock_analysis[Stock],stock_analysis[Industry]) -> Paper & Paper Products | F143: =_xlfn.XLOOKUP($B143,stock_analysis[Stock],stock_analysis[Market_Cap_Cr]) -> 207.26601 | G143: =Imputs!$C$2 -> 0.0667 | H143: =Imputs!$C$3 -> 0.0523 | I143: =_xlfn.XLOOKUP($B143,stock_analysis[Stock],stock_analysis[Beta_Daily]) -> 0.63166396 | J143: =_xlfn.XLOOKUP($B143,stock_analysis[Stock],stock_analysis[Beta_Weekly]) -> 0.72063772 | K143: =_xlfn.XLOOKUP($B143,stock_analysis[Stock],stock_analysis[Beta_Monthly]) -> 1.4045037 | L143: =G143+H143*I143 -> 0.099736025 | M143: =J143*H143+G143 -> 0.10438935 | N143: =K143*H143+G143 -> 0.14015555 | O143: =_xlfn.XLOOKUP($B143,stock_analysis[Stock],stock_analysis[Interest_Coverage_Ratio]) -> 19.049367 | P143: {=CHOOSE( _xlfn.IFS(Table2[[#This Row],[Financial Services ]]=TRUE,2,Table2[[#This Row],[FIRM TYPE]]=TRUE,1,Table2[[#This Row],[FIRM TYPE]]=FALSE,3), _xlfn.CHOOSECOLS(_xlfn._xlws.FILTER(Rating1[],(Table2[[#This Row],[Interest Coverage Ratio]]>Rating1[>])*(Table2[[#This Row],[Interest Coverage Ratio]]<Rating1[≤ to])),4), _xlfn.CHOOSECOLS(_xlfn._xlws.FILTER(Rating2[],(Table2[[#This Row],[Interest Coverage Ratio]]>Rating2[greater than])*(Table2[[#This Row],[Interest Coverage Ratio]]<Rating2[≤ to])),4), _xlfn.CHOOSECOLS(_xlfn._xlws.FILTER(Rating3[],(Table2[[#This Row],[Interest Coverage Ratio]]>Rating3[greater than])*(Table2[[#This Row],[Interest Coverage Ratio]]<Rating3[≤ to])),4) )} -> 0.004 | Q143: {=CHOOSE( _xlfn.IFS(Table2[[#This Row],[Financial Services ]]=TRUE,2,Table2[[#This Row],[FIRM TYPE]]=TRUE,1,Table2[[#This Row],[FIRM TYPE]]=FALSE,3), _xlfn.CHOOSECOLS(_xlfn._xlws.FILTER(Rating1[],(Table2[[#This Row],[Interest Coverage Ratio]]>Rating1[>])*(Table2[[#This Row],[Interest Coverage Ratio]]<Rating1[≤ to])),3), _xlfn.CHOOSECOLS(_xlfn._xlws.FILTER(Rating2[],(Table2[[#This Row],[Interest Coverage Ratio]]>Rating2[greater than])*(Table2[[#This Row],[Interest Coverage Ratio]]<Rating2[≤ to])),3), _xlfn.CHOOSECOLS(_xlfn._xlws.FILTER(Rating3[],(Table2[[#This Row],[Interest Coverage Ratio]]>Rating3[greater than])*(Table2[[#This Row],[Interest Coverage Ratio]]<Rating3[≤ to])),3) )} -> Aaa/AAA | R143: =Table2[[#This Row],[Default Spread]]+Table2[[#This Row],[Risk Free Rate]] -> 0.0707 | S143: =_xlfn.XLOOKUP($B143,stock_analysis[Stock],stock_analysis[Market_Cap_Cr]) -> 207.26601 | T143: =_xlfn.XLOOKUP($B143,stock_analysis[Stock],stock_analysis[Total_Debt_Cr]) -> 57.285901 | U143: =Table2[[#This Row],[Market Value of Equity]]/(Table2[[#This Row],[Market Value of Equity]]+Table2[[#This Row],[Market Value of Debt]]) -> 0.78346064 | V143: =Table2[[#This Row],[Market Value of Debt]]/(Table2[[#This Row],[Market Value of Equity]]+Table2[[#This Row],[Market Value of Debt]]) -> 0.21653936 | W143: =(Table2[[#This Row],[Cost of Equity (Daily Beta)]]*Table2[[#This Row],[Weight of Equity]])+(Table2[[#This Row],[Cost of Debt]]*Table2[[#This Row],[Weight of Debt]]) -> 0.093448583 | X143: =(Table2[[#This Row],[Cost of Equity (Weekly Beta)]]*Table2[[#This Row],[Weight of Equity]])+(Table2[[#This Row],[Cost of Debt]]*Table2[[#This Row],[Weight of Debt]]) -> 0.097094282 | Y143: =(Table2[[#This Row],[Cost of Equity (Monthly Beta)]]*Table2[[#This Row],[Weight of Equity]])+(Table2[[#This Row],[Cost of Debt]]*Table2[[#This Row],[Weight of Debt]]) -> 0.12511569 | Z143: =IF(Table2[[#This Row],[Sector]]="Financial Services",TRUE,FALSE) -> FALSE | AA143: =IF(Table2[[#This Row],[Market Capitalisation In(Cr)]]>25000,TRUE,FALSE) -> FALSE
B144: KUANTUM | C144: =_xlfn.XLOOKUP(B144,stock_analysis[Stock],stock_analysis[Company_Name]) -> Kuantum Papers Limited | D144: =_xlfn.XLOOKUP(B144,stock_analysis[Stock],stock_analysis[Sector]) -> Basic Materials | E144: =_xlfn.XLOOKUP($B144,stock_analysis[Stock],stock_analysis[Industry]) -> Paper & Paper Products | F144: =_xlfn.XLOOKUP($B144,stock_analysis[Stock],stock_analysis[Market_Cap_Cr]) -> 729.96029 | G144: =Imputs!$C$2 -> 0.0667 | H144: =Imputs!$C$3 -> 0.0523 | I144: =_xlfn.XLOOKUP($B144,stock_analysis[Stock],stock_analysis[Beta_Daily]) -> 1.0637325 | J144: =_xlfn.XLOOKUP($B144,stock_analysis[Stock],stock_analysis[Beta_Weekly]) -> 1.3005072 | K144: =_xlfn.XLOOKUP($B144,stock_analysis[Stock],stock_analysis[Beta_Monthly]) -> 0.97737847 | L144: =G144+H144*I144 -> 0.12233321 | M144: =J144*H144+G144 -> 0.13471652 | N144: =K144*H144+G144 -> 0.11781689 | O144: =_xlfn.XLOOKUP($B144,stock_analysis[Stock],stock_analysis[Interest_Coverage_Ratio]) -> 5.1377282 | P144: {=CHOOSE( _xlfn.IFS(Table2[[#This Row],[Financial Services ]]=TRUE,2,Table2[[#This Row],[FIRM TYPE]]=TRUE,1,Table2[[#This Row],[FIRM TYPE]]=FALSE,3), _xlfn.CHOOSECOLS(_xlfn._xlws.FILTER(Rating1[],(Table2[[#This Row],[Interest Coverage Ratio]]>Rating1[>])*(Table2[[#This Row],[Interest Coverage Ratio]]<Rating1[≤ to])),4), _xlfn.CHOOSECOLS(_xlfn._xlws.FILTER(Rating2[],(Table2[[#This Row],[Interest Coverage Ratio]]>Rating2[greater than])*(Table2[[#This Row],[Interest Coverage Ratio]]<Rating2[≤ to])),4), _xlfn.CHOOSECOLS(_xlfn._xlws.FILTER(Rating3[],(Table2[[#This Row],[Interest Coverage Ratio]]>Rating3[greater than])*(Table2[[#This Row],[Interest Coverage Ratio]]<Rating3[≤ to])),4) )} -> 0.0089 | Q144: {=CHOOSE( _xlfn.IFS(Table2[[#This Row],[Financial Services ]]=TRUE,2,Table2[[#This Row],[FIRM TYPE]]=TRUE,1,Table2[[#This Row],[FIRM TYPE]]=FALSE,3), _xlfn.CHOOSECOLS(_xlfn._xlws.FILTER(Rating1[],(Table2[[#This Row],[Interest Coverage Ratio]]>Rating1[>])*(Table2[[#This Row],[Interest Coverage Ratio]]<Rating1[≤ to])),3), _xlfn.CHOOSECOLS(_xlfn._xlws.FILTER(Rating2[],(Table2[[#This Row],[Interest Coverage Ratio]]>Rating2[greater than])*(Table2[[#This Row],[Interest Coverage Ratio]]<Rating2[≤ to])),3), _xlfn.CHOOSECOLS(_xlfn._xlws.FILTER(Rating3[],(Table2[[#This Row],[Interest Coverage Ratio]]>Rating3[greater than])*(Table2[[#This Row],[Interest Coverage Ratio]]<Rating3[≤ to])),3) )} -> A3/A- | R144: =Table2[[#This Row],[Default Spread]]+Table2[[#This Row],[Risk Free Rate]] -> 0.0756 | S144: =_xlfn.XLOOKUP($B144,stock_analysis[Stock],stock_analysis[Market_Cap_Cr]) -> 729.96029 | T144: =_xlfn.XLOOKUP($B144,stock_analysis[Stock],stock_analysis[Total_Debt_Cr]) -> 677.66001 | U144: =Table2[[#This Row],[Market Value of Equity]]/(Table2[[#This Row],[Market Value of Equity]]+Table2[[#This Row],[Market Value of Debt]]) -> 0.51857756 | V144: =Table2[[#This Row],[Market Value of Debt]]/(Table2[[#This Row],[Market Value of Equity]]+Table2[[#This Row],[Market Value of Debt]]) -> 0.48142244 | W144: =(Table2[[#This Row],[Cost of Equity (Daily Beta)]]*Table2[[#This Row],[Weight of Equity]])+(Table2[[#This Row],[Cost of Debt]]*Table2[[#This Row],[Weight of Debt]]) -> 0.099834795 | X144: =(Table2[[#This Row],[Cost of Equity (Weekly Beta)]]*Table2[[#This Row],[Weight of Equity]])+(Table2[[#This Row],[Cost of Debt]]*Table2[[#This Row],[Weight of Debt]]) -> 0.1062565 | Y144: =(Table2[[#This Row],[Cost of Equity (Monthly Beta)]]*Table2[[#This Row],[Weight of Equity]])+(Table2[[#This Row],[Cost of Debt]]*Table2[[#This Row],[Weight of Debt]]) -> 0.097492734 | Z144: =IF(Table2[[#This Row],[Sector]]="Financial Services",TRUE,FALSE) -> FALSE | AA144: =IF(Table2[[#This Row],[Market Capitalisation In(Cr)]]>25000,TRUE,FALSE) -> FALSE
B145: SESHAPAPER | C145: =_xlfn.XLOOKUP(B145,stock_analysis[Stock],stock_analysis[Company_Name]) -> Seshasayee Paper and Boards Limited | D145: =_xlfn.XLOOKUP(B145,stock_analysis[Stock],stock_analysis[Sector]) -> Basic Materials | E145: =_xlfn.XLOOKUP($B145,stock_analysis[Stock],stock_analysis[Industry]) -> Paper & Paper Products | F145: =_xlfn.XLOOKUP($B145,stock_analysis[Stock],stock_analysis[Market_Cap_Cr]) -> 1673.1977 | G145: =Imputs!$C$2 -> 0.0667 | H145: =Imputs!$C$3 -> 0.0523 | I145: =_xlfn.XLOOKUP($B145,stock_analysis[Stock],stock_analysis[Beta_Daily]) -> 0.69552875 | J145: =_xlfn.XLOOKUP($B145,stock_analysis[Stock],stock_analysis[Beta_Weekly]) -> 0.98959633 | K145: =_xlfn.XLOOKUP($B145,stock_analysis[Stock],stock_analysis[Beta_Monthly]) -> 0.98427973 | L145: =G145+H145*I145 -> 0.10307615 | M145: =J145*H145+G145 -> 0.11845589 | N145: =K145*H145+G145 -> 0.11817783 | O145: =_xlfn.XLOOKUP($B145,stock_analysis[Stock],stock_analysis[Interest_Coverage_Ratio]) -> 22.663808 | P145: {=CHOOSE( _xlfn.IFS(Table2[[#This Row],[Financial Services ]]=TRUE,2,Table2[[#This Row],[FIRM TYPE]]=TRUE,1,Table2[[#This Row],[FIRM TYPE]]=FALSE,3), _xlfn.CHOOSECOLS(_xlfn._xlws.FILTER(Rating1[],(Table2[[#This Row],[Interest Coverage Ratio]]>Rating1[>])*(Table2[[#This Row],[Interest Coverage Ratio]]<Rating1[≤ to])),4), _xlfn.CHOOSECOLS(_xlfn._xlws.FILTER(Rating2[],(Table2[[#This Row],[Interest Coverage Ratio]]>Rating2[greater than])*(Table2[[#This Row],[Interest Coverage Ratio]]<Rating2[≤ to])),4), _xlfn.CHOOSECOLS(_xlfn._xlws.FILTER(Rating3[],(Table2[[#This Row],[Interest Coverage Ratio]]>Rating3[greater than])*(Table2[[#This Row],[Interest Coverage Ratio]]<Rating3[≤ to])),4) )} -> 0.004 | Q145: {=CHOOSE( _xlfn.IFS(Table2[[#This Row],[Financial Services ]]=TRUE,2,Table2[[#This Row],[FIRM TYPE]]=TRUE,1,Table2[[#This Row],[FIRM TYPE]]=FALSE,3), _xlfn.CHOOSECOLS(_xlfn._xlws.FILTER(Rating1[],(Table2[[#This Row],[Interest Coverage Ratio]]>Rating1[>])*(Table2[[#This Row],[Interest Coverage Ratio]]<Rating1[≤ to])),3), _xlfn.CHOOSECOLS(_xlfn._xlws.FILTER(Rating2[],(Table2[[#This Row],[Interest Coverage Ratio]]>Rating2[greater than])*(Table2[[#This Row],[Interest Coverage Ratio]]<Rating2[≤ to])),3), _xlfn.CHOOSECOLS(_xlfn._xlws.FILTER(Rating3[],(Table2[[#This Row],[Interest Coverage Ratio]]>Rating3[greater than])*(Table2[[#This Row],[Interest Coverage Ratio]]<Rating3[≤ to])),3) )} -> Aaa/AAA | R145: =Table2[[#This Row],[Default Spread]]+Table2[[#This Row],[Risk Free Rate]] -> 0.0707 | S145: =_xlfn.XLOOKUP($B145,stock_analysis[Stock],stock_analysis[Market_Cap_Cr]) -> 1673.1977 | T145: =_xlfn.XLOOKUP($B145,stock_analysis[Stock],stock_analysis[Total_Debt_Cr]) -> 76.750003 | U145: =Table2[[#This Row],[Market Value of Equity]]/(Table2[[#This Row],[Market Value of Equity]]+Table2[[#This Row],[Market Value of Debt]]) -> 0.95614154 | V145: =Table2[[#This Row],[Market Value of Debt]]/(Table2[[#This Row],[Market Value of Equity]]+Table2[[#This Row],[Market Value of Debt]]) -> 0.043858456 | W145: =(Table2[[#This Row],[Cost of Equity (Daily Beta)]]*Table2[[#This Row],[Weight of Equity]])+(Table2[[#This Row],[Cost of Debt]]*Table2[[#This Row],[Weight of Debt]]) -> 0.10165619 | X145: =(Table2[[#This Row],[Cost of Equity (Weekly Beta)]]*Table2[[#This Row],[Weight of Equity]])+(Table2[[#This Row],[Cost of Debt]]*Table2[[#This Row],[Weight of Debt]]) -> 0.11636139 | Y145: =(Table2[[#This Row],[Cost of Equity (Monthly Beta)]]*Table2[[#This Row],[Weight of Equity]])+(Table2[[#This Row],[Cost of Debt]]*Table2[[#This Row],[Weight of Debt]]) -> 0.11609553 | Z145: =IF(Table2[[#This Row],[Sector]]="Financial Services",TRUE,FALSE) -> FALSE | AA145: =IF(Table2[[#This Row],[Market Capitalisation In(Cr)]]>25000,TRUE,FALSE) -> FALSE
B146: RUCHIRA | C146: =_xlfn.XLOOKUP(B146,stock_analysis[Stock],stock_analysis[Company_Name]) -> Ruchira Papers Limited | D146: =_xlfn.XLOOKUP(B146,stock_analysis[Stock],stock_analysis[Sector]) -> Basic Materials | E146: =_xlfn.XLOOKUP($B146,stock_analysis[Stock],stock_analysis[Industry]) -> Paper & Paper Products | F146: =_xlfn.XLOOKUP($B146,stock_analysis[Stock],stock_analysis[Market_Cap_Cr]) -> 319.04289 | G146: =Imputs!$C$2 -> 0.0667 | H146: =Imputs!$C$3 -> 0.0523 | I146: =_xlfn.XLOOKUP($B146,stock_analysis[Stock],stock_analysis[Beta_Daily]) -> 1.1343141 | J146: =_xlfn.XLOOKUP($B146,stock_analysis[Stock],stock_analysis[Beta_Weekly]) -> 1.075032 | K146: =_xlfn.XLOOKUP($B146,stock_analysis[Stock],stock_analysis[Beta_Monthly]) -> 0.76255907 | L146: =G146+H146*I146 -> 0.12602463 | M146: =J146*H146+G146 -> 0.12292418 | N146: =K146*H146+G146 -> 0.10658184 | O146: =_xlfn.XLOOKUP($B146,stock_analysis[Stock],stock_analysis[Interest_Coverage_Ratio]) -> 24.055404 | P146: {=CHOOSE( _xlfn.IFS(Table2[[#This Row],[Financial Services ]]=TRUE,2,Table2[[#This Row],[FIRM TYPE]]=TRUE,1,Table2[[#This Row],[FIRM TYPE]]=FALSE,3), _xlfn.CHOOSECOLS(_xlfn._xlws.FILTER(Rating1[],(Table2[[#This Row],[Interest Coverage Ratio]]>Rating1[>])*(Table2[[#This Row],[Interest Coverage Ratio]]<Rating1[≤ to])),4), _xlfn.CHOOSECOLS(_xlfn._xlws.FILTER(Rating2[],(Table2[[#This Row],[Interest Coverage Ratio]]>Rating2[greater than])*(Table2[[#This Row],[Interest Coverage Ratio]]<Rating2[≤ to])),4), _xlfn.CHOOSECOLS(_xlfn._xlws.FILTER(Rating3[],(Table2[[#This Row],[Interest Coverage Ratio]]>Rating3[greater than])*(Table2[[#This Row],[Interest Coverage Ratio]]<Rating3[≤ to])),4) )} -> 0.004 | Q146: {=CHOOSE( _xlfn.IFS(Table2[[#This Row],[Financial Services ]]=TRUE,2,Table2[[#This Row],[FIRM TYPE]]=TRUE,1,Table2[[#This Row],[FIRM TYPE]]=FALSE,3), _xlfn.CHOOSECOLS(_xlfn._xlws.FILTER(Rating1[],(Table2[[#This Row],[Interest Coverage Ratio]]>Rating1[>])*(Table2[[#This Row],[Interest Coverage Ratio]]<Rating1[≤ to])),3), _xlfn.CHOOSECOLS(_xlfn._xlws.FILTER(Rating2[],(Table2[[#This Row],[Interest Coverage Ratio]]>Rating2[greater than])*(Table2[[#This Row],[Interest Coverage Ratio]]<Rating2[≤ to])),3), _xlfn.CHOOSECOLS(_xlfn._xlws.FILTER(Rating3[],(Table2[[#This Row],[Interest Coverage Ratio]]>Rating3[greater than])*(Table2[[#This Row],[Interest Coverage Ratio]]<Rating3[≤ to])),3) )} -> Aaa/AAA | R146: =Table2[[#This Row],[Default Spread]]+Table2[[#This Row],[Risk Free Rate]] -> 0.0707 | S146: =_xlfn.XLOOKUP($B146,stock_analysis[Stock],stock_analysis[Market_Cap_Cr]) -> 319.04289 | T146: =_xlfn.XLOOKUP($B146,stock_analysis[Stock],stock_analysis[Total_Debt_Cr]) -> 189.4807 | U146: =Table2[[#This Row],[Market Value of Equity]]/(Table2[[#This Row],[Market Value of Equity]]+Table2[[#This Row],[Market Value of Debt]]) -> 0.62739054 | V146: =Table2[[#This Row],[Market Value of Debt]]/(Table2[[#This Row],[Market Value of Equity]]+Table2[[#This Row],[Market Value of Debt]]) -> 0.37260946 | W146: =(Table2[[#This Row],[Cost of Equity (Daily Beta)]]*Table2[[#This Row],[Weight of Equity]])+(Table2[[#This Row],[Cost of Debt]]*Table2[[#This Row],[Weight of Debt]]) -> 0.10541015 | X146: =(Table2[[#This Row],[Cost of Equity (Weekly Beta)]]*Table2[[#This Row],[Weight of Equity]])+(Table2[[#This Row],[Cost of Debt]]*Table2[[#This Row],[Weight of Debt]]) -> 0.10346495 | Y146: =(Table2[[#This Row],[Cost of Equity (Monthly Beta)]]*Table2[[#This Row],[Weight of Equity]])+(Table2[[#This Row],[Cost of Debt]]*Table2[[#This Row],[Weight of Debt]]) -> 0.093211926 | Z146: =IF(Table2[[#This Row],[Sector]]="Financial Services",TRUE,FALSE) -> FALSE | AA146: =IF(Table2[[#This Row],[Market Capitalisation In(Cr)]]>25000,TRUE,FALSE) -> FALSE
... B1915: GKENERGY | C1915: =_xlfn.XLOOKUP(B1915,stock_analysis[Stock],stock_analysis[Company_Name]) -> GK Energy Limited | D1915: =_xlfn.XLOOKUP(B1915,stock_analysis[Stock],stock_analysis[Sector]) -> Utilities | E1915: =_xlfn.XLOOKUP($B1915,stock_analysis[Stock],stock_analysis[Industry]) -> Utilities - Renewable | F1915: =_xlfn.XLOOKUP($B1915,stock_analysis[Stock],stock_analysis[Market_Cap_Cr]) -> 2031.012 | G1915: =Imputs!$C$2 -> 0.0667 | H1915: =Imputs!$C$3 -> 0.0523 | I1915: =_xlfn.XLOOKUP($B1915,stock_analysis[Stock],stock_analysis[Beta_Daily]) -> 2.7778583 | J1915: =_xlfn.XLOOKUP($B1915,stock_analysis[Stock],stock_analysis[Beta_Weekly]) -> 3.6436647 | K1915: =_xlfn.XLOOKUP($B1915,stock_analysis[Stock],stock_analysis[Beta_Monthly]) -> 1.1681551 | L1915: =G1915+H1915*I1915 -> 0.21198199 | M1915: =J1915*H1915+G1915 -> 0.25726366 | N1915: =K1915*H1915+G1915 -> 0.12779451 | O1915: =_xlfn.XLOOKUP($B1915,stock_analysis[Stock],stock_analysis[Interest_Coverage_Ratio]) -> 10.018009 | P1915: {=CHOOSE( _xlfn.IFS(Table2[[#This Row],[Financial Services ]]=TRUE,2,Table2[[#This Row],[FIRM TYPE]]=TRUE,1,Table2[[#This Row],[FIRM TYPE]]=FALSE,3), _xlfn.CHOOSECOLS(_xlfn._xlws.FILTER(Rating1[],(Table2[[#This Row],[Interest Coverage Ratio]]>Rating1[>])*(Table2[[#This Row],[Interest Coverage Ratio]]<Rating1[≤ to])),4), _xlfn.CHOOSECOLS(_xlfn._xlws.FILTER(Rating2[],(Table2[[#This Row],[Interest Coverage Ratio]]>Rating2[greater than])*(Table2[[#This Row],[Interest Coverage Ratio]]<Rating2[≤ to])),4), _xlfn.CHOOSECOLS(_xlfn._xlws.FILTER(Rating3[],(Table2[[#This Row],[Interest Coverage Ratio]]>Rating3[greater than])*(Table2[[#This Row],[Interest Coverage Ratio]]<Rating3[≤ to])),4) )} -> 0.0055 | Q1915: {=CHOOSE( _xlfn.IFS(Table2[[#This Row],[Financial Services ]]=TRUE,2,Table2[[#This Row],[FIRM TYPE]]=TRUE,1,Table2[[#This Row],[FIRM TYPE]]=FALSE,3), _xlfn.CHOOSECOLS(_xlfn._xlws.FILTER(Rating1[],(Table2[[#This Row],[Interest Coverage Ratio]]>Rating1[>])*(Table2[[#This Row],[Interest Coverage Ratio]]<Rating1[≤ to])),3), _xlfn.CHOOSECOLS(_xlfn._xlws.FILTER(Rating2[],(Table2[[#This Row],[Interest Coverage Ratio]]>Rating2[greater than])*(Table2[[#This Row],[Interest Coverage Ratio]]<Rating2[≤ to])),3), _xlfn.CHOOSECOLS(_xlfn._xlws.FILTER(Rating3[],(Table2[[#This Row],[Interest Coverage Ratio]]>Rating3[greater than])*(Table2[[#This Row],[Interest Coverage Ratio]]<Rating3[≤ to])),3) )} -> Aa2/AA | R1915: =Table2[[#This Row],[Default Spread]]+Table2[[#This Row],[Risk Free Rate]] -> 0.0722 | S1915: =_xlfn.XLOOKUP($B1915,stock_analysis[Stock],stock_analysis[Market_Cap_Cr]) -> 2031.012 | T1915: =_xlfn.XLOOKUP($B1915,stock_analysis[Stock],stock_analysis[Total_Debt_Cr]) -> 423.79599 | U1915: =Table2[[#This Row],[Market Value of Equity]]/(Table2[[#This Row],[Market Value of Equity]]+Table2[[#This Row],[Market Value of Debt]]) -> 0.82736084 | V1915: =Table2[[#This Row],[Market Value of Debt]]/(Table2[[#This Row],[Market Value of Equity]]+Table2[[#This Row],[Market Value of Debt]]) -> 0.17263916 | W1915: =(Table2[[#This Row],[Cost of Equity (Daily Beta)]]*Table2[[#This Row],[Weight of Equity]])+(Table2[[#This Row],[Cost of Debt]]*Table2[[#This Row],[Weight of Debt]]) -> 0.18785014 | X1915: =(Table2[[#This Row],[Cost of Equity (Weekly Beta)]]*Table2[[#This Row],[Weight of Equity]])+(Table2[[#This Row],[Cost of Debt]]*Table2[[#This Row],[Weight of Debt]]) -> 0.22531443 | Y1915: =(Table2[[#This Row],[Cost of Equity (Monthly Beta)]]*Table2[[#This Row],[Weight of Equity]])+(Table2[[#This Row],[Cost of Debt]]*Table2[[#This Row],[Weight of Debt]]) -> 0.11819672 | Z1915: =IF(Table2[[#This Row],[Sector]]="Financial Services",TRUE,FALSE) -> FALSE | AA1915: =IF(Table2[[#This Row],[Market Capitalisation In(Cr)]]>25000,TRUE,FALSE) -> FALSE

Sheet WACC By Sector
B2: WACC BY SECTOR
B3: Sector | C3: Average Daily WACC | D3: Median Daily WACC | E3: Average Weekly WACC | F3: Median Weekly WACC | G3: Average Monthly WACC | H3: Median Monthly WACC
B4: {=_xlfn.UNIQUE(Table2[Sector])} -> Basic Materials | C4: {=AVERAGE(_xlfn.CHOOSECOLS(_xlfn._xlws.FILTER(Table2[],Table2[Sector]=$B4),MATCH("WACC (Daily)",Table2[#Headers],0)))} -> 0.12407993 | D4: {=MEDIAN(_xlfn.CHOOSECOLS(_xlfn._xlws.FILTER(Table2[],Table2[Sector]=$B4),MATCH("WACC (Daily)",Table2[#Headers],0)))} -> 0.11821836 | E4: {=AVERAGE(_xlfn.CHOOSECOLS(_xlfn._xlws.FILTER(Table2[],Table2[Sector]=$B4),MATCH("WACC (Weekly)",Table2[#Headers],0)))} -> 0.1338565 | F4: {=MEDIAN(_xlfn.CHOOSECOLS(_xlfn._xlws.FILTER(Table2[],Table2[Sector]=$B4),MATCH("WACC (Weekly)",Table2[#Headers],0)))} -> 0.12899808 | G4: {=AVERAGE(_xlfn.CHOOSECOLS(_xlfn._xlws.FILTER(Table2[],Table2[Sector]=$B4),MATCH("WACC (Monthly)",Table2[#Headers],0)))} -> 0.12624982 | H4: {=MEDIAN(_xlfn.CHOOSECOLS(_xlfn._xlws.FILTER(Table2[],Table2[Sector]=$B4),MATCH("WACC (Monthly)",Table2[#Headers],0)))} -> 0.11979717
B5: Communication Services | C5: {=AVERAGE(_xlfn.CHOOSECOLS(_xlfn._xlws.FILTER(Table2[],Table2[Sector]=$B5),MATCH("WACC (Daily)",Table2[#Headers],0)))} -> 0.130516 | D5: {=MEDIAN(_xlfn.CHOOSECOLS(_xlfn._xlws.FILTER(Table2[],Table2[Sector]=$B5),23))} -> 0.13523245 | E5: {=AVERAGE(_xlfn.CHOOSECOLS(_xlfn._xlws.FILTER(Table2[],Table2[Sector]=$B5),MATCH("WACC (Weekly)",Table2[#Headers],0)))} -> 0.14109162 | F5: {=MEDIAN(_xlfn.CHOOSECOLS(_xlfn._xlws.FILTER(Table2[],Table2[Sector]=$B5),MATCH("WACC (Weekly)",Table2[#Headers],0)))} -> 0.13523245 | G5: {=AVERAGE(_xlfn.CHOOSECOLS(_xlfn._xlws.FILTER(Table2[],Table2[Sector]=$B5),MATCH("WACC (Monthly)",Table2[#Headers],0)))} -> 0.13602089 | H5: {=MEDIAN(_xlfn.CHOOSECOLS(_xlfn._xlws.FILTER(Table2[],Table2[Sector]=$B5),MATCH("WACC (Monthly)",Table2[#Headers],0)))} -> 0.12220965
B6: Consumer Cyclical | C6: {=AVERAGE(_xlfn.CHOOSECOLS(_xlfn._xlws.FILTER(Table2[],Table2[Sector]=$B6),MATCH("WACC (Daily)",Table2[#Headers],0)))} -> 0.12536025 | D6: {=MEDIAN(_xlfn.CHOOSECOLS(_xlfn._xlws.FILTER(Table2[],Table2[Sector]=$B6),23))} -> 0.12805077 | E6: {=AVERAGE(_xlfn.CHOOSECOLS(_xlfn._xlws.FILTER(Table2[],Table2[Sector]=$B6),MATCH("WACC (Weekly)",Table2[#Headers],0)))} -> 0.13252953 | F6: {=MEDIAN(_xlfn.CHOOSECOLS(_xlfn._xlws.FILTER(Table2[],Table2[Sector]=$B6),MATCH("WACC (Weekly)",Table2[#Headers],0)))} -> 0.12805077 | G6: {=AVERAGE(_xlfn.CHOOSECOLS(_xlfn._xlws.FILTER(Table2[],Table2[Sector]=$B6),MATCH("WACC (Monthly)",Table2[#Headers],0)))} -> 0.12344167 | H6: {=MEDIAN(_xlfn.CHOOSECOLS(_xlfn._xlws.FILTER(Table2[],Table2[Sector]=$B6),MATCH("WACC (Monthly)",Table2[#Headers],0)))} -> 0.11624239
B7: Consumer Defensive | C7: {=AVERAGE(_xlfn.CHOOSECOLS(_xlfn._xlws.FILTER(Table2[],Table2[Sector]=$B7),MATCH("WACC (Daily)",Table2[#Headers],0)))} -> 0.11761002 | D7: {=MEDIAN(_xlfn.CHOOSECOLS(_xlfn._xlws.FILTER(Table2[],Table2[Sector]=$B7),23))} -> 0.12281128 | E7: {=AVERAGE(_xlfn.CHOOSECOLS(_xlfn._xlws.FILTER(Table2[],Table2[Sector]=$B7),MATCH("WACC (Weekly)",Table2[#Headers],0)))} -> 0.12722712 | F7: {=MEDIAN(_xlfn.CHOOSECOLS(_xlfn._xlws.FILTER(Table2[],Table2[Sector]=$B7),MATCH("WACC (Weekly)",Table2[#Headers],0)))} -> 0.12281128 | G7: {=AVERAGE(_xlfn.CHOOSECOLS(_xlfn._xlws.FILTER(Table2[],Table2[Sector]=$B7),MATCH("WACC (Monthly)",Table2[#Headers],0)))} -> 0.11693623 | H7: {=MEDIAN(_xlfn.CHOOSECOLS(_xlfn._xlws.FILTER(Table2[],Table2[Sector]=$B7),MATCH("WACC (Monthly)",Table2[#Headers],0)))} -> 0.11994474
B8: Energy | C8: {=AVERAGE(_xlfn.CHOOSECOLS(_xlfn._xlws.FILTER(Table2[],Table2[Sector]=$B8),MATCH("WACC (Daily)",Table2[#Headers],0)))} -> 0.11851207 | D8: {=MEDIAN(_xlfn.CHOOSECOLS(_xlfn._xlws.FILTER(Table2[],Table2[Sector]=$B8),23))} -> 0.12148289 | E8: {=AVERAGE(_xlfn.CHOOSECOLS(_xlfn._xlws.FILTER(Table2[],Table2[Sector]=$B8),MATCH("WACC (Weekly)",Table2[#Headers],0)))} -> 0.1298811 | F8: {=MEDIAN(_xlfn.CHOOSECOLS(_xlfn._xlws.FILTER(Table2[],Table2[Sector]=$B8),MATCH("WACC (Weekly)",Table2[#Headers],0)))} -> 0.12148289 | G8: {=AVERAGE(_xlfn.CHOOSECOLS(_xlfn._xlws.FILTER(Table2[],Table2[Sector]=$B8),MATCH("WACC (Monthly)",Table2[#Headers],0)))} -> 0.12893439 | H8: {=MEDIAN(_xlfn.CHOOSECOLS(_xlfn._xlws.FILTER(Table2[],Table2[Sector]=$B8),MATCH("WACC (Monthly)",Table2[#Headers],0)))} -> 0.1197144
B9: Financial Services | C9: {=AVERAGE(_xlfn.CHOOSECOLS(_xlfn._xlws.FILTER(Table2[],Table2[Sector]=$B9),MATCH("WACC (Daily)",Table2[#Headers],0)))} -> 0.11738561 | D9: {=MEDIAN(_xlfn.CHOOSECOLS(_xlfn._xlws.FILTER(Table2[],Table2[Sector]=$B9),23))} -> 0.11739984 | E9: {=AVERAGE(_xlfn.CHOOSECOLS(_xlfn._xlws.FILTER(Table2[],Table2[Sector]=$B9),MATCH("WACC (Weekly)",Table2[#Headers],0)))} -> 0.12849532 | F9: {=MEDIAN(_xlfn.CHOOSECOLS(_xlfn._xlws.FILTER(Table2[],Table2[Sector]=$B9),MATCH("WACC (Weekly)",Table2[#Headers],0)))} -> 0.11739984 | G9: {=AVERAGE(_xlfn.CHOOSECOLS(_xlfn._xlws.FILTER(Table2[],Table2[Sector]=$B9),MATCH("WACC (Monthly)",Table2[#Headers],0)))} -> 0.12978769 | H9: {=MEDIAN(_xlfn.CHOOSECOLS(_xlfn._xlws.FILTER(Table2[],Table2[Sector]=$B9),MATCH("WACC (Monthly)",Table2[#Headers],0)))} -> 0.10645126
B10: Healthcare | C10: {=AVERAGE(_xlfn.CHOOSECOLS(_xlfn._xlws.FILTER(Table2[],Table2[Sector]=$B10),MATCH("WACC (Daily)",Table2[#Headers],0)))} -> 0.11518056 | D10: {=MEDIAN(_xlfn.CHOOSECOLS(_xlfn._xlws.FILTER(Table2[],Table2[Sector]=$B10),23))} -> 0.11982147 | E10: {=AVERAGE(_xlfn.CHOOSECOLS(_xlfn._xlws.FILTER(Table2[],Table2[Sector]=$B10),MATCH("WACC (Weekly)",Table2[#Headers],0)))} -> 0.12217551 | F10: {=MEDIAN(_xlfn.CHOOSECOLS(_xlfn._xlws.FILTER(Table2[],Table2[Sector]=$B10),MATCH("WACC (Weekly)",Table2[#Headers],0)))} -> 0.11982147 | G10: {=AVERAGE(_xlfn.CHOOSECOLS(_xlfn._xlws.FILTER(Table2[],Table2[Sector]=$B10),MATCH("WACC (Monthly)",Table2[#Headers],0)))} -> 0.12688366 | H10: {=MEDIAN(_xlfn.CHOOSECOLS(_xlfn._xlws.FILTER(Table2[],Table2[Sector]=$B10),MATCH("WACC (Monthly)",Table2[#Headers],0)))} -> 0.11542312
B11: Industrials | C11: {=AVERAGE(_xlfn.CHOOSECOLS(_xlfn._xlws.FILTER(Table2[],Table2[Sector]=$B11),MATCH("WACC (Daily)",Table2[#Headers],0)))} -> 0.12542506 | D11: {=MEDIAN(_xlfn.CHOOSECOLS(_xlfn._xlws.FILTER(Table2[],Table2[Sector]=$B11),23))} -> 0.13746923 | E11: {=AVERAGE(_xlfn.CHOOSECOLS(_xlfn._xlws.FILTER(Table2[],Table2[Sector]=$B11),MATCH("WACC (Weekly)",Table2[#Headers],0)))} -> 0.13822725 | F11: {=MEDIAN(_xlfn.CHOOSECOLS(_xlfn._xlws.FILTER(Table2[],Table2[Sector]=$B11),MATCH("WACC (Weekly)",Table2[#Headers],0)))} -> 0.13746923 | G11: {=AVERAGE(_xlfn.CHOOSECOLS(_xlfn._xlws.FILTER(Table2[],Table2[Sector]=$B11),MATCH("WACC (Monthly)",Table2[#Headers],0)))} -> 0.1293769 | H11: {=MEDIAN(_xlfn.CHOOSECOLS(_xlfn._xlws.FILTER(Table2[],Table2[Sector]=$B11),MATCH("WACC (Monthly)",Table2[#Headers],0)))} -> 0.12132931
B12: Real Estate | C12: {=AVERAGE(_xlfn.CHOOSECOLS(_xlfn._xlws.FILTER(Table2[],Table2[Sector]=$B12),MATCH("WACC (Daily)",Table2[#Headers],0)))} -> 0.13668551 | D12: {=MEDIAN(_xlfn.CHOOSECOLS(_xlfn._xlws.FILTER(Table2[],Table2[Sector]=$B12),23))} -> 0.14735815 | E12: {=AVERAGE(_xlfn.CHOOSECOLS(_xlfn._xlws.FILTER(Table2[],Table2[Sector]=$B12),MATCH("WACC (Weekly)",Table2[#Headers],0)))} -> 0.15196099 | F12: {=MEDIAN(_xlfn.CHOOSECOLS(_xlfn._xlws.FILTER(Table2[],Table2[Sector]=$B12),MATCH("WACC (Weekly)",Table2[#Headers],0)))} -> 0.14735815 | G12: {=AVERAGE(_xlfn.CHOOSECOLS(_xlfn._xlws.FILTER(Table2[],Table2[Sector]=$B12),MATCH("WACC (Monthly)",Table2[#Headers],0)))} -> 0.1475765 | H12: {=MEDIAN(_xlfn.CHOOSECOLS(_xlfn._xlws.FILTER(Table2[],Table2[Sector]=$B12),MATCH("WACC (Monthly)",Table2[#Headers],0)))} -> 0.13984383
B13: Technology | C13: {=AVERAGE(_xlfn.CHOOSECOLS(_xlfn._xlws.FILTER(Table2[],Table2[Sector]=$B13),MATCH("WACC (Daily)",Table2[#Headers],0)))} -> 0.13023715 | D13: {=MEDIAN(_xlfn.CHOOSECOLS(_xlfn._xlws.FILTER(Table2[],Table2[Sector]=$B13),23))} -> 0.13680175 | E13: {=AVERAGE(_xlfn.CHOOSECOLS(_xlfn._xlws.FILTER(Table2[],Table2[Sector]=$B13),MATCH("WACC (Weekly)",Table2[#Headers],0)))} -> 0.11764961 | F13: {=MEDIAN(_xlfn.CHOOSECOLS(_xlfn._xlws.FILTER(Table2[],Table2[Sector]=$B13),MATCH("WACC (Weekly)",Table2[#Headers],0)))} -> 0.13680175 | G13: {=AVERAGE(_xlfn.CHOOSECOLS(_xlfn._xlws.FILTER(Table2[],Table2[Sector]=$B13),MATCH("WACC (Monthly)",Table2[#Headers],0)))} -> 0.12549288 | H13: {=MEDIAN(_xlfn.CHOOSECOLS(_xlfn._xlws.FILTER(Table2[],Table2[Sector]=$B13),MATCH("WACC (Monthly)",Table2[#Headers],0)))} -> 0.12650571
B14: Utilities | C14: {=AVERAGE(_xlfn.CHOOSECOLS(_xlfn._xlws.FILTER(Table2[],Table2[Sector]=$B14),MATCH("WACC (Daily)",Table2[#Headers],0)))} -> 0.12140052 | D14: {=MEDIAN(_xlfn.CHOOSECOLS(_xlfn._xlws.FILTER(Table2[],Table2[Sector]=$B14),23))} -> 0.12763101 | E14: {=AVERAGE(_xlfn.CHOOSECOLS(_xlfn._xlws.FILTER(Table2[],Table2[Sector]=$B14),MATCH("WACC (Weekly)",Table2[#Headers],0)))} -> 0.13405157 | F14: {=MEDIAN(_xlfn.CHOOSECOLS(_xlfn._xlws.FILTER(Table2[],Table2[Sector]=$B14),MATCH("WACC (Weekly)",Table2[#Headers],0)))} -> 0.12763101 | G14: {=AVERAGE(_xlfn.CHOOSECOLS(_xlfn._xlws.FILTER(Table2[],Table2[Sector]=$B14),MATCH("WACC (Monthly)",Table2[#Headers],0)))} -> 0.12681788 | H14: {=MEDIAN(_xlfn.CHOOSECOLS(_xlfn._xlws.FILTER(Table2[],Table2[Sector]=$B14),MATCH("WACC (Monthly)",Table2[#Headers],0)))} -> 0.1196119

Sheet WACC By Industry
B2: WACC BY INDUSTRY
B3: Sector | C3: Average Daily WACC | D3: Median Daily WACC | E3: Average Weekly WACC | F3: Median Weekly WACC | G3: Average Monthly WACC | H3: Median Monthly WACC
B4: {=_xlfn.UNIQUE(Table2[Industry])} -> Agricultural Inputs | C4: {=AVERAGE(_xlfn.CHOOSECOLS(_xlfn._xlws.FILTER(Table2[],Table2[Industry]=$B4),MATCH("WACC (Daily)",Table2[#Headers],0)))} -> 0.11783258 | D4: {=MEDIAN(_xlfn.CHOOSECOLS(_xlfn._xlws.FILTER(Table2[],Table2[Industry]=$B4),MATCH("WACC (Daily)",Table2[#Headers],0)))} -> 0.11314449 | E4: {=AVERAGE(_xlfn.CHOOSECOLS(_xlfn._xlws.FILTER(Table2[],Table2[Industry]=$B4),MATCH("WACC (Weekly)",Table2[#Headers],0)))} -> 0.12863743 | F4: {=MEDIAN(_xlfn.CHOOSECOLS(_xlfn._xlws.FILTER(Table2[],Table2[Industry]=$B4),MATCH("WACC (Weekly)",Table2[#Headers],0)))} -> 0.12587943 | G4: {=AVERAGE(_xlfn.CHOOSECOLS(_xlfn._xlws.FILTER(Table2[],Table2[Industry]=$B4),MATCH("WACC (Monthly)",Table2[#Headers],0)))} -> 0.11578832 | H4: {=MEDIAN(_xlfn.CHOOSECOLS(_xlfn._xlws.FILTER(Table2[],Table2[Industry]=$B4),MATCH("WACC (Monthly)",Table2[#Headers],0)))} -> 0.11959926
B5: Aluminum | C5: {=AVERAGE(_xlfn.CHOOSECOLS(_xlfn._xlws.FILTER(Table2[],Table2[Industry]=$B5),MATCH("WACC (Daily)",Table2[#Headers],0)))} -> 0.11367256 | D5: {=MEDIAN(_xlfn.CHOOSECOLS(_xlfn._xlws.FILTER(Table2[],Table2[Industry]=$B5),MATCH("WACC (Daily)",Table2[#Headers],0)))} -> 0.11160239 | E5: {=AVERAGE(_xlfn.CHOOSECOLS(_xlfn._xlws.FILTER(Table2[],Table2[Industry]=$B5),MATCH("WACC (Weekly)",Table2[#Headers],0)))} -> 0.12351922 | F5: {=MEDIAN(_xlfn.CHOOSECOLS(_xlfn._xlws.FILTER(Table2[],Table2[Industry]=$B5),MATCH("WACC (Weekly)",Table2[#Headers],0)))} -> 0.1238054 | G5: {=AVERAGE(_xlfn.CHOOSECOLS(_xlfn._xlws.FILTER(Table2[],Table2[Industry]=$B5),MATCH("WACC (Monthly)",Table2[#Headers],0)))} -> 0.12162991 | H5: {=MEDIAN(_xlfn.CHOOSECOLS(_xlfn._xlws.FILTER(Table2[],Table2[Industry]=$B5),MATCH("WACC (Monthly)",Table2[#Headers],0)))} -> 0.12126729
B6: Building Materials | C6: {=AVERAGE(_xlfn.CHOOSECOLS(_xlfn._xlws.FILTER(Table2[],Table2[Industry]=$B6),MATCH("WACC (Daily)",Table2[#Headers],0)))} -> 0.12533617 | D6: {=MEDIAN(_xlfn.CHOOSECOLS(_xlfn._xlws.FILTER(Table2[],Table2[Industry]=$B6),MATCH("WACC (Daily)",Table2[#Headers],0)))} -> 0.11234027 | E6: {=AVERAGE(_xlfn.CHOOSECOLS(_xlfn._xlws.FILTER(Table2[],Table2[Industry]=$B6),MATCH("WACC (Weekly)",Table2[#Headers],0)))} -> 0.13667972 | F6: {=MEDIAN(_xlfn.CHOOSECOLS(_xlfn._xlws.FILTER(Table2[],Table2[Industry]=$B6),MATCH("WACC (Weekly)",Table2[#Headers],0)))} -> 0.1240616 | G6: {=AVERAGE(_xlfn.CHOOSECOLS(_xlfn._xlws.FILTER(Table2[],Table2[Industry]=$B6),MATCH("WACC (Monthly)",Table2[#Headers],0)))} -> 0.1282666 | H6: {=MEDIAN(_xlfn.CHOOSECOLS(_xlfn._xlws.FILTER(Table2[],Table2[Industry]=$B6),MATCH("WACC (Monthly)",Table2[#Headers],0)))} -> 0.11490871
B7: Chemicals | C7: {=AVERAGE(_xlfn.CHOOSECOLS(_xlfn._xlws.FILTER(Table2[],Table2[Industry]=$B7),MATCH("WACC (Daily)",Table2[#Headers],0)))} -> 0.12508734 | D7: {=MEDIAN(_xlfn.CHOOSECOLS(_xlfn._xlws.FILTER(Table2[],Table2[Industry]=$B7),MATCH("WACC (Daily)",Table2[#Headers],0)))} -> 0.11817125 | E7: {=AVERAGE(_xlfn.CHOOSECOLS(_xlfn._xlws.FILTER(Table2[],Table2[Industry]=$B7),MATCH("WACC (Weekly)",Table2[#Headers],0)))} -> 0.13704674 | F7: {=MEDIAN(_xlfn.CHOOSECOLS(_xlfn._xlws.FILTER(Table2[],Table2[Industry]=$B7),MATCH("WACC (Weekly)",Table2[#Headers],0)))} -> 0.13546764 | G7: {=AVERAGE(_xlfn.CHOOSECOLS(_xlfn._xlws.FILTER(Table2[],Table2[Industry]=$B7),MATCH("WACC (Monthly)",Table2[#Headers],0)))} -> 0.13448725 | H7: {=MEDIAN(_xlfn.CHOOSECOLS(_xlfn._xlws.FILTER(Table2[],Table2[Industry]=$B7),MATCH("WACC (Monthly)",Table2[#Headers],0)))} -> 0.13226663
B8: Copper | C8: {=AVERAGE(_xlfn.CHOOSECOLS(_xlfn._xlws.FILTER(Table2[],Table2[Industry]=$B8),MATCH("WACC (Daily)",Table2[#Headers],0)))} -> 0.11771924 | D8: {=MEDIAN(_xlfn.CHOOSECOLS(_xlfn._xlws.FILTER(Table2[],Table2[Industry]=$B8),MATCH("WACC (Daily)",Table2[#Headers],0)))} -> 0.11492596 | E8: {=AVERAGE(_xlfn.CHOOSECOLS(_xlfn._xlws.FILTER(Table2[],Table2[Industry]=$B8),MATCH("WACC (Weekly)",Table2[#Headers],0)))} -> 0.1181768 | F8: {=MEDIAN(_xlfn.CHOOSECOLS(_xlfn._xlws.FILTER(Table2[],Table2[Industry]=$B8),MATCH("WACC (Weekly)",Table2[#Headers],0)))} -> 0.11850333 | G8: {=AVERAGE(_xlfn.CHOOSECOLS(_xlfn._xlws.FILTER(Table2[],Table2[Industry]=$B8),MATCH("WACC (Monthly)",Table2[#Headers],0)))} -> 0.10929454 | H8: {=MEDIAN(_xlfn.CHOOSECOLS(_xlfn._xlws.FILTER(Table2[],Table2[Industry]=$B8),MATCH("WACC (Monthly)",Table2[#Headers],0)))} -> 0.10651157
B9: Lumber & Wood Production | C9: {=AVERAGE(_xlfn.CHOOSECOLS(_xlfn._xlws.FILTER(Table2[],Table2[Industry]=$B9),MATCH("WACC (Daily)",Table2[#Headers],0)))} -> 0.11933853 | D9: {=MEDIAN(_xlfn.CHOOSECOLS(_xlfn._xlws.FILTER(Table2[],Table2[Industry]=$B9),MATCH("WACC (Daily)",Table2[#Headers],0)))} -> 0.11517524 | E9: {=AVERAGE(_xlfn.CHOOSECOLS(_xlfn._xlws.FILTER(Table2[],Table2[Industry]=$B9),MATCH("WACC (Weekly)",Table2[#Headers],0)))} -> 0.13438226 | F9: {=MEDIAN(_xlfn.CHOOSECOLS(_xlfn._xlws.FILTER(Table2[],Table2[Industry]=$B9),MATCH("WACC (Weekly)",Table2[#Headers],0)))} -> 0.13032001 | G9: {=AVERAGE(_xlfn.CHOOSECOLS(_xlfn._xlws.FILTER(Table2[],Table2[Industry]=$B9),MATCH("WACC (Monthly)",Table2[#Headers],0)))} -> 0.12483059 | H9: {=MEDIAN(_xlfn.CHOOSECOLS(_xlfn._xlws.FILTER(Table2[],Table2[Industry]=$B9),MATCH("WACC (Monthly)",Table2[#Headers],0)))} -> 0.11828686
B10: Other Industrial Metals & Mining | C10: {=AVERAGE(_xlfn.CHOOSECOLS(_xlfn._xlws.FILTER(Table2[],Table2[Industry]=$B10),MATCH("WACC (Daily)",Table2[#Headers],0)))} -> 0.13898356 | D10: {=MEDIAN(_xlfn.CHOOSECOLS(_xlfn._xlws.FILTER(Table2[],Table2[Industry]=$B10),MATCH("WACC (Daily)",Table2[#Headers],0)))} -> 0.12830299 | E10: {=AVERAGE(_xlfn.CHOOSECOLS(_xlfn._xlws.FILTER(Table2[],Table2[Industry]=$B10),MATCH("WACC (Weekly)",Table2[#Headers],0)))} -> 0.14864087 | F10: {=MEDIAN(_xlfn.CHOOSECOLS(_xlfn._xlws.FILTER(Table2[],Table2[Industry]=$B10),MATCH("WACC (Weekly)",Table2[#Headers],0)))} -> 0.13334257 | G10: {=AVERAGE(_xlfn.CHOOSECOLS(_xlfn._xlws.FILTER(Table2[],Table2[Industry]=$B10),MATCH("WACC (Monthly)",Table2[#Headers],0)))} -> 0.16348967 | H10: {=MEDIAN(_xlfn.CHOOSECOLS(_xlfn._xlws.FILTER(Table2[],Table2[Industry]=$B10),MATCH("WACC (Monthly)",Table2[#Headers],0)))} -> 0.11375952
B11: Other Precious Metals & Mining | C11: {=AVERAGE(_xlfn.CHOOSECOLS(_xlfn._xlws.FILTER(Table2[],Table2[Industry]=$B11),MATCH("WACC (Daily)",Table2[#Headers],0)))} -> 0.13924518 | D11: {=MEDIAN(_xlfn.CHOOSECOLS(_xlfn._xlws.FILTER(Table2[],Table2[Industry]=$B11),MATCH("WACC (Daily)",Table2[#Headers],0)))} -> 0.13924518 | E11: {=AVERAGE(_xlfn.CHOOSECOLS(_xlfn._xlws.FILTER(Table2[],Table2[Industry]=$B11),MATCH("WACC (Weekly)",Table2[#Headers],0)))} -> 0.14727114 | F11: {=MEDIAN(_xlfn.CHOOSECOLS(_xlfn._xlws.FILTER(Table2[],Table2[Industry]=$B11),MATCH("WACC (Weekly)",Table2[#Headers],0)))} -> 0.14727114 | G11: {=AVERAGE(_xlfn.CHOOSECOLS(_xlfn._xlws.FILTER(Table2[],Table2[Industry]=$B11),MATCH("WACC (Monthly)",Table2[#Headers],0)))} -> 0.10018173 | H11: {=MEDIAN(_xlfn.CHOOSECOLS(_xlfn._xlws.FILTER(Table2[],Table2[Industry]=$B11),MATCH("WACC (Monthly)",Table2[#Headers],0)))} -> 0.10018173
B12: Paper & Paper Products | C12: {=AVERAGE(_xlfn.CHOOSECOLS(_xlfn._xlws.FILTER(Table2[],Table2[Industry]=$B12),MATCH("WACC (Daily)",Table2[#Headers],0)))} -> 0.13952128 | D12: {=MEDIAN(_xlfn.CHOOSECOLS(_xlfn._xlws.FILTER(Table2[],Table2[Industry]=$B12),MATCH("WACC (Daily)",Table2[#Headers],0)))} -> 0.11894056 | E12: {=AVERAGE(_xlfn.CHOOSECOLS(_xlfn._xlws.FILTER(Table2[],Table2[Industry]=$B12),MATCH("WACC (Weekly)",Table2[#Headers],0)))} -> 0.14535993 | F12: {=MEDIAN(_xlfn.CHOOSECOLS(_xlfn._xlws.FILTER(Table2[],Table2[Industry]=$B12),MATCH("WACC (Weekly)",Table2[#Headers],0)))} -> 0.13013779 | G12: {=AVERAGE(_xlfn.CHOOSECOLS(_xlfn._xlws.FILTER(Table2[],Table2[Industry]=$B12),MATCH("WACC (Monthly)",Table2[#Headers],0)))} -> 0.14386547 | H12: {=MEDIAN(_xlfn.CHOOSECOLS(_xlfn._xlws.FILTER(Table2[],Table2[Industry]=$B12),MATCH("WACC (Monthly)",Table2[#Headers],0)))} -> 0.13236952
B13: Specialty Chemicals | C13: {=AVERAGE(_xlfn.CHOOSECOLS(_xlfn._xlws.FILTER(Table2[],Table2[Industry]=$B13),MATCH("WACC (Daily)",Table2[#Headers],0)))} -> 0.11919753 | D13: {=MEDIAN(_xlfn.CHOOSECOLS(_xlfn._xlws.FILTER(Table2[],Table2[Industry]=$B13),MATCH("WACC (Daily)",Table2[#Headers],0)))} -> 0.11289374 | E13: {=AVERAGE(_xlfn.CHOOSECOLS(_xlfn._xlws.FILTER(Table2[],Table2[Industry]=$B13),MATCH("WACC (Weekly)",Table2[#Headers],0)))} -> 0.13073129 | F13: {=MEDIAN(_xlfn.CHOOSECOLS(_xlfn._xlws.FILTER(Table2[],Table2[Industry]=$B13),MATCH("WACC (Weekly)",Table2[#Headers],0)))} -> 0.12509954 | G13: {=AVERAGE(_xlfn.CHOOSECOLS(_xlfn._xlws.FILTER(Table2[],Table2[Industry]=$B13),MATCH("WACC (Monthly)",Table2[#Headers],0)))} -> 0.12305969 | H13: {=MEDIAN(_xlfn.CHOOSECOLS(_xlfn._xlws.FILTER(Table2[],Table2[Industry]=$B13),MATCH("WACC (Monthly)",Table2[#Headers],0)))} -> 0.11980907
B14: Steel | C14: {=AVERAGE(_xlfn.CHOOSECOLS(_xlfn._xlws.FILTER(Table2[],Table2[Industry]=$B14),MATCH("WACC (Daily)",Table2[#Headers],0)))} -> 0.12846787 | D14: {=MEDIAN(_xlfn.CHOOSECOLS(_xlfn._xlws.FILTER(Table2[],Table2[Industry]=$B14),MATCH("WACC (Daily)",Table2[#Headers],0)))} -> 0.12646017 | E14: {=AVERAGE(_xlfn.CHOOSECOLS(_xlfn._xlws.FILTER(Table2[],Table2[Industry]=$B14),MATCH("WACC (Weekly)",Table2[#Headers],0)))} -> 0.13529765 | F14: {=MEDIAN(_xlfn.CHOOSECOLS(_xlfn._xlws.FILTER(Table2[],Table2[Industry]=$B14),MATCH("WACC (Weekly)",Table2[#Headers],0)))} -> 0.13188837 | G14: {=AVERAGE(_xlfn.CHOOSECOLS(_xlfn._xlws.FILTER(Table2[],Table2[Industry]=$B14),MATCH("WACC (Monthly)",Table2[#Headers],0)))} -> 0.12468145 | H14: {=MEDIAN(_xlfn.CHOOSECOLS(_xlfn._xlws.FILTER(Table2[],Table2[Industry]=$B14),MATCH("WACC (Monthly)",Table2[#Headers],0)))} -> 0.11643993
B15: Advertising Agencies | C15: {=AVERAGE(_xlfn.CHOOSECOLS(_xlfn._xlws.FILTER(Table2[],Table2[Industry]=$B15),MATCH("WACC (Daily)",Table2[#Headers],0)))} -> 0.11677602 | D15: {=MEDIAN(_xlfn.CHOOSECOLS(_xlfn._xlws.FILTER(Table2[],Table2[Industry]=$B15),MATCH("WACC (Daily)",Table2[#Headers],0)))} -> 0.11440725 | E15: {=AVERAGE(_xlfn.CHOOSECOLS(_xlfn._xlws.FILTER(Table2[],Table2[Industry]=$B15),MATCH("WACC (Weekly)",Table2[#Headers],0)))} -> 0.12564395 | F15: {=MEDIAN(_xlfn.CHOOSECOLS(_xlfn._xlws.FILTER(Table2[],Table2[Industry]=$B15),MATCH("WACC (Weekly)",Table2[#Headers],0)))} -> 0.12449877 | G15: {=AVERAGE(_xlfn.CHOOSECOLS(_xlfn._xlws.FILTER(Table2[],Table2[Industry]=$B15),MATCH("WACC (Monthly)",Table2[#Headers],0)))} -> 0.081433732 | H15: {=MEDIAN(_xlfn.CHOOSECOLS(_xlfn._xlws.FILTER(Table2[],Table2[Industry]=$B15),MATCH("WACC (Monthly)",Table2[#Headers],0)))} -> 0.090736664
B16: Broadcasting | C16: {=AVERAGE(_xlfn.CHOOSECOLS(_xlfn._xlws.FILTER(Table2[],Table2[Industry]=$B16),MATCH("WACC (Daily)",Table2[#Headers],0)))} -> 0.13075427 | D16: {=MEDIAN(_xlfn.CHOOSECOLS(_xlfn._xlws.FILTER(Table2[],Table2[Industry]=$B16),MATCH("WACC (Daily)",Table2[#Headers],0)))} -> 0.11220182 | E16: {=AVERAGE(_xlfn.CHOOSECOLS(_xlfn._xlws.FILTER(Table2[],Table2[Industry]=$B16),MATCH("WACC (Weekly)",Table2[#Headers],0)))} -> 0.14682101 | F16: {=MEDIAN(_xlfn.CHOOSECOLS(_xlfn._xlws.FILTER(Table2[],Table2[Industry]=$B16),MATCH("WACC (Weekly)",Table2[#Headers],0)))} -> 0.13617443 | G16: {=AVERAGE(_xlfn.CHOOSECOLS(_xlfn._xlws.FILTER(Table2[],Table2[Industry]=$B16),MATCH("WACC (Monthly)",Table2[#Headers],0)))} -> 0.14772712 | H16: {=MEDIAN(_xlfn.CHOOSECOLS(_xlfn._xlws.FILTER(Table2[],Table2[Industry]=$B16),MATCH("WACC (Monthly)",Table2[#Headers],0)))} -> 0.12797941
... B123: Utilities - Renewable | C123: {=AVERAGE(_xlfn.CHOOSECOLS(_xlfn._xlws.FILTER(Table2[],Table2[Industry]=$B123),MATCH("WACC (Daily)",Table2[#Headers],0)))} -> 0.12899402 | D123: {=MEDIAN(_xlfn.CHOOSECOLS(_xlfn._xlws.FILTER(Table2[],Table2[Industry]=$B123),MATCH("WACC (Daily)",Table2[#Headers],0)))} -> 0.13184473 | E123: {=AVERAGE(_xlfn.CHOOSECOLS(_xlfn._xlws.FILTER(Table2[],Table2[Industry]=$B123),MATCH("WACC (Weekly)",Table2[#Headers],0)))} -> 0.15016355 | F123: {=MEDIAN(_xlfn.CHOOSECOLS(_xlfn._xlws.FILTER(Table2[],Table2[Industry]=$B123),MATCH("WACC (Weekly)",Table2[#Headers],0)))} -> 0.14309312 | G123: {=AVERAGE(_xlfn.CHOOSECOLS(_xlfn._xlws.FILTER(Table2[],Table2[Industry]=$B123),MATCH("WACC (Monthly)",Table2[#Headers],0)))} -> 0.12593835 | H123: {=MEDIAN(_xlfn.CHOOSECOLS(_xlfn._xlws.FILTER(Table2[],Table2[Industry]=$B123),MATCH("WACC (Monthly)",Table2[#Headers],0)))} -> 0.12228013

Sheet WACC By Credit Rating
B2: WACC BY INDUSTRY
B3: Sector | C3: Average Daily WACC | D3: Median Daily WACC | E3: Average Weekly WACC | F3: Median Weekly WACC | G3: Average Monthly WACC | H3: Median Monthly WACC
B4: {=Rating3[Rating is]} -> A1/A+ | C4: {=AVERAGE(_xlfn.CHOOSECOLS(_xlfn._xlws.FILTER(Table2[],Table2[Credit Rating (Acc to lookup table)]=$B4),MATCH("WACC (Daily)",Table2[#Headers],0)))} -> 0.1170189 | D4: {=MEDIAN(_xlfn.CHOOSECOLS(_xlfn._xlws.FILTER(Table2[],Table2[Credit Rating (Acc to lookup table)]=$B4),MATCH("WACC (Daily)",Table2[#Headers],0)))} -> 0.11679425 | E4: {=AVERAGE(_xlfn.CHOOSECOLS(_xlfn._xlws.FILTER(Table2[],Table2[Credit Rating (Acc to lookup table)]=$B4),MATCH("WACC (Weekly)",Table2[#Headers],0)))} -> 0.12536746 | F4: {=MEDIAN(_xlfn.CHOOSECOLS(_xlfn._xlws.FILTER(Table2[],Table2[Credit Rating (Acc to lookup table)]=$B4),MATCH("WACC (Weekly)",Table2[#Headers],0)))} -> 0.12530076 | G4: {=AVERAGE(_xlfn.CHOOSECOLS(_xlfn._xlws.FILTER(Table2[],Table2[Credit Rating (Acc to lookup table)]=$B4),MATCH("WACC (Monthly)",Table2[#Headers],0)))} -> 0.12275931 | H4: {=MEDIAN(_xlfn.CHOOSECOLS(_xlfn._xlws.FILTER(Table2[],Table2[Credit Rating (Acc to lookup table)]=$B4),MATCH("WACC (Monthly)",Table2[#Headers],0)))} -> 0.11901018
B5: A2/A | C5: {=AVERAGE(_xlfn.CHOOSECOLS(_xlfn._xlws.FILTER(Table2[],Table2[Credit Rating (Acc to lookup table)]=$B5),MATCH("WACC (Daily)",Table2[#Headers],0)))} -> 0.11438775 | D5: {=MEDIAN(_xlfn.CHOOSECOLS(_xlfn._xlws.FILTER(Table2[],Table2[Credit Rating (Acc to lookup table)]=$B5),MATCH("WACC (Daily)",Table2[#Headers],0)))} -> 0.11115855 | E5: {=AVERAGE(_xlfn.CHOOSECOLS(_xlfn._xlws.FILTER(Table2[],Table2[Credit Rating (Acc to lookup table)]=$B5),MATCH("WACC (Weekly)",Table2[#Headers],0)))} -> 0.12396191 | F5: {=MEDIAN(_xlfn.CHOOSECOLS(_xlfn._xlws.FILTER(Table2[],Table2[Credit Rating (Acc to lookup table)]=$B5),MATCH("WACC (Weekly)",Table2[#Headers],0)))} -> 0.12378829 | G5: {=AVERAGE(_xlfn.CHOOSECOLS(_xlfn._xlws.FILTER(Table2[],Table2[Credit Rating (Acc to lookup table)]=$B5),MATCH("WACC (Monthly)",Table2[#Headers],0)))} -> 0.13328607 | H5: {=MEDIAN(_xlfn.CHOOSECOLS(_xlfn._xlws.FILTER(Table2[],Table2[Credit Rating (Acc to lookup table)]=$B5),MATCH("WACC (Monthly)",Table2[#Headers],0)))} -> 0.1134681
B6: A3/A- | C6: {=AVERAGE(_xlfn.CHOOSECOLS(_xlfn._xlws.FILTER(Table2[],Table2[Credit Rating (Acc to lookup table)]=$B6),MATCH("WACC (Daily)",Table2[#Headers],0)))} -> 0.1135999 | D6: {=MEDIAN(_xlfn.CHOOSECOLS(_xlfn._xlws.FILTER(Table2[],Table2[Credit Rating (Acc to lookup table)]=$B6),MATCH("WACC (Daily)",Table2[#Headers],0)))} -> 0.10895951 | E6: {=AVERAGE(_xlfn.CHOOSECOLS(_xlfn._xlws.FILTER(Table2[],Table2[Credit Rating (Acc to lookup table)]=$B6),MATCH("WACC (Weekly)",Table2[#Headers],0)))} -> 0.12408374 | F6: {=MEDIAN(_xlfn.CHOOSECOLS(_xlfn._xlws.FILTER(Table2[],Table2[Credit Rating (Acc to lookup table)]=$B6),MATCH("WACC (Weekly)",Table2[#Headers],0)))} -> 0.1201262 | G6: {=AVERAGE(_xlfn.CHOOSECOLS(_xlfn._xlws.FILTER(Table2[],Table2[Credit Rating (Acc to lookup table)]=$B6),MATCH("WACC (Monthly)",Table2[#Headers],0)))} -> 0.11941761 | H6: {=MEDIAN(_xlfn.CHOOSECOLS(_xlfn._xlws.FILTER(Table2[],Table2[Credit Rating (Acc to lookup table)]=$B6),MATCH("WACC (Monthly)",Table2[#Headers],0)))} -> 0.11224389
B7: Aa2/AA | C7: {=AVERAGE(_xlfn.CHOOSECOLS(_xlfn._xlws.FILTER(Table2[],Table2[Credit Rating (Acc to lookup table)]=$B7),MATCH("WACC (Daily)",Table2[#Headers],0)))} -> 0.11724079 | D7: {=MEDIAN(_xlfn.CHOOSECOLS(_xlfn._xlws.FILTER(Table2[],Table2[Credit Rating (Acc to lookup table)]=$B7),MATCH("WACC (Daily)",Table2[#Headers],0)))} -> 0.11471708 | E7: {=AVERAGE(_xlfn.CHOOSECOLS(_xlfn._xlws.FILTER(Table2[],Table2[Credit Rating (Acc to lookup table)]=$B7),MATCH("WACC (Weekly)",Table2[#Headers],0)))} -> 0.12766135 | F7: {=MEDIAN(_xlfn.CHOOSECOLS(_xlfn._xlws.FILTER(Table2[],Table2[Credit Rating (Acc to lookup table)]=$B7),MATCH("WACC (Weekly)",Table2[#Headers],0)))} -> 0.12202159 | G7: {=AVERAGE(_xlfn.CHOOSECOLS(_xlfn._xlws.FILTER(Table2[],Table2[Credit Rating (Acc to lookup table)]=$B7),MATCH("WACC (Monthly)",Table2[#Headers],0)))} -> 0.11208514 | H7: {=MEDIAN(_xlfn.CHOOSECOLS(_xlfn._xlws.FILTER(Table2[],Table2[Credit Rating (Acc to lookup table)]=$B7),MATCH("WACC (Monthly)",Table2[#Headers],0)))} -> 0.11471911
B8: Aaa/AAA | C8: {=AVERAGE(_xlfn.CHOOSECOLS(_xlfn._xlws.FILTER(Table2[],Table2[Credit Rating (Acc to lookup table)]=$B8),MATCH("WACC (Daily)",Table2[#Headers],0)))} -> 0.1168256 | D8: {=MEDIAN(_xlfn.CHOOSECOLS(_xlfn._xlws.FILTER(Table2[],Table2[Credit Rating (Acc to lookup table)]=$B8),MATCH("WACC (Daily)",Table2[#Headers],0)))} -> 0.11599128 | E8: {=AVERAGE(_xlfn.CHOOSECOLS(_xlfn._xlws.FILTER(Table2[],Table2[Credit Rating (Acc to lookup table)]=$B8),MATCH("WACC (Weekly)",Table2[#Headers],0)))} -> 0.12242989 | F8: {=MEDIAN(_xlfn.CHOOSECOLS(_xlfn._xlws.FILTER(Table2[],Table2[Credit Rating (Acc to lookup table)]=$B8),MATCH("WACC (Weekly)",Table2[#Headers],0)))} -> 0.12829542 | G8: {=AVERAGE(_xlfn.CHOOSECOLS(_xlfn._xlws.FILTER(Table2[],Table2[Credit Rating (Acc to lookup table)]=$B8),MATCH("WACC (Monthly)",Table2[#Headers],0)))} -> 0.12049595 | H8: {=MEDIAN(_xlfn.CHOOSECOLS(_xlfn._xlws.FILTER(Table2[],Table2[Credit Rating (Acc to lookup table)]=$B8),MATCH("WACC (Monthly)",Table2[#Headers],0)))} -> 0.11642703
B9: B1/B+ | C9: {=AVERAGE(_xlfn.CHOOSECOLS(_xlfn._xlws.FILTER(Table2[],Table2[Credit Rating (Acc to lookup table)]=$B9),MATCH("WACC (Daily)",Table2[#Headers],0)))} -> 0.11275539 | D9: {=MEDIAN(_xlfn.CHOOSECOLS(_xlfn._xlws.FILTER(Table2[],Table2[Credit Rating (Acc to lookup table)]=$B9),MATCH("WACC (Daily)",Table2[#Headers],0)))} -> 0.11144247 | E9: {=AVERAGE(_xlfn.CHOOSECOLS(_xlfn._xlws.FILTER(Table2[],Table2[Credit Rating (Acc to lookup table)]=$B9),MATCH("WACC (Weekly)",Table2[#Headers],0)))} -> 0.12300223 | F9: {=MEDIAN(_xlfn.CHOOSECOLS(_xlfn._xlws.FILTER(Table2[],Table2[Credit Rating (Acc to lookup table)]=$B9),MATCH("WACC (Weekly)",Table2[#Headers],0)))} -> 0.12211288 | G9: {=AVERAGE(_xlfn.CHOOSECOLS(_xlfn._xlws.FILTER(Table2[],Table2[Credit Rating (Acc to lookup table)]=$B9),MATCH("WACC (Monthly)",Table2[#Headers],0)))} -> 0.10764881 | H9: {=MEDIAN(_xlfn.CHOOSECOLS(_xlfn._xlws.FILTER(Table2[],Table2[Credit Rating (Acc to lookup table)]=$B9),MATCH("WACC (Monthly)",Table2[#Headers],0)))} -> 0.1121663
B10: B2/B | C10: {=AVERAGE(_xlfn.CHOOSECOLS(_xlfn._xlws.FILTER(Table2[],Table2[Credit Rating (Acc to lookup table)]=$B10),MATCH("WACC (Daily)",Table2[#Headers],0)))} -> 0.11344731 | D10: {=MEDIAN(_xlfn.CHOOSECOLS(_xlfn._xlws.FILTER(Table2[],Table2[Credit Rating (Acc to lookup table)]=$B10),MATCH("WACC (Daily)",Table2[#Headers],0)))} -> 0.11476389 | E10: {=AVERAGE(_xlfn.CHOOSECOLS(_xlfn._xlws.FILTER(Table2[],Table2[Credit Rating (Acc to lookup table)]=$B10),MATCH("WACC (Weekly)",Table2[#Headers],0)))} -> 0.12000399 | F10: {=MEDIAN(_xlfn.CHOOSECOLS(_xlfn._xlws.FILTER(Table2[],Table2[Credit Rating (Acc to lookup table)]=$B10),MATCH("WACC (Weekly)",Table2[#Headers],0)))} -> 0.119025 | G10: {=AVERAGE(_xlfn.CHOOSECOLS(_xlfn._xlws.FILTER(Table2[],Table2[Credit Rating (Acc to lookup table)]=$B10),MATCH("WACC (Monthly)",Table2[#Headers],0)))} -> 0.11153222 | H10: {=MEDIAN(_xlfn.CHOOSECOLS(_xlfn._xlws.FILTER(Table2[],Table2[Credit Rating (Acc to lookup table)]=$B10),MATCH("WACC (Monthly)",Table2[#Headers],0)))} -> 0.11600602
B11: B3/B- | C11: {=AVERAGE(_xlfn.CHOOSECOLS(_xlfn._xlws.FILTER(Table2[],Table2[Credit Rating (Acc to lookup table)]=$B11),MATCH("WACC (Daily)",Table2[#Headers],0)))} -> 0.12020708 | D11: {=MEDIAN(_xlfn.CHOOSECOLS(_xlfn._xlws.FILTER(Table2[],Table2[Credit Rating (Acc to lookup table)]=$B11),MATCH("WACC (Daily)",Table2[#Headers],0)))} -> 0.11985738 | E11: {=AVERAGE(_xlfn.CHOOSECOLS(_xlfn._xlws.FILTER(Table2[],Table2[Credit Rating (Acc to lookup table)]=$B11),MATCH("WACC (Weekly)",Table2[#Headers],0)))} -> 0.13156713 | F11: {=MEDIAN(_xlfn.CHOOSECOLS(_xlfn._xlws.FILTER(Table2[],Table2[Credit Rating (Acc to lookup table)]=$B11),MATCH("WACC (Weekly)",Table2[#Headers],0)))} -> 0.12995964 | G11: {=AVERAGE(_xlfn.CHOOSECOLS(_xlfn._xlws.FILTER(Table2[],Table2[Credit Rating (Acc to lookup table)]=$B11),MATCH("WACC (Monthly)",Table2[#Headers],0)))} -> 0.11643697 | H11: {=MEDIAN(_xlfn.CHOOSECOLS(_xlfn._xlws.FILTER(Table2[],Table2[Credit Rating (Acc to lookup table)]=$B11),MATCH("WACC (Monthly)",Table2[#Headers],0)))} -> 0.11699153
B12: Ba1/BB+ | C12: {=AVERAGE(_xlfn.CHOOSECOLS(_xlfn._xlws.FILTER(Table2[],Table2[Credit Rating (Acc to lookup table)]=$B12),MATCH("WACC (Daily)",Table2[#Headers],0)))} -> 0.11056199 | D12: {=MEDIAN(_xlfn.CHOOSECOLS(_xlfn._xlws.FILTER(Table2[],Table2[Credit Rating (Acc to lookup table)]=$B12),MATCH("WACC (Daily)",Table2[#Headers],0)))} -> 0.1079776 | E12: {=AVERAGE(_xlfn.CHOOSECOLS(_xlfn._xlws.FILTER(Table2[],Table2[Credit Rating (Acc to lookup table)]=$B12),MATCH("WACC (Weekly)",Table2[#Headers],0)))} -> 0.12027407 | F12: {=MEDIAN(_xlfn.CHOOSECOLS(_xlfn._xlws.FILTER(Table2[],Table2[Credit Rating (Acc to lookup table)]=$B12),MATCH("WACC (Weekly)",Table2[#Headers],0)))} -> 0.1214728 | G12: {=AVERAGE(_xlfn.CHOOSECOLS(_xlfn._xlws.FILTER(Table2[],Table2[Credit Rating (Acc to lookup table)]=$B12),MATCH("WACC (Monthly)",Table2[#Headers],0)))} -> 0.10752084 | H12: {=MEDIAN(_xlfn.CHOOSECOLS(_xlfn._xlws.FILTER(Table2[],Table2[Credit Rating (Acc to lookup table)]=$B12),MATCH("WACC (Monthly)",Table2[#Headers],0)))} -> 0.10538779
B13: Ba2/BB | C13: {=AVERAGE(_xlfn.CHOOSECOLS(_xlfn._xlws.FILTER(Table2[],Table2[Credit Rating (Acc to lookup table)]=$B13),MATCH("WACC (Daily)",Table2[#Headers],0)))} -> 0.11186961 | D13: {=MEDIAN(_xlfn.CHOOSECOLS(_xlfn._xlws.FILTER(Table2[],Table2[Credit Rating (Acc to lookup table)]=$B13),MATCH("WACC (Daily)",Table2[#Headers],0)))} -> 0.11142106 | E13: {=AVERAGE(_xlfn.CHOOSECOLS(_xlfn._xlws.FILTER(Table2[],Table2[Credit Rating (Acc to lookup table)]=$B13),MATCH("WACC (Weekly)",Table2[#Headers],0)))} -> 0.1194637 | F13: {=MEDIAN(_xlfn.CHOOSECOLS(_xlfn._xlws.FILTER(Table2[],Table2[Credit Rating (Acc to lookup table)]=$B13),MATCH("WACC (Weekly)",Table2[#Headers],0)))} -> 0.11617005 | G13: {=AVERAGE(_xlfn.CHOOSECOLS(_xlfn._xlws.FILTER(Table2[],Table2[Credit Rating (Acc to lookup table)]=$B13),MATCH("WACC (Monthly)",Table2[#Headers],0)))} -> 0.1085358 | H13: {=MEDIAN(_xlfn.CHOOSECOLS(_xlfn._xlws.FILTER(Table2[],Table2[Credit Rating (Acc to lookup table)]=$B13),MATCH("WACC (Monthly)",Table2[#Headers],0)))} -> 0.10578398
B14: Baa2/BBB | C14: {=AVERAGE(_xlfn.CHOOSECOLS(_xlfn._xlws.FILTER(Table2[],Table2[Credit Rating (Acc to lookup table)]=$B14),MATCH("WACC (Daily)",Table2[#Headers],0)))} -> 0.11268787 | D14: {=MEDIAN(_xlfn.CHOOSECOLS(_xlfn._xlws.FILTER(Table2[],Table2[Credit Rating (Acc to lookup table)]=$B14),MATCH("WACC (Daily)",Table2[#Headers],0)))} -> 0.1131175 | E14: {=AVERAGE(_xlfn.CHOOSECOLS(_xlfn._xlws.FILTER(Table2[],Table2[Credit Rating (Acc to lookup table)]=$B14),MATCH("WACC (Weekly)",Table2[#Headers],0)))} -> 0.12223728 | F14: {=MEDIAN(_xlfn.CHOOSECOLS(_xlfn._xlws.FILTER(Table2[],Table2[Credit Rating (Acc to lookup table)]=$B14),MATCH("WACC (Weekly)",Table2[#Headers],0)))} -> 0.12052148 | G14: {=AVERAGE(_xlfn.CHOOSECOLS(_xlfn._xlws.FILTER(Table2[],Table2[Credit Rating (Acc to lookup table)]=$B14),MATCH("WACC (Monthly)",Table2[#Headers],0)))} -> 0.13064651 | H14: {=MEDIAN(_xlfn.CHOOSECOLS(_xlfn._xlws.FILTER(Table2[],Table2[Credit Rating (Acc to lookup table)]=$B14),MATCH("WACC (Monthly)",Table2[#Headers],0)))} -> 0.11147414
B15: C2/C | C15: {=AVERAGE(_xlfn.CHOOSECOLS(_xlfn._xlws.FILTER(Table2[],Table2[Credit Rating (Acc to lookup table)]=$B15),MATCH("WACC (Daily)",Table2[#Headers],0)))} -> 0.16563146 | D15: {=MEDIAN(_xlfn.CHOOSECOLS(_xlfn._xlws.FILTER(Table2[],Table2[Credit Rating (Acc to lookup table)]=$B15),MATCH("WACC (Daily)",Table2[#Headers],0)))} -> 0.16716612 | E15: {=AVERAGE(_xlfn.CHOOSECOLS(_xlfn._xlws.FILTER(Table2[],Table2[Credit Rating (Acc to lookup table)]=$B15),MATCH("WACC (Weekly)",Table2[#Headers],0)))} -> 0.17987605 | F15: {=MEDIAN(_xlfn.CHOOSECOLS(_xlfn._xlws.FILTER(Table2[],Table2[Credit Rating (Acc to lookup table)]=$B15),MATCH("WACC (Weekly)",Table2[#Headers],0)))} -> 0.18452423 | G15: {=AVERAGE(_xlfn.CHOOSECOLS(_xlfn._xlws.FILTER(Table2[],Table2[Credit Rating (Acc to lookup table)]=$B15),MATCH("WACC (Monthly)",Table2[#Headers],0)))} -> 0.1721449 | H15: {=MEDIAN(_xlfn.CHOOSECOLS(_xlfn._xlws.FILTER(Table2[],Table2[Credit Rating (Acc to lookup table)]=$B15),MATCH("WACC (Monthly)",Table2[#Headers],0)))} -> 0.18222529
B16: Ca2/CC | C16: {=AVERAGE(_xlfn.CHOOSECOLS(_xlfn._xlws.FILTER(Table2[],Table2[Credit Rating (Acc to lookup table)]=$B16),MATCH("WACC (Daily)",Table2[#Headers],0)))} -> 0.15056541 | D16: {=MEDIAN(_xlfn.CHOOSECOLS(_xlfn._xlws.FILTER(Table2[],Table2[Credit Rating (Acc to lookup table)]=$B16),MATCH("WACC (Daily)",Table2[#Headers],0)))} -> 0.1573065 | E16: {=AVERAGE(_xlfn.CHOOSECOLS(_xlfn._xlws.FILTER(Table2[],Table2[Credit Rating (Acc to lookup table)]=$B16),MATCH("WACC (Weekly)",Table2[#Headers],0)))} -> 0.15994362 | F16: {=MEDIAN(_xlfn.CHOOSECOLS(_xlfn._xlws.FILTER(Table2[],Table2[Credit Rating (Acc to lookup table)]=$B16),MATCH("WACC (Weekly)",Table2[#Headers],0)))} -> 0.1650655 | G16: {=AVERAGE(_xlfn.CHOOSECOLS(_xlfn._xlws.FILTER(Table2[],Table2[Credit Rating (Acc to lookup table)]=$B16),MATCH("WACC (Monthly)",Table2[#Headers],0)))} -> 0.15388649 | H16: {=MEDIAN(_xlfn.CHOOSECOLS(_xlfn._xlws.FILTER(Table2[],Table2[Credit Rating (Acc to lookup table)]=$B16),MATCH("WACC (Monthly)",Table2[#Headers],0)))} -> 0.15854315
... B18: D2/D | C18: {=AVERAGE(_xlfn.CHOOSECOLS(_xlfn._xlws.FILTER(Table2[],Table2[Credit Rating (Acc to lookup table)]=$B18),MATCH("WACC (Daily)",Table2[#Headers],0)))} -> 0.16958467 | D18: {=MEDIAN(_xlfn.CHOOSECOLS(_xlfn._xlws.FILTER(Table2[],Table2[Credit Rating (Acc to lookup table)]=$B18),MATCH("WACC (Daily)",Table2[#Headers],0)))} -> 0.1630845 | E18: {=AVERAGE(_xlfn.CHOOSECOLS(_xlfn._xlws.FILTER(Table2[],Table2[Credit Rating (Acc to lookup table)]=$B18),MATCH("WACC (Weekly)",Table2[#Headers],0)))} -> 0.17952928 | F18: {=MEDIAN(_xlfn.CHOOSECOLS(_xlfn._xlws.FILTER(Table2[],Table2[Credit Rating (Acc to lookup table)]=$B18),MATCH("WACC (Weekly)",Table2[#Headers],0)))} -> 0.17787784 | G18: {=AVERAGE(_xlfn.CHOOSECOLS(_xlfn._xlws.FILTER(Table2[],Table2[Credit Rating (Acc to lookup table)]=$B18),MATCH("WACC (Monthly)",Table2[#Headers],0)))} -> 0.17137892 | H18: {=MEDIAN(_xlfn.CHOOSECOLS(_xlfn._xlws.FILTER(Table2[],Table2[Credit Rating (Acc to lookup table)]=$B18),MATCH("WACC (Monthly)",Table2[#Headers],0)))} -> 0.17387837

Sheet Ratings Sheet
A2: For large non-financial service firms | F2: For financial service firms (default spreads are slighty different) | K2: 0.1
A3: If interest coverage ratio is | F3: If long term interest coverage ratio is
A4: > | B4: ≤ to | C4: Rating is | D4: Spread is | F4: greater than | G4: ≤ to | H4: Rating is | I4: Spread is
A5: -100000 | B5: 0.199999 | C5: D2/D | D5: 0.19 | F5: -100000 | G5: 0.049999 | H5: D2/D | I5: 0.19
A6: 0.2 | B6: 0.649999 | C6: C2/C | D6: 0.16 | F6: 0.05 | G6: 0.099999 | H6: C2/C | I6: 0.16
A7: 0.65 | B7: 0.799999 | C7: Ca2/CC | D7: 0.1261 | F7: 0.1 | G7: 0.199999 | H7: Ca2/CC | I7: 0.1261
A8: 0.8 | B8: 1.249999 | C8: Caa/CCC | D8: 0.0885 | F8: 0.2 | G8: 0.299999 | H8: Caa/CCC | I8: 0.0885 | L8: {=_xlfn.CHOOSECOLS(_xlfn._xlws.FILTER(Rating1[],(K2>Rating1[>])*(K2<Rating1[≤ to])),4)} -> 0.19
A9: 1.25 | B9: 1.499999 | C9: B3/B- | D9: 0.0509 | F9: 0.3 | G9: 0.399999 | H9: B3/B- | I9: 0.0509
A10: 1.5 | B10: 1.749999 | C10: B2/B | D10: 0.0321 | F10: 0.4 | G10: 0.499999 | H10: B2/B | I10: 0.0321
A11: 1.75 | B11: 1.999999 | C11: B1/B+ | D11: 0.0275 | F11: 0.5 | G11: 0.599999 | H11: B1/B+ | I11: 0.0275 | L11: {=CHOOSE(1,_xlfn.CHOOSECOLS(_xlfn._xlws.FILTER(Rating1[],(K2>Rating1[>])*(K2<Rating1[≤ to])),4))} -> 0.19
A12: 2 | B12: 2.2499999 | C12: Ba2/BB | D12: 0.0184 | F12: 0.6 | G12: 0.749999 | H12: Ba2/BB | I12: 0.0184
A13: 2.25 | B13: 2.49999 | C13: Ba1/BB+ | D13: 0.0138 | F13: 0.75 | G13: 0.899999 | H13: Ba1/BB+ | I13: 0.0138
A14: 2.5 | B14: 2.999999 | C14: Baa2/BBB | D14: 0.0111 | F14: 0.9 | G14: 1.199999 | H14: Baa2/BBB | I14: 0.0111
A15: 3 | B15: 4.249999 | C15: A3/A- | D15: 0.0089 | F15: 1.2 | G15: 1.49999 | H15: A3/A- | I15: 0.0089
A16: 4.25 | B16: 5.499999 | C16: A2/A | D16: 0.0078 | F16: 1.5 | G16: 1.99999 | H16: A2/A | I16: 0.0078
A17: 5.5 | B17: 6.499999 | C17: A1/A+ | D17: 0.007 | F17: 2 | G17: 2.49999 | H17: A1/A+ | I17: 0.007
A18: 6.5 | B18: 8.499999 | C18: Aa2/AA | D18: 0.0055 | F18: 2.5 | G18: 2.99999 | H18: Aa2/AA | I18: 0.0055
A19: 8.5 | B19: 100000 | C19: Aaa/AAA | D19: 0.004 | F19: 3 | G19: 100000 | H19: Aaa/AAA | I19: 0.004
A21: For smaller and riskier firms
A22: If interest coverage ratio is
A23: greater than | B23: ≤ to | C23: Rating is | D23: Spread is
A24: 7.5 | B24: 9.499999 | C24: A1/A+ | D24: 0.007
A25: 6 | B25: 7.499999 | C25: A2/A | D25: 0.0078
A26: 4.5 | B26: 5.999999 | C26: A3/A- | D26: 0.0089
A27: 9.5 | B27: 12.499999 | C27: Aa2/AA | D27: 0.0055
A28: 12.5 | B28: 100000 | C28: Aaa/AAA | D28: 0.004
A29: 2.5 | B29: 2.999999 | C29: B1/B+ | D29: 0.0275
A30: 2 | B30: 2.499999 | C30: B2/B | D30: 0.0321
A31: 1.5 | B31: 1.999999 | C31: B3/B- | D31: 0.0509
A32: 3.5 | B32: 3.9999999 | C32: Ba1/BB+ | D32: 0.0138
A33: 3 | B33: 3.499999 | C33: Ba2/BB | D33: 0.0184
A34: 4 | B34: 4.499999 | C34: Baa2/BBB | D34: 0.0111
A35: 0.5 | B35: 0.799999 | C35: C2/C | D35: 0.16
... A38: -100000 | B38: 0.499999 | C38: D2/D | D38: 0.19

Sheet Data
A1: Stock | B1: Company_Name | C1: Sector | D1: Industry | E1: Beta_Daily | F1: Beta_Weekly | G1: Beta_Monthly | H1: Interest_Coverage_Ratio | I1: Market_Cap_Cr | J1: Total_Debt_Cr | K1: Total_Cash_Cr
A2: 20MICRONS | B2: 20 Microns Limited | C2: Basic Materials | D2: Other Industrial Metals & Mining | E2: 1.1950363 | F2: 1.37515 | G2: 8.2148172 | H2: 8.3028055 | I2: 589.33535 | J2: 163.3658 | K2: 58.345997
A3: 360ONE | B3: 360 ONE WAM LIMITED | C3: Financial Services | D3: Asset Management | E3: 0.080689656 | F3: 1.3993013 | G3: 1.37515 | H3: 2.5331254 | I3: 43599.246 | J3: 13764.67 | K3: 1279.43
A4: 3IINFOLTD | B4: 3i Infotech Limited | C4: Technology | D4: Information Technology Services | E4: 0.87666415 | F4: 0.26466764 | G4: 0.49989306 | H4: 2.6924198 | I4: 278.36908 | J4: 34.79 | K4: 45.54
A5: 3MINDIA | B5: 3M India Limited | C5: Industrials | D5: Conglomerates | E5: 0.17308839 | F5: 1.8524196 | G5: 0.49379736 | H5: 72.596475 | I5: 38374.461 | J5: 103.3189 | K5: 619.4625
A6: 63MOONS | B6: 63 moons technologies limited | C6: Technology | D6: Software - Application | E6: -0.15835713 | F6: 1.0000104 | G6: 0.051417035 | H6: -81.769139 | I6: 2601.2887 | J6: 5.2994 | K6: 2221.2327
A7: A2ZINFRA | B7: A2Z Infra Engineering Limited | C7: Industrials | D7: Engineering & Construction | E7: 0.22581231 | F7: -0.43872103 | G7: 0.023425999 | H7: 2.4173654 | I7: 288.83656 | J7: 91.293498 | K7: 4.3846
A8: AARTECH | B8: Aartech Solonics Limited | C8: Industrials | D8: Electrical Equipment & Parts | E8: 0.046652556 | F8: 1 | G8: 1.1614304 | H8: 5.1121119 | I8: 132.48247 | J8: 5.4037 | K8: 13.808499
A9: AARTIDRUGS | B9: Aarti Drugs Limited | C9: Healthcare | D9: Drug Manufacturers - Specialty & Generic | E9: 1.5194814 | F9: 0.28231969 | G9: 0.22197648 | H9: 6.9034305 | I9: 3284.5771 | J9: 573.49002 | K9: 24.54
A10: AARTIIND | B10: Aarti Industries Limited | C10: Basic Materials | D10: Specialty Chemicals | E10: 0.069415447 | F10: 0.16926804 | G10: 4.0671447 | H10: 2.3001693 | I10: 14907.051 | J10: 3973 | K10: 169
A11: AARTIPHARM | B11: Aarti Pharmalabs Limited | C11: Healthcare | D11: Drug Manufacturers - Specialty & Generic | E11: -0.064209023 | F11: -0.014474811 | G11: 0.7839485 | H11: 14.410326 | I11: 6287.0749 | J11: 674.72169 | K11: 55.556198
A12: AARVI | B12: Aarvi Encon Limited | C12: Industrials | D12: Staffing & Employment Services | E12: -0.014474811 | F12: 0.7208142 | G12: 0.52632789 | H12: 4.6484342 | I12: 185.80023 | J12: 32.014598 | K12: 22.538
A13: ABAN | B13: Aban Offshore Limited | C13: Energy | D13: Oil & Gas Drilling | E13: 0.59566999 | F13: 0.49983192 | G13: 0.53474434 | H13: 0.19696919 | I13: 123.96795 | J13: 16278.413 | K13: 149.151
... A1915: ZYDUSWELL | B1915: Zydus Wellness Limited | C1915: Consumer Defensive | D1915: Packaged Foods | E1915: 0.63688195 | F1915: 0.90875053 | G1915: 0.62210857 | H1915: 31.931034 | I1915: 12150.49 | J1915: 3042.0001 | K1915: 148.09999
